Workbook
Name _Hlk80188971: 'Exclusions '!$B$5
Name _Hlk81725290: 'Exclusions '!$B$1
Name CensusKnown: [1]Code!$C$9
Name Check0: [1]Code!$C$285
Name Check1: [1]Code!$C$286
Name Check10: [1]Code!$C$295
Name Check11: [1]Code!#REF!
Name Check2: [1]Code!$C$287
Name Check3: [1]Code!$C$288
Name Check4: [1]Code!$C$289
Name Check5: [1]Code!$C$290
Name Check6: [1]Code!$C$291
Name Check7: [1]Code!$C$292
Name Check8: [1]Code!$C$293
Name Check9: [1]Code!$C$294
Name CoIns10: [1]Code!$D$66
Name CoIns20: [1]Code!$D$67
Name CoInsDiscount: [1]Code!$D$155
Name CompLoad: [1]Code!$D$159
Name currency: [1]Code!$C$4
Name Data_SOS: [1]Data!$G$3
Name Dental: [1]Code!$D$98
Name DentalLimit: [1]Code!$C$100
Name eff_date: [2]Inputs!$C$17
Name end_date: [2]Inputs!$C$18
Name FlatLoad: [1]Code!$D$153
Name FlatTariff: [1]Code!$C$17
Name Individual: [1]Code!$C$7
Name InNo: [1]Code!$A$166
Name INonly: [1]Code!$C$43
Name INPlan: [1]Code!$C$13
Name InputIntSOS: [1]Code!$D$73
Name IntSOS: [1]Code!$C$74
Name Limit: [1]Code!$C$29
Name Limit_Factor: [1]Code!$D$144
Name LoadIN: [1]Code!$D$150
Name Loadings: [2]Inputs!$H$18
Name LoadInOnly: [1]Code!$D$148
Name LoadOUT: [1]Code!$D$151
Name MarriedGirlsRatio: [1]Code!$C$242
Name MarriedRatio: [1]Code!$C$241
Name Maternity: [1]Code!$D$79
Name NK: [1]Code!$C$182
Name NRP_dental: [1]Code!$C$170
Name NRP_optical: [1]Code!$C$171
Name optical: [1]Code!$D$116
Name OUTNo: [1]Code!$A$168
Name OUTPlan: [1]Code!$C$62
Name Plans_AUH: '[2]Inputs Mapping'!$A$12:$A$14
Name plans_dxb_new: '[2]Inputs Mapping'!$A$4:$A$8
Name SizeLoad: [1]Code!$D$146
Name SOAP10: [1]Code!$D$70
Name SOAP10Discount: [1]Code!$D$157
Name TotalMembers: [1]Code!$C$222
Name version: [1]Code!$D$1

Sheet Premium working
G1: NGI Fee | H1: 0.12 | K1: 45630
D2: NRP increase for the AUH plan Classic - 04 in line with AUH min premium | G2: TPA | H2: 0 | K2: Male Premium - 10% Increased | L2: * Additional Premium for New DHA Benefits | Q2: Dental Premium
G3: Commission | H3: ='Census List'!E28 -> 0.05 | K3: Female Premium - 20% Increased | L3: AED - 173/- For HN Exclusive , Premier & Advantage Network | Q3: TPA | R3: Location | S3: Plan Name | T3: for premium on census | U3: Gross | V3: NRP
H4: =SUM(H1:H3) -> 0.17 | L4: AED - 89/- For HN Standard Plus , Standard & Basic Plus | Q4: Healthnet | R4: Dubai | S4: Prime Plan-1 | T4: =+CONCATENATE(Q4," ",S4," ",R4) -> Healthnet Prime Plan-1 Dubai | U4: =V4/(1-$H$4) -> 506 | V4: 420
A5: TPA | B5: Location | C5: Plans | D5: Age Band | E5: Gender | F5: for premium on Census | G5: Unique ID | H5: Gross Rate | I5: PA | J5: NRP | K5: Revised NRP-04/12/2024 | L5: *Additional Premium | M5: Revised NRP+PA+New DHA benefits | N5: Network | O5: Plans | Q5: Healthnet | R5: Dubai | S5: Prime Plan-2 | T5: =+CONCATENATE(Q5," ",S5," ",R5) -> Healthnet Prime Plan-2 Dubai | U5: =V5/(1-$H$4) -> 422 | V5: 350
A6: Healthnet | B6: Dubai | C6: Prime Plan-1 | D6: 00-17 | E6: Male | F6: =+CONCATENATE(A6," ",C6," ",B6," ",D6," ",E6) -> Healthnet Prime Plan-1 Dubai 00-17 Male | G6: =CONCATENATE(C6," ",D6," ",E6) -> Prime Plan-1 00-17 Male | H6: =ROUND(M6/(1-$H$4),0) -> 6946 | I6: 54.6 | J6: 5034 | K6: =J6+(J6*10%) -> 5537 | L6: 173 | M6: =L6+K6+I6 -> 5765 | N6: HN Exclusive | Q6: Healthnet | R6: Dubai | S6: Classic Plan-1 | T6: =+CONCATENATE(Q6," ",S6," ",R6) -> Healthnet Classic Plan-1 Dubai | U6: =V6/(1-$H$4) -> 422 | V6: 350
A7: Healthnet | B7: Dubai | C7: Prime Plan-1 | D7: 18-35 | E7: Male | F7: =+CONCATENATE(A7," ",C7," ",B7," ",D7," ",E7) -> Healthnet Prime Plan-1 Dubai 18-35 Male | G7: =CONCATENATE(C7," ",D7," ",E7) -> Prime Plan-1 18-35 Male | H7: =ROUND(M7/(1-$H$4),0) -> 8028 | I7: 54.6 | J7: 5850 | K7: =J7+(J7*10%) -> 6435 | L7: 173 | M7: =L7+K7+I7 -> 6663 | N7: HN Exclusive | Q7: Healthnet | R7: Dubai | S7: Classic Plan-2 | T7: =+CONCATENATE(Q7," ",S7," ",R7) -> Healthnet Classic Plan-2 Dubai | U7: =V7/(1-$H$4) -> 361 | V7: 300
A8: Healthnet | B8: Dubai | C8: Prime Plan-1 | D8: 36-45 | E8: Male | F8: =+CONCATENATE(A8," ",C8," ",B8," ",D8," ",E8) -> Healthnet Prime Plan-1 Dubai 36-45 Male | G8: =CONCATENATE(C8," ",D8," ",E8) -> Prime Plan-1 36-45 Male | H8: =ROUND(M8/(1-$H$4),0) -> 9508 | I8: 54.6 | J8: 6967 | K8: =J8+(J8*10%) -> 7664 | L8: 173 | M8: =L8+K8+I8 -> 7892 | N8: HN Exclusive | Q8: Healthnet | R8: Dubai | S8: Classic Plan-3 | T8: =+CONCATENATE(Q8," ",S8," ",R8) -> Healthnet Classic Plan-3 Dubai | U8: =V8/(1-$H$4) -> 361 | V8: 300
A9: Healthnet | B9: Dubai | C9: Prime Plan-1 | D9: 46-55 | E9: Male | F9: =+CONCATENATE(A9," ",C9," ",B9," ",D9," ",E9) -> Healthnet Prime Plan-1 Dubai 46-55 Male | G9: =CONCATENATE(C9," ",D9," ",E9) -> Prime Plan-1 46-55 Male | H9: =ROUND(M9/(1-$H$4),0) -> 16543 | I9: 54.6 | J9: 12275 | K9: =J9+(J9*10%) -> 13503 | L9: 173 | M9: =L9+K9+I9 -> 13731 | N9: HN Exclusive | Q9: Healthnet | R9: Dubai | S9: Classic Plan-4 | T9: =+CONCATENATE(Q9," ",S9," ",R9) -> Healthnet Classic Plan-4 Dubai | U9: =V9/(1-$H$4) -> 361 | V9: 300
A10: Healthnet | B10: Dubai | C10: Prime Plan-1 | D10: 56-59 | E10: Male | F10: =+CONCATENATE(A10," ",C10," ",B10," ",D10," ",E10) -> Healthnet Prime Plan-1 Dubai 56-59 Male | G10: =CONCATENATE(C10," ",D10," ",E10) -> Prime Plan-1 56-59 Male | H10: =ROUND(M10/(1-$H$4),0) -> 20589 | I10: 54.6 | J10: 15328 | K10: =J10+(J10*10%) -> 16861 | L10: 173 | M10: =L10+K10+I10 -> 17089 | N10: HN Exclusive | Q10: Healthnet | R10: Dubai | S10: Classic Plan-1R | T10: =+CONCATENATE(Q10," ",S10," ",R10) -> Healthnet Classic Plan-1R Dubai | U10: =V10/(1-$H$4) -> 422 | V10: 350
A11: Healthnet | B11: Dubai | C11: Prime Plan-1 | D11: 60-65 | E11: Male | F11: =+CONCATENATE(A11," ",C11," ",B11," ",D11," ",E11) -> Healthnet Prime Plan-1 Dubai 60-65 Male | G11: =CONCATENATE(C11," ",D11," ",E11) -> Prime Plan-1 60-65 Male | H11: =ROUND(M11/(1-$H$4),0) -> 29765 | I11: 54.6 | J11: 22252 | K11: =J11+(J11*10%) -> 24477 | L11: 173 | M11: =L11+K11+I11 -> 24705 | N11: HN Exclusive | Q11: Healthnet | R11: Dubai | S11: Classic Plan-2R | T11: =+CONCATENATE(Q11," ",S11," ",R11) -> Healthnet Classic Plan-2R Dubai | U11: =V11/(1-$H$4) -> 361 | V11: 300
A12: Healthnet | B12: Dubai | C12: Prime Plan-1 | D12: 66-70 | E12: Male | F12: =+CONCATENATE(A12," ",C12," ",B12," ",D12," ",E12) -> Healthnet Prime Plan-1 Dubai 66-70 Male | G12: =CONCATENATE(C12," ",D12," ",E12) -> Prime Plan-1 66-70 Male | H12: =ROUND(M12/(1-$H$4),0) -> 46581 | I12: 54.6 | J12: 34940 | K12: =J12+(J12*10%) -> 38434 | L12: 173 | M12: =L12+K12+I12 -> 38662 | N12: HN Exclusive | Q12: Healthnet | R12: Dubai | S12: Classic Plan-3R | T12: =+CONCATENATE(Q12," ",S12," ",R12) -> Healthnet Classic Plan-3R Dubai | U12: =V12/(1-$H$4) -> 361 | V12: 300
A13: Healthnet | B13: Dubai | C13: Prime Plan-1 | D13: 00-17 | E13: Female | F13: =+CONCATENATE(A13," ",C13," ",B13," ",D13," ",E13) -> Healthnet Prime Plan-1 Dubai 00-17 Female | G13: =CONCATENATE(C13," ",D13," ",E13) -> Prime Plan-1 00-17 Female | H13: =ROUND(M13/(1-$H$4),0) -> 7917 | I13: 54.6 | J13: 5286 | K13: =J13+(J13*20%) -> 6343 | L13: 173 | M13: =L13+K13+I13 -> 6571 | N13: HN Exclusive | Q13: Healthnet | R13: Dubai | S13: Classic Plan-4R | T13: =+CONCATENATE(Q13," ",S13," ",R13) -> Healthnet Classic Plan-4R Dubai | U13: =V13/(1-$H$4) -> 361 | V13: 300
A14: Healthnet | B14: Dubai | C14: Prime Plan-1 | D14: 18-35 | E14: Female | F14: =+CONCATENATE(A14," ",C14," ",B14," ",D14," ",E14) -> Healthnet Prime Plan-1 Dubai 18-35 Female | G14: =CONCATENATE(C14," ",D14," ",E14) -> Prime Plan-1 18-35 Female | H14: =ROUND(M14/(1-$H$4),0) -> 9158 | I14: 54.6 | J14: 6144 | K14: =J14+(J14*20%) -> 7373 | L14: 173 | M14: =L14+K14+I14 -> 7601 | N14: HN Exclusive | Q14: Healthnet | R14: Abu Dhabi | S14: Prime Plan-1-AUH | T14: =+CONCATENATE(Q14," ",S14," ",R14) -> Healthnet Prime Plan-1-AUH Abu Dhabi | U14: =V14/(1-$H$4) -> 506 | V14: 420
A15: Healthnet | B15: Dubai | C15: Prime Plan-1 | D15: 36-45 | E15: Female | F15: =+CONCATENATE(A15," ",C15," ",B15," ",D15," ",E15) -> Healthnet Prime Plan-1 Dubai 36-45 Female | G15: =CONCATENATE(C15," ",D15," ",E15) -> Prime Plan-1 36-45 Female | H15: =ROUND(M15/(1-$H$4),0) -> 10852 | I15: 54.6 | J15: 7316 | K15: =J15+(J15*20%) -> 8779 | L15: 173 | M15: =L15+K15+I15 -> 9007 | N15: HN Exclusive | Q15: Healthnet | R15: Abu Dhabi | S15: Prime Plan-2-AUH | T15: =+CONCATENATE(Q15," ",S15," ",R15) -> Healthnet Prime Plan-2-AUH Abu Dhabi | U15: =V15/(1-$H$4) -> 422 | V15: 350
A16: Healthnet | B16: Dubai | C16: Prime Plan-1 | D16: 46-55 | E16: Female | F16: =+CONCATENATE(A16," ",C16," ",B16," ",D16," ",E16) -> Healthnet Prime Plan-1 Dubai 46-55 Female | G16: =CONCATENATE(C16," ",D16," ",E16) -> Prime Plan-1 46-55 Female | H16: =ROUND(M16/(1-$H$4),0) -> 20554 | I16: 54.6 | J16: 14027 | K16: =J16+(J16*20%) -> 16832 | L16: 173 | M16: =L16+K16+I16 -> 17060 | N16: HN Exclusive | Q16: Healthnet | R16: Abu Dhabi | S16: Classic Plan-1-AUH | T16: =+CONCATENATE(Q16," ",S16," ",R16) -> Healthnet Classic Plan-1-AUH Abu Dhabi | U16: =V16/(1-$H$4) -> 422 | V16: 350
A17: Healthnet | B17: Dubai | C17: Prime Plan-1 | D17: 56-59 | E17: Female | F17: =+CONCATENATE(A17," ",C17," ",B17," ",D17," ",E17) -> Healthnet Prime Plan-1 Dubai 56-59 Female | G17: =CONCATENATE(C17," ",D17," ",E17) -> Prime Plan-1 56-59 Female | H17: =ROUND(M17/(1-$H$4),0) -> 25848 | I17: 54.6 | J17: 17688 | K17: =J17+(J17*20%) -> 21226 | L17: 173 | M17: =L17+K17+I17 -> 21454 | N17: HN Exclusive | Q17: Healthnet | R17: Abu Dhabi | S17: Classic Plan-2-AUH | T17: =+CONCATENATE(Q17," ",S17," ",R17) -> Healthnet Classic Plan-2-AUH Abu Dhabi | U17: =V17/(1-$H$4) -> 361 | V17: 300
A18: Healthnet | B18: Dubai | C18: Prime Plan-1 | D18: 60-65 | E18: Female | F18: =+CONCATENATE(A18," ",C18," ",B18," ",D18," ",E18) -> Healthnet Prime Plan-1 Dubai 60-65 Female | G18: =CONCATENATE(C18," ",D18," ",E18) -> Prime Plan-1 60-65 Female | H18: =ROUND(M18/(1-$H$4),0) -> 34054 | I18: 54.6 | J18: 23364 | K18: =J18+(J18*20%) -> 28037 | L18: 173 | M18: =L18+K18+I18 -> 28265 | N18: HN Exclusive | Q18: Healthnet | R18: Abu Dhabi | S18: Classic Plan-3-AUH | T18: =+CONCATENATE(Q18," ",S18," ",R18) -> Healthnet Classic Plan-3-AUH Abu Dhabi | U18: =V18/(1-$H$4) -> 361 | V18: 300
A19: Healthnet | B19: Dubai | C19: Prime Plan-1 | D19: 66-70 | E19: Female | F19: =+CONCATENATE(A19," ",C19," ",B19," ",D19," ",E19) -> Healthnet Prime Plan-1 Dubai 66-70 Female | G19: =CONCATENATE(C19," ",D19," ",E19) -> Prime Plan-1 66-70 Female | H19: =ROUND(M19/(1-$H$4),0) -> 53318 | I19: 54.6 | J19: 36688 | K19: =J19+(J19*20%) -> 44026 | L19: 173 | M19: =L19+K19+I19 -> 44254 | N19: HN Exclusive | Q19: Healthnet | R19: Abu Dhabi | S19: Classic Plan-4-AUH | T19: =+CONCATENATE(Q19," ",S19," ",R19) -> Healthnet Classic Plan-4-AUH Abu Dhabi | U19: =V19/(1-$H$4) -> 361 | V19: 300
A20: Healthnet | B20: Dubai | C20: Prime Plan-2 | D20: 00-17 | E20: Male | F20: =+CONCATENATE(A20," ",C20," ",B20," ",D20," ",E20) -> Healthnet Prime Plan-2 Dubai 00-17 Male | G20: =CONCATENATE(C20," ",D20," ",E20) -> Prime Plan-2 00-17 Male | H20: =ROUND(M20/(1-$H$4),0) -> 5835 | I20: 54.6 | J20: 4195 | K20: =J20+(J20*10%) -> 4615 | L20: 173 | M20: =L20+K20+I20 -> 4843 | N20: HN Premier
A21: Healthnet | B21: Dubai | C21: Prime Plan-2 | D21: 18-35 | E21: Male | F21: =+CONCATENATE(A21," ",C21," ",B21," ",D21," ",E21) -> Healthnet Prime Plan-2 Dubai 18-35 Male | G21: =CONCATENATE(C21," ",D21," ",E21) -> Prime Plan-2 18-35 Male | H21: =ROUND(M21/(1-$H$4),0) -> 6736 | I21: 54.6 | J21: 4875 | K21: =J21+(J21*10%) -> 5363 | L21: 173 | M21: =L21+K21+I21 -> 5591 | N21: HN Premier
A22: Healthnet | B22: Dubai | C22: Prime Plan-2 | D22: 36-45 | E22: Male | F22: =+CONCATENATE(A22," ",C22," ",B22," ",D22," ",E22) -> Healthnet Prime Plan-2 Dubai 36-45 Male | G22: =CONCATENATE(C22," ",D22," ",E22) -> Prime Plan-2 36-45 Male | H22: =ROUND(M22/(1-$H$4),0) -> 7970 | I22: 54.6 | J22: 5806 | K22: =J22+(J22*10%) -> 6387 | L22: 173 | M22: =L22+K22+I22 -> 6615 | N22: HN Premier
A23: Healthnet | B23: Dubai | C23: Prime Plan-2 | D23: 46-55 | E23: Male | F23: =+CONCATENATE(A23," ",C23," ",B23," ",D23," ",E23) -> Healthnet Prime Plan-2 Dubai 46-55 Male | G23: =CONCATENATE(C23," ",D23," ",E23) -> Prime Plan-2 46-55 Male | H23: =ROUND(M23/(1-$H$4),0) -> 13831 | I23: 54.6 | J23: 10229 | K23: =J23+(J23*10%) -> 11252 | L23: 173 | M23: =L23+K23+I23 -> 11480 | N23: HN Premier
A24: Healthnet | B24: Dubai | C24: Prime Plan-2 | D24: 56-59 | E24: Male | F24: =+CONCATENATE(A24," ",C24," ",B24," ",D24," ",E24) -> Healthnet Prime Plan-2 Dubai 56-59 Male | G24: =CONCATENATE(C24," ",D24," ",E24) -> Prime Plan-2 56-59 Male | H24: =ROUND(M24/(1-$H$4),0) -> 17202 | I24: 54.6 | J24: 12773 | K24: =J24+(J24*10%) -> 14050 | L24: 173 | M24: =L24+K24+I24 -> 14278 | N24: HN Premier
A25: Healthnet | B25: Dubai | C25: Prime Plan-2 | D25: 60-65 | E25: Male | F25: =+CONCATENATE(A25," ",C25," ",B25," ",D25," ",E25) -> Healthnet Prime Plan-2 Dubai 60-65 Male | G25: =CONCATENATE(C25," ",D25," ",E25) -> Prime Plan-2 60-65 Male | H25: =ROUND(M25/(1-$H$4),0) -> 24849 | I25: 54.6 | J25: 18543 | K25: =J25+(J25*10%) -> 20397 | L25: 173 | M25: =L25+K25+I25 -> 20625 | N25: HN Premier
A26: Healthnet | B26: Dubai | C26: Prime Plan-2 | D26: 66-70 | E26: Male | F26: =+CONCATENATE(A26," ",C26," ",B26," ",D26," ",E26) -> Healthnet Prime Plan-2 Dubai 66-70 Male | G26: =CONCATENATE(C26," ",D26," ",E26) -> Prime Plan-2 66-70 Male | H26: =ROUND(M26/(1-$H$4),0) -> 38864 | I26: 54.6 | J26: 29117 | K26: =J26+(J26*10%) -> 32029 | L26: 173 | M26: =L26+K26+I26 -> 32257 | N26: HN Premier
A27: Healthnet | B27: Dubai | C27: Prime Plan-2 | D27: 00-17 | E27: Female | F27: =+CONCATENATE(A27," ",C27," ",B27," ",D27," ",E27) -> Healthnet Prime Plan-2 Dubai 00-17 Female | G27: =CONCATENATE(C27," ",D27," ",E27) -> Prime Plan-2 00-17 Female | H27: =ROUND(M27/(1-$H$4),0) -> 6643 | I27: 54.6 | J27: 4405 | K27: =J27+(J27*20%) -> 5286 | L27: 173 | M27: =L27+K27+I27 -> 5514 | N27: HN Premier
A28: Healthnet | B28: Dubai | C28: Prime Plan-2 | D28: 18-35 | E28: Female | F28: =+CONCATENATE(A28," ",C28," ",B28," ",D28," ",E28) -> Healthnet Prime Plan-2 Dubai 18-35 Female | G28: =CONCATENATE(C28," ",D28," ",E28) -> Prime Plan-2 18-35 Female | H28: =ROUND(M28/(1-$H$4),0) -> 7677 | I28: 54.6 | J28: 5120 | K28: =J28+(J28*20%) -> 6144 | L28: 173 | M28: =L28+K28+I28 -> 6372 | N28: HN Premier
A29: Healthnet | B29: Dubai | C29: Prime Plan-2 | D29: 36-45 | E29: Female | F29: =+CONCATENATE(A29," ",C29," ",B29," ",D29," ",E29) -> Healthnet Prime Plan-2 Dubai 36-45 Female | G29: =CONCATENATE(C29," ",D29," ",E29) -> Prime Plan-2 36-45 Female | H29: =ROUND(M29/(1-$H$4),0) -> 9089 | I29: 54.6 | J29: 6097 | K29: =J29+(J29*20%) -> 7316 | L29: 173 | M29: =L29+K29+I29 -> 7544 | N29: HN Premier
A30: Healthnet | B30: Dubai | C30: Prime Plan-2 | D30: 46-55 | E30: Female | F30: =+CONCATENATE(A30," ",C30," ",B30," ",D30," ",E30) -> Healthnet Prime Plan-2 Dubai 46-55 Female | G30: =CONCATENATE(C30," ",D30," ",E30) -> Prime Plan-2 46-55 Female | H30: =ROUND(M30/(1-$H$4),0) -> 17175 | I30: 54.6 | J30: 11689 | K30: =J30+(J30*20%) -> 14027 | L30: 173 | M30: =L30+K30+I30 -> 14255 | N30: HN Premier | X30: Age Band | Y30: Gender | Z30: Network | AA30: NRP - R | AB30: NRP - Classic - Open
A31: Healthnet | B31: Dubai | C31: Prime Plan-2 | D31: 56-59 | E31: Female | F31: =+CONCATENATE(A31," ",C31," ",B31," ",D31," ",E31) -> Healthnet Prime Plan-2 Dubai 56-59 Female | G31: =CONCATENATE(C31," ",D31," ",E31) -> Prime Plan-2 56-59 Female | H31: =ROUND(M31/(1-$H$4),0) -> 21586 | I31: 54.6 | J31: 14740 | K31: =J31+(J31*20%) -> 17688 | L31: 173 | M31: =L31+K31+I31 -> 17916 | N31: HN Premier | X31: 00-17 | Y31: Male | Z31: HN Exclusive | AA31: =AA45+(AA45*20%) -> 4840 | AB31: =AA31+(AA31*$AC$34) -> 4840 | AC31: 0.15
A32: Healthnet | B32: Dubai | C32: Prime Plan-2 | D32: 60-65 | E32: Female | F32: =+CONCATENATE(A32," ",C32," ",B32," ",D32," ",E32) -> Healthnet Prime Plan-2 Dubai 60-65 Female | G32: =CONCATENATE(C32," ",D32," ",E32) -> Prime Plan-2 60-65 Female | H32: =ROUND(M32/(1-$H$4),0) -> 28424 | I32: 54.6 | J32: 19470 | K32: =J32+(J32*20%) -> 23364 | L32: 173 | M32: =L32+K32+I32 -> 23592 | N32: HN Premier | X32: 18-35 | Y32: Male | AA32: =AA46+(AA46*20%) -> 5549 | AB32: =AA32+(AA32*$AC$34) -> 5549
A33: Healthnet | B33: Dubai | C33: Prime Plan-2 | D33: 66-70 | E33: Female | F33: =+CONCATENATE(A33," ",C33," ",B33," ",D33," ",E33) -> Healthnet Prime Plan-2 Dubai 66-70 Female | G33: =CONCATENATE(C33," ",D33," ",E33) -> Prime Plan-2 66-70 Female | H33: =ROUND(M33/(1-$H$4),0) -> 44477 | I33: 54.6 | J33: 30573 | K33: =J33+(J33*20%) -> 36688 | L33: 173 | M33: =L33+K33+I33 -> 36916 | N33: HN Premier | X33: 36-45 | Y33: Male | AA33: =AA47+(AA47*20%) -> 6521 | AB33: =AA33+(AA33*$AC$34) -> 6521
A34: Healthnet | B34: Dubai | C34: Classic Plan-1 | D34: 00-17 | E34: Male | F34: =+CONCATENATE(A34," ",C34," ",B34," ",D34," ",E34) -> Healthnet Classic Plan-1 Dubai 00-17 Male | G34: =CONCATENATE(C34," ",D34," ",E34) -> Classic Plan-1 00-17 Male | H34: =ROUND(M34/(1-$H$4),0) -> 4877 | I34: 54.6 | J34: 3473 | K34: =J34+(J34*10%) -> 3820 | L34: 173 | M34: =L34+K34+I34 -> 4048 | N34: HN Advantage | X34: 46-55 | Y34: Male | AA34: =AA48+(AA48*20%) -> 11136 | AB34: =AA34+(AA34*$AC$34) -> 11136
A35: Healthnet | B35: Dubai | C35: Classic Plan-1 | D35: 18-35 | E35: Male | F35: =+CONCATENATE(A35," ",C35," ",B35," ",D35," ",E35) -> Healthnet Classic Plan-1 Dubai 18-35 Male | G35: =CONCATENATE(C35," ",D35," ",E35) -> Classic Plan-1 18-35 Male | H35: =ROUND(M35/(1-$H$4),0) -> 5623 | I35: 54.6 | J35: 4035 | K35: =J35+(J35*10%) -> 4439 | L35: 173 | M35: =L35+K35+I35 -> 4667 | N35: HN Advantage | X35: 56-59 | Y35: Male | AA35: =AA49+(AA49*20%) -> 13790 | AB35: =AA35+(AA35*$AC$34) -> 13790
A36: Healthnet | B36: Dubai | C36: Classic Plan-1 | D36: 36-45 | E36: Male | F36: =+CONCATENATE(A36," ",C36," ",B36," ",D36," ",E36) -> Healthnet Classic Plan-1 Dubai 36-45 Male | G36: =CONCATENATE(C36," ",D36," ",E36) -> Classic Plan-1 36-45 Male | H36: =ROUND(M36/(1-$H$4),0) -> 6646 | I36: 54.6 | J36: 4807 | K36: =J36+(J36*10%) -> 5288 | L36: 173 | M36: =L36+K36+I36 -> 5516 | N36: HN Advantage | X36: 60 - 65 | Y36: Male | AA36: =AA50+(AA50*20%) -> 19811 | AB36: =AA36+(AA36*$AC$34) -> 19811
A37: Healthnet | B37: Dubai | C37: Classic Plan-1 | D37: 46-55 | E37: Male | F37: =+CONCATENATE(A37," ",C37," ",B37," ",D37," ",E37) -> Healthnet Classic Plan-1 Dubai 46-55 Male | G37: =CONCATENATE(C37," ",D37," ",E37) -> Classic Plan-1 46-55 Male | H37: =ROUND(M37/(1-$H$4),0) -> 11498 | I37: 54.6 | J37: 8468 | K37: =J37+(J37*10%) -> 9315 | L37: 173 | M37: =L37+K37+I37 -> 9543 | N37: HN Advantage | X37: 66 and above | Y37: Male | AA37: =AA51+(AA51*20%) -> 30845 | AB37: =AA37+(AA37*$AC$34) -> 30845
A38: Healthnet | B38: Dubai | C38: Classic Plan-1 | D38: 56-59 | E38: Male | F38: =+CONCATENATE(A38," ",C38," ",B38," ",D38," ",E38) -> Healthnet Classic Plan-1 Dubai 56-59 Male | G38: =CONCATENATE(C38," ",D38," ",E38) -> Classic Plan-1 56-59 Male | H38: =ROUND(M38/(1-$H$4),0) -> 14288 | I38: 54.6 | J38: 10574 | K38: =J38+(J38*10%) -> 11631 | L38: 173 | M38: =L38+K38+I38 -> 11859 | N38: HN Advantage | X38: 00-17 | Y38: Female | AA38: =AA52+(AA52*20%) -> 5081 | AB38: =AA38+(AA38*$AC$34) -> 5081
A39: Healthnet | B39: Dubai | C39: Classic Plan-1 | D39: 60-65 | E39: Male | F39: =+CONCATENATE(A39," ",C39," ",B39," ",D39," ",E39) -> Healthnet Classic Plan-1 Dubai 60-65 Male | G39: =CONCATENATE(C39," ",D39," ",E39) -> Classic Plan-1 60-65 Male | H39: =ROUND(M39/(1-$H$4),0) -> 20618 | I39: 54.6 | J39: 15350 | K39: =J39+(J39*10%) -> 16885 | L39: 173 | M39: =L39+K39+I39 -> 17113 | N39: HN Advantage | X39: 18-35 | Y39: Female | AA39: =AA53+(AA53*20%) -> 8202 | AB39: =AA39+(AA39*$AC$34) -> 8202
A40: Healthnet | B40: Dubai | C40: Classic Plan-1 | D40: 66-70 | E40: Male | F40: =+CONCATENATE(A40," ",C40," ",B40," ",D40," ",E40) -> Healthnet Classic Plan-1 Dubai 66-70 Male | G40: =CONCATENATE(C40," ",D40," ",E40) -> Classic Plan-1 66-70 Male | H40: =ROUND(M40/(1-$H$4),0) -> 32219 | I40: 54.6 | J40: 24104 | K40: =J40+(J40*10%) -> 26514 | L40: 173 | M40: =L40+K40+I40 -> 26742 | N40: HN Advantage | X40: 36-45 | Y40: Female | AA40: =AA54+(AA54*20%) -> 9223 | AB40: =AA40+(AA40*$AC$34) -> 9223
A41: Healthnet | B41: Dubai | C41: Classic Plan-1 | D41: 00-17 | E41: Female | F41: =+CONCATENATE(A41," ",C41," ",B41," ",D41," ",E41) -> Healthnet Classic Plan-1 Dubai 00-17 Female | G41: =CONCATENATE(C41," ",D41," ",E41) -> Classic Plan-1 00-17 Female | H41: =ROUND(M41/(1-$H$4),0) -> 5547 | I41: 54.6 | J41: 3647 | K41: =J41+(J41*20%) -> 4376 | L41: 173 | M41: =L41+K41+I41 -> 4604 | N41: HN Advantage | X41: 46-55 | Y41: Female | AA41: =AA55+(AA55*20%) -> 12683 | AB41: =AA41+(AA41*$AC$34) -> 12683
A42: Healthnet | B42: Dubai | C42: Classic Plan-1 | D42: 18-35 | E42: Female | F42: =+CONCATENATE(A42," ",C42," ",B42," ",D42," ",E42) -> Healthnet Classic Plan-1 Dubai 18-35 Female | G42: =CONCATENATE(C42," ",D42," ",E42) -> Classic Plan-1 18-35 Female | H42: =ROUND(M42/(1-$H$4),0) -> 6402 | I42: 54.6 | J42: 4238 | K42: =J42+(J42*20%) -> 5086 | L42: 173 | M42: =L42+K42+I42 -> 5314 | N42: HN Advantage | X42: 56-59 | Y42: Female | AA42: =AA56+(AA56*20%) -> 15865 | AB42: =AA42+(AA42*$AC$34) -> 15865
A43: Healthnet | B43: Dubai | C43: Classic Plan-1 | D43: 36-45 | E43: Female | F43: =+CONCATENATE(A43," ",C43," ",B43," ",D43," ",E43) -> Healthnet Classic Plan-1 Dubai 36-45 Female | G43: =CONCATENATE(C43," ",D43," ",E43) -> Classic Plan-1 36-45 Female | H43: =ROUND(M43/(1-$H$4),0) -> 7573 | I43: 54.6 | J43: 5048 | K43: =J43+(J43*20%) -> 6058 | L43: 173 | M43: =L43+K43+I43 -> 6286 | N43: HN Advantage | X43: 60 - 65 | Y43: Female | AA43: =AA57+(AA57*20%) -> 20801 | AB43: =AA43+(AA43*$AC$34) -> 20801
A44: Healthnet | B44: Dubai | C44: Classic Plan-1 | D44: 46-55 | E44: Female | F44: =+CONCATENATE(A44," ",C44," ",B44," ",D44," ",E44) -> Healthnet Classic Plan-1 Dubai 46-55 Female | G44: =CONCATENATE(C44," ",D44," ",E44) -> Classic Plan-1 46-55 Female | H44: =ROUND(M44/(1-$H$4),0) -> 14264 | I44: 54.6 | J44: 9676 | K44: =J44+(J44*20%) -> 11611 | L44: 173 | M44: =L44+K44+I44 -> 11839 | N44: HN Advantage | X44: 66 and above | Y44: Female | AA44: =AA58+(AA58*20%) -> 32387 | AB44: =AA44+(AA44*$AC$34) -> 32387
A45: Healthnet | B45: Dubai | C45: Classic Plan-1 | D45: 56-59 | E45: Female | F45: =+CONCATENATE(A45," ",C45," ",B45," ",D45," ",E45) -> Healthnet Classic Plan-1 Dubai 56-59 Female | G45: =CONCATENATE(C45," ",D45," ",E45) -> Classic Plan-1 56-59 Female | H45: =ROUND(M45/(1-$H$4),0) -> 17914 | I45: 54.6 | J45: 12201 | K45: =J45+(J45*20%) -> 14641 | L45: 173 | M45: =L45+K45+I45 -> 14869 | N45: HN Advantage | X45: 00-17 | Y45: Male | Z45: HN Premier | AA45: 4033 | AB45: =AA45+(AA45*$AC$48) -> 4033 | AC45: 0.12
A46: Healthnet | B46: Dubai | C46: Classic Plan-1 | D46: 60-65 | E46: Female | F46: =+CONCATENATE(A46," ",C46," ",B46," ",D46," ",E46) -> Healthnet Classic Plan-1 Dubai 60-65 Female | G46: =CONCATENATE(C46," ",D46," ",E46) -> Classic Plan-1 60-65 Female | H46: =ROUND(M46/(1-$H$4),0) -> 23578 | I46: 54.6 | J46: 16118 | K46: =J46+(J46*20%) -> 19342 | L46: 173 | M46: =L46+K46+I46 -> 19570 | N46: HN Advantage | X46: 18-35 | Y46: Male | AA46: 4624 | AB46: =AA46+(AA46*$AC$48) -> 4624
A47: Healthnet | B47: Dubai | C47: Classic Plan-1 | D47: 66-70 | E47: Female | F47: =+CONCATENATE(A47," ",C47," ",B47," ",D47," ",E47) -> Healthnet Classic Plan-1 Dubai 66-70 Female | G47: =CONCATENATE(C47," ",D47," ",E47) -> Classic Plan-1 66-70 Female | H47: =ROUND(M47/(1-$H$4),0) -> 36866 | I47: 54.6 | J47: 25309 | K47: =J47+(J47*20%) -> 30371 | L47: 173 | M47: =L47+K47+I47 -> 30599 | N47: HN Advantage | X47: 36-45 | Y47: Male | AA47: 5434 | AB47: =AA47+(AA47*$AC$48) -> 5434
A48: Healthnet | B48: Dubai | C48: Classic Plan-2 | D48: 00-17 | E48: Male | F48: =+CONCATENATE(A48," ",C48," ",B48," ",D48," ",E48) -> Healthnet Classic Plan-2 Dubai 00-17 Male | G48: =CONCATENATE(C48," ",D48," ",E48) -> Classic Plan-2 00-17 Male | H48: =ROUND(M48/(1-$H$4),0) -> 4229 | I48: 54.6 | J48: 3060 | K48: =J48+(J48*10%) -> 3366 | L48: 89 | M48: =L48+K48+I48 -> 3510 | N48: HN Standard Plus | X48: 46-55 | Y48: Male | AA48: 9280 | AB48: =AA48+(AA48*$AC$48) -> 9280
A49: Healthnet | B49: Dubai | C49: Classic Plan-2 | D49: 18-35 | E49: Male | F49: =+CONCATENATE(A49," ",C49," ",B49," ",D49," ",E49) -> Healthnet Classic Plan-2 Dubai 18-35 Male | G49: =CONCATENATE(C49," ",D49," ",E49) -> Classic Plan-2 18-35 Male | H49: =ROUND(M49/(1-$H$4),0) -> 4439 | I49: 54.6 | J49: 3218 | K49: =J49+(J49*10%) -> 3540 | L49: 89 | M49: =L49+K49+I49 -> 3684 | N49: HN Standard Plus | X49: 56-59 | Y49: Male | AA49: 11492 | AB49: =AA49+(AA49*$AC$48) -> 11492
A50: Healthnet | B50: Dubai | C50: Classic Plan-2 | D50: 36-45 | E50: Male | F50: =+CONCATENATE(A50," ",C50," ",B50," ",D50," ",E50) -> Healthnet Classic Plan-2 Dubai 36-45 Male | G50: =CONCATENATE(C50," ",D50," ",E50) -> Classic Plan-2 36-45 Male | H50: =ROUND(M50/(1-$H$4),0) -> 5318 | I50: 54.6 | J50: 3882 | K50: =J50+(J50*10%) -> 4270 | L50: 89 | M50: =L50+K50+I50 -> 4414 | N50: HN Standard Plus | X50: 60 - 65 | Y50: Male | AA50: 16509 | AB50: =AA50+(AA50*$AC$48) -> 16509
A51: Healthnet | B51: Dubai | C51: Classic Plan-2 | D51: 46-55 | E51: Male | F51: =+CONCATENATE(A51," ",C51," ",B51," ",D51," ",E51) -> Healthnet Classic Plan-2 Dubai 46-55 Male | G51: =CONCATENATE(C51," ",D51," ",E51) -> Classic Plan-2 46-55 Male | H51: =ROUND(M51/(1-$H$4),0) -> 8461 | I51: 54.6 | J51: 6254 | K51: =J51+(J51*10%) -> 6879 | L51: 89 | M51: =L51+K51+I51 -> 7023 | N51: HN Standard Plus | X51: 66 and above | Y51: Male | AA51: 25704 | AB51: =AA51+(AA51*$AC$48) -> 25704
A52: Healthnet | B52: Dubai | C52: Classic Plan-2 | D52: 56-59 | E52: Male | F52: =+CONCATENATE(A52," ",C52," ",B52," ",D52," ",E52) -> Healthnet Classic Plan-2 Dubai 56-59 Male | G52: =CONCATENATE(C52," ",D52," ",E52) -> Classic Plan-2 56-59 Male | H52: =ROUND(M52/(1-$H$4),0) -> 13033 | I52: 54.6 | J52: 9703 | K52: =J52+(J52*10%) -> 10673 | L52: 89 | M52: =L52+K52+I52 -> 10817 | N52: HN Standard Plus | X52: 00-17 | Y52: Female | AA52: 4234 | AB52: =AA52+(AA52*$AC$48) -> 4234
A53: Healthnet | B53: Dubai | C53: Classic Plan-2 | D53: 60-65 | E53: Male | F53: =+CONCATENATE(A53," ",C53," ",B53," ",D53," ",E53) -> Healthnet Classic Plan-2 Dubai 60-65 Male | G53: =CONCATENATE(C53," ",D53," ",E53) -> Classic Plan-2 60-65 Male | H53: =ROUND(M53/(1-$H$4),0) -> 15402 | I53: 54.6 | J53: 11491 | K53: =J53+(J53*10%) -> 12640 | L53: 89 | M53: =L53+K53+I53 -> 12784 | N53: HN Standard Plus | X53: 18-35 | Y53: Female | AA53: 6835 | AB53: =AA53+(AA53*$AC$48) -> 6835
A54: Healthnet | B54: Dubai | C54: Classic Plan-2 | D54: 66-70 | E54: Male | F54: =+CONCATENATE(A54," ",C54," ",B54," ",D54," ",E54) -> Healthnet Classic Plan-2 Dubai 66-70 Male | G54: =CONCATENATE(C54," ",D54," ",E54) -> Classic Plan-2 66-70 Male | H54: =ROUND(M54/(1-$H$4),0) -> 18481 | I54: 54.6 | J54: 13814 | K54: =J54+(J54*10%) -> 15195 | L54: 89 | M54: =L54+K54+I54 -> 15339 | N54: HN Standard Plus | X54: 36-45 | Y54: Female | AA54: 7686 | AB54: =AA54+(AA54*$AC$48) -> 7686
A55: Healthnet | B55: Dubai | C55: Classic Plan-2 | D55: 00-17 | E55: Female | F55: =+CONCATENATE(A55," ",C55," ",B55," ",D55," ",E55) -> Healthnet Classic Plan-2 Dubai 00-17 Female | G55: =CONCATENATE(C55," ",D55," ",E55) -> Classic Plan-2 00-17 Female | H55: =ROUND(M55/(1-$H$4),0) -> 5128 | I55: 54.6 | J55: 3427 | K55: =J55+(J55*20%) -> 4112 | L55: 89 | M55: =L55+K55+I55 -> 4256 | N55: HN Standard Plus | X55: 46-55 | Y55: Female | AA55: 10569 | AB55: =AA55+(AA55*$AC$48) -> 10569
A56: Healthnet | B56: Dubai | C56: Classic Plan-2 | D56: 18-35 | E56: Female | F56: =+CONCATENATE(A56," ",C56," ",B56," ",D56," ",E56) -> Healthnet Classic Plan-2 Dubai 18-35 Female | G56: =CONCATENATE(C56," ",D56," ",E56) -> Classic Plan-2 18-35 Female | H56: =ROUND(M56/(1-$H$4),0) -> 5384 | I56: 54.6 | J56: 3604 | K56: =J56+(J56*20%) -> 4325 | L56: 89 | M56: =L56+K56+I56 -> 4469 | N56: HN Standard Plus | X56: 56-59 | Y56: Female | AA56: 13221 | AB56: =AA56+(AA56*$AC$48) -> 13221
A57: Healthnet | B57: Dubai | C57: Classic Plan-2 | D57: 36-45 | E57: Female | F57: =+CONCATENATE(A57," ",C57," ",B57," ",D57," ",E57) -> Healthnet Classic Plan-2 Dubai 36-45 Female | G57: =CONCATENATE(C57," ",D57," ",E57) -> Classic Plan-2 36-45 Female | H57: =ROUND(M57/(1-$H$4),0) -> 6460 | I57: 54.6 | J57: 4348 | K57: =J57+(J57*20%) -> 5218 | L57: 89 | M57: =L57+K57+I57 -> 5362 | N57: HN Standard Plus | X57: 60 - 65 | Y57: Female | AA57: 17334 | AB57: =AA57+(AA57*$AC$48) -> 17334
A58: Healthnet | B58: Dubai | C58: Classic Plan-2 | D58: 46-55 | E58: Female | F58: =+CONCATENATE(A58," ",C58," ",B58," ",D58," ",E58) -> Healthnet Classic Plan-2 Dubai 46-55 Female | G58: =CONCATENATE(C58," ",D58," ",E58) -> Classic Plan-2 46-55 Female | H58: =ROUND(M58/(1-$H$4),0) -> 10835 | I58: 54.6 | J58: 7374 | K58: =J58+(J58*20%) -> 8849 | L58: 89 | M58: =L58+K58+I58 -> 8993 | N58: HN Standard Plus | X58: 66 and above | Y58: Female | AA58: 26989 | AB58: =AA58+(AA58*$AC$48) -> 26989
A59: Healthnet | B59: Dubai | C59: Classic Plan-2 | D59: 56-59 | E59: Female | F59: =+CONCATENATE(A59," ",C59," ",B59," ",D59," ",E59) -> Healthnet Classic Plan-2 Dubai 56-59 Female | G59: =CONCATENATE(C59," ",D59," ",E59) -> Classic Plan-2 56-59 Female | H59: =ROUND(M59/(1-$H$4),0) -> 15883 | I59: 54.6 | J59: 10866 | K59: =J59+(J59*20%) -> 13039 | L59: 89 | M59: =L59+K59+I59 -> 13183 | N59: HN Standard Plus | X59: 00-17 | Y59: Male | Z59: HN Advantage | AA59: 3428 | AB59: =AA59+(AA59*$AC$62) -> 3428 | AC59: 0.12
A60: Healthnet | B60: Dubai | C60: Classic Plan-2 | D60: 60-65 | E60: Female | F60: =+CONCATENATE(A60," ",C60," ",B60," ",D60," ",E60) -> Healthnet Classic Plan-2 Dubai 60-65 Female | G60: =CONCATENATE(C60," ",D60," ",E60) -> Classic Plan-2 60-65 Female | H60: =ROUND(M60/(1-$H$4),0) -> 16787 | I60: 54.6 | J60: 11491 | K60: =J60+(J60*20%) -> 13789 | L60: 89 | M60: =L60+K60+I60 -> 13933 | N60: HN Standard Plus | X60: 18-35 | Y60: Male | AA60: 3930 | AB60: =AA60+(AA60*$AC$62) -> 3930
A61: Healthnet | B61: Dubai | C61: Classic Plan-2 | D61: 66-70 | E61: Female | F61: =+CONCATENATE(A61," ",C61," ",B61," ",D61," ",E61) -> Healthnet Classic Plan-2 Dubai 66-70 Female | G61: =CONCATENATE(C61," ",D61," ",E61) -> Classic Plan-2 66-70 Female | H61: =ROUND(M61/(1-$H$4),0) -> 20146 | I61: 54.6 | J61: 13814 | K61: =J61+(J61*20%) -> 16577 | L61: 89 | M61: =L61+K61+I61 -> 16721 | N61: HN Standard Plus | X61: 36-45 | Y61: Male | AA61: 4619 | AB61: =AA61+(AA61*$AC$62) -> 4619
A62: Healthnet | B62: Dubai | C62: Classic Plan-3 | D62: 00-17 | E62: Male | F62: =+CONCATENATE(A62," ",C62," ",B62," ",D62," ",E62) -> Healthnet Classic Plan-3 Dubai 00-17 Male | G62: =CONCATENATE(C62," ",D62," ",E62) -> Classic Plan-3 00-17 Male | H62: =ROUND(M62/(1-$H$4),0) -> 3113 | I62: 54.6 | J62: 2218 | K62: =J62+(J62*10%) -> 2440 | L62: 89 | M62: =L62+K62+I62 -> 2584 | N62: HN Standard | X62: 46-55 | Y62: Male | AA62: 7888 | AB62: =AA62+(AA62*$AC$62) -> 7888
A63: Healthnet | B63: Dubai | C63: Classic Plan-3 | D63: 18-35 | E63: Male | F63: =+CONCATENATE(A63," ",C63," ",B63," ",D63," ",E63) -> Healthnet Classic Plan-3 Dubai 18-35 Male | G63: =CONCATENATE(C63," ",D63," ",E63) -> Classic Plan-3 18-35 Male | H63: =ROUND(M63/(1-$H$4),0) -> 3552 | I63: 54.6 | J63: 2549 | K63: =J63+(J63*10%) -> 2804 | L63: 89 | M63: =L63+K63+I63 -> 2948 | N63: HN Standard | X63: 56-59 | Y63: Male | AA63: 9768 | AB63: =AA63+(AA63*$AC$62) -> 9768
A64: Healthnet | B64: Dubai | C64: Classic Plan-3 | D64: 36-45 | E64: Male | F64: =+CONCATENATE(A64," ",C64," ",B64," ",D64," ",E64) -> Healthnet Classic Plan-3 Dubai 36-45 Male | G64: =CONCATENATE(C64," ",D64," ",E64) -> Classic Plan-3 36-45 Male | H64: =ROUND(M64/(1-$H$4),0) -> 4090 | I64: 54.6 | J64: 2955 | K64: =J64+(J64*10%) -> 3251 | L64: 89 | M64: =L64+K64+I64 -> 3395 | N64: HN Standard | X64: 60 - 65 | Y64: Male | AA64: 14033 | AB64: =AA64+(AA64*$AC$62) -> 14033
A65: Healthnet | B65: Dubai | C65: Classic Plan-3 | D65: 46-55 | E65: Male | F65: =+CONCATENATE(A65," ",C65," ",B65," ",D65," ",E65) -> Healthnet Classic Plan-3 Dubai 46-55 Male | G65: =CONCATENATE(C65," ",D65," ",E65) -> Classic Plan-3 46-55 Male | H65: =ROUND(M65/(1-$H$4),0) -> 5928 | I65: 54.6 | J65: 4342 | K65: =J65+(J65*10%) -> 4776 | L65: 89 | M65: =L65+K65+I65 -> 4920 | N65: HN Standard | X65: 66 and above | Y65: Male | AA65: 21848 | AB65: =AA65+(AA65*$AC$62) -> 21848
A66: Healthnet | B66: Dubai | C66: Classic Plan-3 | D66: 56-59 | E66: Male | F66: =+CONCATENATE(A66," ",C66," ",B66," ",D66," ",E66) -> Healthnet Classic Plan-3 Dubai 56-59 Male | G66: =CONCATENATE(C66," ",D66," ",E66) -> Classic Plan-3 56-59 Male | H66: =ROUND(M66/(1-$H$4),0) -> 8112 | I66: 54.6 | J66: 5990 | K66: =J66+(J66*10%) -> 6589 | L66: 89 | M66: =L66+K66+I66 -> 6733 | N66: HN Standard | X66: 00-17 | Y66: Female | AA66: 3599 | AB66: =AA66+(AA66*$AC$62) -> 3599
A67: Healthnet | B67: Dubai | C67: Classic Plan-3 | D67: 60-65 | E67: Male | F67: =+CONCATENATE(A67," ",C67," ",B67," ",D67," ",E67) -> Healthnet Classic Plan-3 Dubai 60-65 Male | G67: =CONCATENATE(C67," ",D67," ",E67) -> Classic Plan-3 60-65 Male | H67: =ROUND(M67/(1-$H$4),0) -> 11043 | I67: 54.6 | J67: 8202 | K67: =J67+(J67*10%) -> 9022 | L67: 89 | M67: =L67+K67+I67 -> 9166 | N67: HN Standard | X67: 18-35 | Y67: Female | AA67: 5810 | AB67: =AA67+(AA67*$AC$62) -> 5810
A68: Healthnet | B68: Dubai | C68: Classic Plan-3 | D68: 66-70 | E68: Male | F68: =+CONCATENATE(A68," ",C68," ",B68," ",D68," ",E68) -> Healthnet Classic Plan-3 Dubai 66-70 Male | G68: =CONCATENATE(C68," ",D68," ",E68) -> Classic Plan-3 66-70 Male | H68: =ROUND(M68/(1-$H$4),0) -> 14575 | I68: 54.6 | J68: 10866 | K68: =J68+(J68*10%) -> 11953 | L68: 89 | M68: =L68+K68+I68 -> 12097 | N68: HN Standard | X68: 36-45 | Y68: Female | AA68: 6533 | AB68: =AA68+(AA68*$AC$62) -> 6533
A69: Healthnet | B69: Dubai | C69: Classic Plan-3 | D69: 00-17 | E69: Female | F69: =+CONCATENATE(A69," ",C69," ",B69," ",D69," ",E69) -> Healthnet Classic Plan-3 Dubai 00-17 Female | G69: =CONCATENATE(C69," ",D69," ",E69) -> Classic Plan-3 00-17 Female | H69: =ROUND(M69/(1-$H$4),0) -> 3540 | I69: 54.6 | J69: 2328 | K69: =J69+(J69*20%) -> 2794 | L69: 89 | M69: =L69+K69+I69 -> 2938 | N69: HN Standard | X69: 46-55 | Y69: Female | AA69: 8984 | AB69: =AA69+(AA69*$AC$62) -> 8984
A70: Healthnet | B70: Dubai | C70: Classic Plan-3 | D70: 18-35 | E70: Female | F70: =+CONCATENATE(A70," ",C70," ",B70," ",D70," ",E70) -> Healthnet Classic Plan-3 Dubai 18-35 Female | G70: =CONCATENATE(C70," ",D70," ",E70) -> Classic Plan-3 18-35 Female | H70: =ROUND(M70/(1-$H$4),0) -> 4042 | I70: 54.6 | J70: 2676 | K70: =J70+(J70*20%) -> 3211 | L70: 89 | M70: =L70+K70+I70 -> 3355 | N70: HN Standard | X70: 56-59 | Y70: Female | AA70: 11238 | AB70: =AA70+(AA70*$AC$62) -> 11238
A71: Healthnet | B71: Dubai | C71: Classic Plan-3 | D71: 36-45 | E71: Female | F71: =+CONCATENATE(A71," ",C71," ",B71," ",D71," ",E71) -> Healthnet Classic Plan-3 Dubai 36-45 Female | G71: =CONCATENATE(C71," ",D71," ",E71) -> Classic Plan-3 36-45 Female | H71: =ROUND(M71/(1-$H$4),0) -> 4658 | I71: 54.6 | J71: 3102 | K71: =J71+(J71*20%) -> 3722 | L71: 89 | M71: =L71+K71+I71 -> 3866 | N71: HN Standard | X71: 60 - 65 | Y71: Female | AA71: 14734 | AB71: =AA71+(AA71*$AC$62) -> 14734
A72: Healthnet | B72: Dubai | C72: Classic Plan-3 | D72: 46-55 | E72: Female | F72: =+CONCATENATE(A72," ",C72," ",B72," ",D72," ",E72) -> Healthnet Classic Plan-3 Dubai 46-55 Female | G72: =CONCATENATE(C72," ",D72," ",E72) -> Classic Plan-3 46-55 Female | H72: =ROUND(M72/(1-$H$4),0) -> 7781 | I72: 54.6 | J72: 5262 | K72: =J72+(J72*20%) -> 6314 | L72: 89 | M72: =L72+K72+I72 -> 6458 | N72: HN Standard | X72: 66 and above | Y72: Female | AA72: 22941 | AB72: =AA72+(AA72*$AC$62) -> 22941
A73: Healthnet | B73: Dubai | C73: Classic Plan-3 | D73: 56-59 | E73: Female | F73: =+CONCATENATE(A73," ",C73," ",B73," ",D73," ",E73) -> Healthnet Classic Plan-3 Dubai 56-59 Female | G73: =CONCATENATE(C73," ",D73," ",E73) -> Classic Plan-3 56-59 Female | H73: =ROUND(M73/(1-$H$4),0) -> 9713 | I73: 54.6 | J73: 6598 | K73: =J73+(J73*20%) -> 7918 | L73: 89 | M73: =L73+K73+I73 -> 8062 | N73: HN Standard | X73: 00-17 | Y73: Male | Z73: HN Standard Plus | AA73: 3062 | AB73: =AA73+(AA73*$AC$76) -> 3062 | AC73: 0.07
A74: Healthnet | B74: Dubai | C74: Classic Plan-3 | D74: 60-65 | E74: Female | F74: =+CONCATENATE(A74," ",C74," ",B74," ",D74," ",E74) -> Healthnet Classic Plan-3 Dubai 60-65 Female | G74: =CONCATENATE(C74," ",D74," ",E74) -> Classic Plan-3 60-65 Female | H74: =ROUND(M74/(1-$H$4),0) -> 12031 | I74: 54.6 | J74: 8202 | K74: =J74+(J74*20%) -> 9842 | L74: 89 | M74: =L74+K74+I74 -> 9986 | N74: HN Standard | X74: 18-35 | Y74: Male | AA74: 3203 | AB74: =AA74+(AA74*$AC$76) -> 3203
A75: Healthnet | B75: Dubai | C75: Classic Plan-3 | D75: 66-70 | E75: Female | F75: =+CONCATENATE(A75," ",C75," ",B75," ",D75," ",E75) -> Healthnet Classic Plan-3 Dubai 66-70 Female | G75: =CONCATENATE(C75," ",D75," ",E75) -> Classic Plan-3 66-70 Female | H75: =ROUND(M75/(1-$H$4),0) -> 15883 | I75: 54.6 | J75: 10866 | K75: =J75+(J75*20%) -> 13039 | L75: 89 | M75: =L75+K75+I75 -> 13183 | N75: HN Standard | X75: 36-45 | Y75: Male | AA75: 3796 | AB75: =AA75+(AA75*$AC$76) -> 3796
A76: Healthnet | B76: Dubai | C76: Classic Plan-4 | D76: 00-17 | E76: Male | F76: =+CONCATENATE(A76," ",C76," ",B76," ",D76," ",E76) -> Healthnet Classic Plan-4 Dubai 00-17 Male | G76: =CONCATENATE(C76," ",D76," ",E76) -> Classic Plan-4 00-17 Male | H76: =ROUND(M76/(1-$H$4),0) -> 2230 | I76: 54.6 | J76: 1552 | K76: =J76+(J76*10%) -> 1707 | L76: 89 | M76: =L76+K76+I76 -> 1851 | N76: HN Basic Plus | X76: 46-55 | Y76: Male | AA76: 5914 | AB76: =AA76+(AA76*$AC$76) -> 5914
A77: Healthnet | B77: Dubai | C77: Classic Plan-4 | D77: 18-35 | E77: Male | F77: =+CONCATENATE(A77," ",C77," ",B77," ",D77," ",E77) -> Healthnet Classic Plan-4 Dubai 18-35 Male | G77: =CONCATENATE(C77," ",D77," ",E77) -> Classic Plan-4 18-35 Male | H77: =ROUND(M77/(1-$H$4),0) -> 2537 | I77: 54.6 | J77: 1784 | K77: =J77+(J77*10%) -> 1962 | L77: 89 | M77: =L77+K77+I77 -> 2106 | N77: HN Basic Plus | X77: 56-59 | Y77: Male | AA77: 8993 | AB77: =AA77+(AA77*$AC$76) -> 8993
A78: Healthnet | B78: Dubai | C78: Classic Plan-4 | D78: 36-45 | E78: Male | F78: =+CONCATENATE(A78," ",C78," ",B78," ",D78," ",E78) -> Healthnet Classic Plan-4 Dubai 36-45 Male | G78: =CONCATENATE(C78," ",D78," ",E78) -> Classic Plan-4 36-45 Male | H78: =ROUND(M78/(1-$H$4),0) -> 2916 | I78: 54.6 | J78: 2069 | K78: =J78+(J78*10%) -> 2276 | L78: 89 | M78: =L78+K78+I78 -> 2420 | N78: HN Basic Plus | X78: 60 - 65 | Y78: Male | AA78: 10260 | AB78: =AA78+(AA78*$AC$76) -> 10260
A79: Healthnet | B79: Dubai | C79: Classic Plan-4 | D79: 46-55 | E79: Male | F79: =+CONCATENATE(A79," ",C79," ",B79," ",D79," ",E79) -> Healthnet Classic Plan-4 Dubai 46-55 Male | G79: =CONCATENATE(C79," ",D79," ",E79) -> Classic Plan-4 46-55 Male | H79: =ROUND(M79/(1-$H$4),0) -> 5019 | I79: 54.6 | J79: 3656 | K79: =J79+(J79*10%) -> 4022 | L79: 89 | M79: =L79+K79+I79 -> 4166 | N79: HN Basic Plus | X79: 66 and above | Y79: Male | AA79: 12334 | AB79: =AA79+(AA79*$AC$76) -> 12334
A80: Healthnet | B80: Dubai | C80: Classic Plan-4 | D80: 56-59 | E80: Male | F80: =+CONCATENATE(A80," ",C80," ",B80," ",D80," ",E80) -> Healthnet Classic Plan-4 Dubai 56-59 Male | G80: =CONCATENATE(C80," ",D80," ",E80) -> Classic Plan-4 56-59 Male | H80: =ROUND(M80/(1-$H$4),0) -> 5730 | I80: 54.6 | J80: 4193 | K80: =J80+(J80*10%) -> 4612 | L80: 89 | M80: =L80+K80+I80 -> 4756 | N80: HN Basic Plus | X80: 00-17 | Y80: Female | AA80: 3430 | AB80: =AA80+(AA80*$AC$76) -> 3430
A81: Healthnet | B81: Dubai | C81: Classic Plan-4 | D81: 60-65 | E81: Male | F81: =+CONCATENATE(A81," ",C81," ",B81," ",D81," ",E81) -> Healthnet Classic Plan-4 Dubai 60-65 Male | G81: =CONCATENATE(C81," ",D81," ",E81) -> Classic Plan-4 60-65 Male | H81: =ROUND(M81/(1-$H$4),0) -> 7782 | I81: 54.6 | J81: 5741 | K81: =J81+(J81*10%) -> 6315 | L81: 89 | M81: =L81+K81+I81 -> 6459 | N81: HN Basic Plus | X81: 18-35 | Y81: Female | AA81: 4907 | AB81: =AA81+(AA81*$AC$76) -> 4907
A82: Healthnet | B82: Dubai | C82: Classic Plan-4 | D82: 66-70 | E82: Male | F82: =+CONCATENATE(A82," ",C82," ",B82," ",D82," ",E82) -> Healthnet Classic Plan-4 Dubai 66-70 Male | G82: =CONCATENATE(C82," ",D82," ",E82) -> Classic Plan-4 66-70 Male | H82: =ROUND(M82/(1-$H$4),0) -> 10254 | I82: 54.6 | J82: 7606 | K82: =J82+(J82*10%) -> 8367 | L82: 89 | M82: =L82+K82+I82 -> 8511 | N82: HN Basic Plus | X82: 36-45 | Y82: Female | AA82: 5572 | AB82: =AA82+(AA82*$AC$76) -> 5572
A83: Healthnet | B83: Dubai | C83: Classic Plan-4 | D83: 00-17 | E83: Female | F83: =+CONCATENATE(A83," ",C83," ",B83," ",D83," ",E83) -> Healthnet Classic Plan-4 Dubai 00-17 Female | G83: =CONCATENATE(C83," ",D83," ",E83) -> Classic Plan-4 00-17 Female | H83: =ROUND(M83/(1-$H$4),0) -> 2530 | I83: 54.6 | J83: 1630 | K83: =J83+(J83*20%) -> 1956 | L83: 89 | M83: =L83+K83+I83 -> 2100 | N83: HN Basic Plus | X83: 46-55 | Y83: Female | AA83: 6953 | AB83: =AA83+(AA83*$AC$76) -> 6953
A84: Healthnet | B84: Dubai | C84: Classic Plan-4 | D84: 18-35 | E84: Female | F84: =+CONCATENATE(A84," ",C84," ",B84," ",D84," ",E84) -> Healthnet Classic Plan-4 Dubai 18-35 Female | G84: =CONCATENATE(C84," ",D84," ",E84) -> Classic Plan-4 18-35 Female | H84: =ROUND(M84/(1-$H$4),0) -> 3124 | I84: 54.6 | J84: 2041 | K84: =J84+(J84*20%) -> 2449 | L84: 89 | M84: =L84+K84+I84 -> 2593 | N84: HN Basic Plus | X84: 56-59 | Y84: Female | AA84: 10072 | AB84: =AA84+(AA84*$AC$76) -> 10072
A85: Healthnet | B85: Dubai | C85: Classic Plan-4 | D85: 36-45 | E85: Female | F85: =+CONCATENATE(A85," ",C85," ",B85," ",D85," ",E85) -> Healthnet Classic Plan-4 Dubai 36-45 Female | G85: =CONCATENATE(C85," ",D85," ",E85) -> Classic Plan-4 36-45 Female | H85: =ROUND(M85/(1-$H$4),0) -> 3961 | I85: 54.6 | J85: 2620 | K85: =J85+(J85*20%) -> 3144 | L85: 89 | M85: =L85+K85+I85 -> 3288 | N85: HN Basic Plus | X85: 60 - 65 | Y85: Female | AA85: 10260 | AB85: =AA85+(AA85*$AC$76) -> 10260
A86: Healthnet | B86: Dubai | C86: Classic Plan-4 | D86: 46-55 | E86: Female | F86: =+CONCATENATE(A86," ",C86," ",B86," ",D86," ",E86) -> Healthnet Classic Plan-4 Dubai 46-55 Female | G86: =CONCATENATE(C86," ",D86," ",E86) -> Classic Plan-4 46-55 Female | H86: =ROUND(M86/(1-$H$4),0) -> 6147 | I86: 54.6 | J86: 4132 | K86: =J86+(J86*20%) -> 4958 | L86: 89 | M86: =L86+K86+I86 -> 5102 | N86: HN Basic Plus | X86: 66 and above | Y86: Female | AA86: 12334 | AB86: =AA86+(AA86*$AC$76) -> 12334
A87: Healthnet | B87: Dubai | C87: Classic Plan-4 | D87: 56-59 | E87: Female | F87: =+CONCATENATE(A87," ",C87," ",B87," ",D87," ",E87) -> Healthnet Classic Plan-4 Dubai 56-59 Female | G87: =CONCATENATE(C87," ",D87," ",E87) -> Classic Plan-4 56-59 Female | H87: =ROUND(M87/(1-$H$4),0) -> 6852 | I87: 54.6 | J87: 4619 | K87: =J87+(J87*20%) -> 5543 | L87: 89 | M87: =L87+K87+I87 -> 5687 | N87: HN Basic Plus | X87: 00-17 | Y87: Male | Z87: HN Standard | AA87: 2310 | AB87: =AA87+(AA87*$AC$90) -> 2310 | AC87: 0.07
A88: Healthnet | B88: Dubai | C88: Classic Plan-4 | D88: 60-65 | E88: Female | F88: =+CONCATENATE(A88," ",C88," ",B88," ",D88," ",E88) -> Healthnet Classic Plan-4 Dubai 60-65 Female | G88: =CONCATENATE(C88," ",D88," ",E88) -> Classic Plan-4 60-65 Female | H88: =ROUND(M88/(1-$H$4),0) -> 8473 | I88: 54.6 | J88: 5741 | K88: =J88+(J88*20%) -> 6889 | L88: 89 | M88: =L88+K88+I88 -> 7033 | N88: HN Basic Plus | X88: 18-35 | Y88: Male | AA88: 2606 | AB88: =AA88+(AA88*$AC$90) -> 2606
A89: Healthnet | B89: Dubai | C89: Classic Plan-4 | D89: 66-70 | E89: Female | F89: =+CONCATENATE(A89," ",C89," ",B89," ",D89," ",E89) -> Healthnet Classic Plan-4 Dubai 66-70 Female | G89: =CONCATENATE(C89," ",D89," ",E89) -> Classic Plan-4 66-70 Female | H89: =ROUND(M89/(1-$H$4),0) -> 11170 | I89: 54.6 | J89: 7606 | K89: =J89+(J89*20%) -> 9127 | L89: 89 | M89: =L89+K89+I89 -> 9271 | N89: HN Basic Plus | X89: 36-45 | Y89: Male | AA89: 2968 | AB89: =AA89+(AA89*$AC$90) -> 2968
A90: Healthnet | B90: Dubai | C90: Classic Plan-1R | D90: 00-17 | E90: Male | F90: =+CONCATENATE(A90," ",C90," ",B90," ",D90," ",E90) -> Healthnet Classic Plan-1R Dubai 00-17 Male | G90: =CONCATENATE(C90," ",D90," ",E90) -> Classic Plan-1R 00-17 Male | H90: =ROUND(M90/(1-$H$4),0) -> 4384 | I90: 54.6 | J90: 3101 | K90: =J90+(J90*10%) -> 3411 | L90: 173 | M90: =L90+K90+I90 -> 3639 | N90: HN Advantage | X90: 46-55 | Y90: Male | AA90: 4207 | AB90: =AA90+(AA90*$AC$90) -> 4207
A91: Healthnet | B91: Dubai | C91: Classic Plan-1R | D91: 18-35 | E91: Male | F91: =+CONCATENATE(A91," ",C91," ",B91," ",D91," ",E91) -> Healthnet Classic Plan-1R Dubai 18-35 Male | G91: =CONCATENATE(C91," ",D91," ",E91) -> Classic Plan-1R 18-35 Male | H91: =ROUND(M91/(1-$H$4),0) -> 5049 | I91: 54.6 | J91: 3603 | K91: =J91+(J91*10%) -> 3963 | L91: 173 | M91: =L91+K91+I91 -> 4191 | N91: HN Advantage | X91: 56-59 | Y91: Male | AA91: 5678 | AB91: =AA91+(AA91*$AC$90) -> 5678
A92: Healthnet | B92: Dubai | C92: Classic Plan-1R | D92: 36-45 | E92: Male | F92: =+CONCATENATE(A92," ",C92," ",B92," ",D92," ",E92) -> Healthnet Classic Plan-1R Dubai 36-45 Male | G92: =CONCATENATE(C92," ",D92," ",E92) -> Classic Plan-1R 36-45 Male | H92: =ROUND(M92/(1-$H$4),0) -> 5963 | I92: 54.6 | J92: 4292 | K92: =J92+(J92*10%) -> 4721 | L92: 173 | M92: =L92+K92+I92 -> 4949 | N92: HN Advantage | X92: 60 - 65 | Y92: Male | AA92: 7323 | AB92: =AA92+(AA92*$AC$90) -> 7323
A93: Healthnet | B93: Dubai | C93: Classic Plan-1R | D93: 46-55 | E93: Male | F93: =+CONCATENATE(A93," ",C93," ",B93," ",D93," ",E93) -> Healthnet Classic Plan-1R Dubai 46-55 Male | G93: =CONCATENATE(C93," ",D93," ",E93) -> Classic Plan-1R 46-55 Male | H93: =ROUND(M93/(1-$H$4),0) -> 10295 | I93: 54.6 | J93: 7561 | K93: =J93+(J93*10%) -> 8317 | L93: 173 | M93: =L93+K93+I93 -> 8545 | N93: HN Advantage | X93: 66 and above | Y93: Male | AA93: 9702 | AB93: =AA93+(AA93*$AC$90) -> 9702
A94: Healthnet | B94: Dubai | C94: Classic Plan-1R | D94: 56-59 | E94: Male | F94: =+CONCATENATE(A94," ",C94," ",B94," ",D94," ",E94) -> Healthnet Classic Plan-1R Dubai 56-59 Male | G94: =CONCATENATE(C94," ",D94," ",E94) -> Classic Plan-1R 56-59 Male | H94: =ROUND(M94/(1-$H$4),0) -> 12787 | I94: 54.6 | J94: 9441 | K94: =J94+(J94*10%) -> 10385 | L94: 173 | M94: =L94+K94+I94 -> 10613 | N94: HN Advantage | X94: 00-17 | Y94: Female | AA94: 2426 | AB94: =AA94+(AA94*$AC$90) -> 2426
A95: Healthnet | B95: Dubai | C95: Classic Plan-1R | D95: 60-65 | E95: Male | F95: =+CONCATENATE(A95," ",C95," ",B95," ",D95," ",E95) -> Healthnet Classic Plan-1R Dubai 60-65 Male | G95: =CONCATENATE(C95," ",D95," ",E95) -> Classic Plan-1R 60-65 Male | H95: =ROUND(M95/(1-$H$4),0) -> 18439 | I95: 54.6 | J95: 13705 | K95: =J95+(J95*10%) -> 15076 | L95: 173 | M95: =L95+K95+I95 -> 15304 | N95: HN Advantage | X95: 18-35 | Y95: Female | AA95: 3946 | AB95: =AA95+(AA95*$AC$90) -> 3946
A96: Healthnet | B96: Dubai | C96: Classic Plan-1R | D96: 66-70 | E96: Male | F96: =+CONCATENATE(A96," ",C96," ",B96," ",D96," ",E96) -> Healthnet Classic Plan-1R Dubai 66-70 Male | G96: =CONCATENATE(C96," ",D96," ",E96) -> Classic Plan-1R 66-70 Male | H96: =ROUND(M96/(1-$H$4),0) -> 28796 | I96: 54.6 | J96: 21521 | K96: =J96+(J96*10%) -> 23673 | L96: 173 | M96: =L96+K96+I96 -> 23901 | N96: HN Advantage | X96: 36-45 | Y96: Female | AA96: 4326 | AB96: =AA96+(AA96*$AC$90) -> 4326
A97: Healthnet | B97: Dubai | C97: Classic Plan-1R | D97: 00-17 | E97: Female | F97: =+CONCATENATE(A97," ",C97," ",B97," ",D97," ",E97) -> Healthnet Classic Plan-1R Dubai 00-17 Female | G97: =CONCATENATE(C97," ",D97," ",E97) -> Classic Plan-1R 00-17 Female | H97: =ROUND(M97/(1-$H$4),0) -> 4982 | I97: 54.6 | J97: 3256 | K97: =J97+(J97*20%) -> 3907 | L97: 173 | M97: =L97+K97+I97 -> 4135 | N97: HN Advantage | X97: 46-55 | Y97: Female | AA97: 5045 | AB97: =AA97+(AA97*$AC$90) -> 5045
A98: Healthnet | B98: Dubai | C98: Classic Plan-1R | D98: 18-35 | E98: Female | F98: =+CONCATENATE(A98," ",C98," ",B98," ",D98," ",E98) -> Healthnet Classic Plan-1R Dubai 18-35 Female | G98: =CONCATENATE(C98," ",D98," ",E98) -> Classic Plan-1R 18-35 Female | H98: =ROUND(M98/(1-$H$4),0) -> 5746 | I98: 54.6 | J98: 3784 | K98: =J98+(J98*20%) -> 4541 | L98: 173 | M98: =L98+K98+I98 -> 4769 | N98: HN Advantage | X98: 56-59 | Y98: Female | AA98: 6237 | AB98: =AA98+(AA98*$AC$90) -> 6237
A99: Healthnet | B99: Dubai | C99: Classic Plan-1R | D99: 36-45 | E99: Female | F99: =+CONCATENATE(A99," ",C99," ",B99," ",D99," ",E99) -> Healthnet Classic Plan-1R Dubai 36-45 Female | G99: =CONCATENATE(C99," ",D99," ",E99) -> Classic Plan-1R 36-45 Female | H99: =ROUND(M99/(1-$H$4),0) -> 6790 | I99: 54.6 | J99: 4507 | K99: =J99+(J99*20%) -> 5408 | L99: 173 | M99: =L99+K99+I99 -> 5636 | N99: HN Advantage | X99: 60 - 65 | Y99: Female | AA99: 7323 | AB99: =AA99+(AA99*$AC$90) -> 7323
A100: Healthnet | B100: Dubai | C100: Classic Plan-1R | D100: 46-55 | E100: Female | F100: =+CONCATENATE(A100," ",C100," ",B100," ",D100," ",E100) -> Healthnet Classic Plan-1R Dubai 46-55 Female | G100: =CONCATENATE(C100," ",D100," ",E100) -> Classic Plan-1R 46-55 Female | H100: =ROUND(M100/(1-$H$4),0) -> 12765 | I100: 54.6 | J100: 8639 | K100: =J100+(J100*20%) -> 10367 | L100: 173 | M100: =L100+K100+I100 -> 10595 | N100: HN Advantage | X100: 66 and above | Y100: Female | AA100: 9702 | AB100: =AA100+(AA100*$AC$90) -> 9702
...

Sheet Census List
M1: Head Office
B2: Prime Plan-1 | M2: Ajman
B3: Prime Plan-2 | M3: Bur Dubai | P3: Prime Plan-1-AUH | Q3: without | R3: 48422 | T3: Prime Plan-1-AUH | U3: with Dental | V3: 48426
B4: Classic Plan-1 | M4: Al Barsha | P4: Prime Plan-2-AUH | Q4: without | R4: 48455 | T4: Prime Plan-2-AUH | U4: with Dental | V4: 48453
B5: Classic Plan-2 | I5: Head Office | M5: Sharjah | P5: Classic Plan-1-AUH | Q5: without | R5: 48457 | T5: Classic Plan-1-AUH | U5: with Dental | V5: 48460
B6: Classic Plan-3 | G6: BDE | I6: Ajman | M6: SZK | P6: Classic Plan-2-AUH | Q6: without | R6: 48461 | T6: Classic Plan-2-AUH | U6: with Dental | V6: 48465
B7: Classic Plan-4 | D7: Married | G7: Broker | I7: Bur Dubai | M7: Abu Dhabi | P7: Classic Plan-3-AUH | Q7: without | R7: 48468 | T7: Classic Plan-3-AUH | U7: with Dental | V7: 48468
B8: Classic Plan-1R | D8: Single | I8: Al Barsha | M8: DIP | P8: Classic Plan-4-AUH | Q8: without | R8: 48469 | T8: Classic Plan-4-AUH | U8: with Dental | V8: 48471
B9: Classic Plan-2R | G9: Yes | I9: Sharjah | L9: Dubai
B10: Classic Plan-3R | D10: Male | G10: No | I10: SZK | L10: Abu Dhabi | O10: DOH # | P10: =IF(D35="Dubai","",IF(D36="Yes",VLOOKUP(D34,T3:V8,3,0),VLOOKUP(D34,P3:R8,3,0)))
B11: Classic Plan-4R | D11: Female | I11: Abu Dhabi
B12: Prime Plan-1-AUH | I12: DIP | P12: =_xlfn.CONCAT(O10," ",P10) -> DOH #
B13: Prime Plan-2-AUH | D13: Principal
B14: Classic Plan-1-AUH | D14: Spouse | F14: Healthnet
B15: Classic Plan-2-AUH | D15: Child | F15: Healthnet
B16: Classic Plan-3-AUH
B17: Classic Plan-4-AUH | D17: Enhanced | E17: Yes
D18: Basic | E18: No
D20: Dubai | L20: =CONCATENATE(J33," ",J35,"- ",J36) -> Head Office -
D21: NE
D22: AUH | L22: Fixed
L23: Percentage
N27: Amount | O27: %
E28: 0.05 | F28: =IF(E28>15%,"Maximum Commission is 15%"," ") | I28: Additional Loading on Maternity (On NRP) | M28: Fixed
O30: Tool Version 2025/3
A32: Policy Holder Name : | H32: Source Type | J32: BDE
A33: TPA : | D33: Healthnet | H33: Branch | J33: Head Office
A34: Plan Name : | D34: Classic Plan-2 | H34: Source Name
A35: Location : | D35: Dubai | H35: BDE Pin No
A36: Dental Benefits : | D36: Enhanced | H36: Quote No
A37: Visa Location : | D37: AUH | J37: Underwriting Comments
A38: Professional : | D38: Others | J38: =VLOOKUP(D38,'TOB IN PUT'!E38:F46,2,0) -> Please Proceed
A40: Census Information
A41: Name | D41: Gender | E41: Date of Birth | F41: Marital Status | G41: Dependency | H41: Nationality | I41: Age | J41: Age Band | K41: Premium | L41: Addional Loading | M41: Final Premium | N41: Dental | O41: Maternity | P41: Total Premium | R41: Addional Loading
A42: HUSSEIN ALI CHABANI | D42: Male | E42: 27003 | F42: Married | G42: Principal | H42: SYRIA | I42: =IFERROR((IF(E42=0,"",(ROUND((TODAY()-E42)/365.25,0)))),"") -> 52 | J42: =IFERROR(IF((CONCATENATE($D$33,"&",$D$35))='Age Band'!$A$1,VLOOKUP('Census List'!I42,'Age Band'!$A:$B,2,0),IF((CONCATENATE($D$33,"&",$D$35))='Age Band'!$D$1,VLOOKUP('Census List'!I42,'Age Band'!$D:$E,2,0),(IF($D$35='Age Band'!$G$1,VLOOKUP('Census List'!I42,'Age Band'!$G:$H,2,0),0)))),"") -> 46-55 | K42: =IFERROR((VLOOKUP((CONCATENATE($D$33," ",$D$34," ",$D$35," ",J42," ",D42)),'Premium working'!$F$5:$H$227,3,0)),"") -> 8461 | L42: 0 | M42: =IFERROR(K42+(K42*R42),"") -> 8461 | N42: =IFERROR(IF(E42<>"",(IF($D$36="Enhanced",(VLOOKUP((CONCATENATE($D$33," ",$D$34," ",$D$35)),'Premium working'!$T$4:$U$19,2,0)),0)),""),"") -> 361 | O42: =IFERROR(IF($D$35="Dubai",IF((COUNTIFS(D42,"Female",F42,"Married",I42,">=18",I42,"<=45"))=1,VLOOKUP((CONCATENATE($D$33," ",$D$34," ",$D$35," Maternity")),'Premium working'!$F:$H,3,0),0),IF($D$35="Abu Dhabi",IF((COUNTIFS(D42,"Female",F42,"Married",I42,">=18",I42,"<=50"))=1,VLOOKUP((CONCATENATE($D$33," ",$D$34," ",$D$35," Maternity")),'Premium working'!$F:$H,3,0),),"Not Applicable")),"") -> 0 | P42: =IFERROR(M42+N42+O42,"") -> 8822 | R42: 0
A43: KINDA AL ASSAD | D43: Female | E43: 28911 | F43: Married | G43: Spouse | H43: SYRIA | I43: =IFERROR((IF(E43=0,"",(ROUND((TODAY()-E43)/365.25,0)))),"") -> 47 | J43: =IFERROR(IF((CONCATENATE($D$33,"&",$D$35))='Age Band'!$A$1,VLOOKUP('Census List'!I43,'Age Band'!$A:$B,2,0),IF((CONCATENATE($D$33,"&",$D$35))='Age Band'!$D$1,VLOOKUP('Census List'!I43,'Age Band'!$D:$E,2,0),(IF($D$35='Age Band'!$G$1,VLOOKUP('Census List'!I43,'Age Band'!$G:$H,2,0),0)))),"") -> 46-55 | K43: =IFERROR((VLOOKUP((CONCATENATE($D$33," ",$D$34," ",$D$35," ",J43," ",D43)),'Premium working'!$F$5:$H$227,3,0)),"") -> 10835 | L43: 0 | M43: =IFERROR(K43+(K43*R43),"") -> 10835 | N43: =IFERROR(IF(E43<>"",(IF($D$36="Enhanced",(VLOOKUP((CONCATENATE($D$33," ",$D$34," ",$D$35)),'Premium working'!$T$4:$U$19,2,0)),0)),""),"") -> 361 | O43: =IFERROR(IF($D$35="Dubai",IF((COUNTIFS(D43,"Female",F43,"Married",I43,">=18",I43,"<=45"))=1,VLOOKUP((CONCATENATE($D$33," ",$D$34," ",$D$35," Maternity")),'Premium working'!$F:$H,3,0),0),IF($D$35="Abu Dhabi",IF((COUNTIFS(D43,"Female",F43,"Married",I43,">=18",I43,"<=50"))=1,VLOOKUP((CONCATENATE($D$33," ",$D$34," ",$D$35," Maternity")),'Premium working'!$F:$H,3,0),),"Not Applicable")),"") -> 0 | P43: =IFERROR(M43+N43+O43,"") -> 11196 | R43: 0
A44: LAYAL CHABANI | D44: Female | E44: 40409 | F44: Single | G44: Child | H44: SYRIA | I44: =IFERROR((IF(E44=0,"",(ROUND((TODAY()-E44)/365.25,0)))),"") -> 15 | J44: =IFERROR(IF((CONCATENATE($D$33,"&",$D$35))='Age Band'!$A$1,VLOOKUP('Census List'!I44,'Age Band'!$A:$B,2,0),IF((CONCATENATE($D$33,"&",$D$35))='Age Band'!$D$1,VLOOKUP('Census List'!I44,'Age Band'!$D:$E,2,0),(IF($D$35='Age Band'!$G$1,VLOOKUP('Census List'!I44,'Age Band'!$G:$H,2,0),0)))),"") -> 00-17 | K44: =IFERROR((VLOOKUP((CONCATENATE($D$33," ",$D$34," ",$D$35," ",J44," ",D44)),'Premium working'!$F$5:$H$227,3,0)),"") -> 5128 | L44: 0 | M44: =IFERROR(K44+(K44*R44),"") -> 5128 | N44: =IFERROR(IF(E44<>"",(IF($D$36="Enhanced",(VLOOKUP((CONCATENATE($D$33," ",$D$34," ",$D$35)),'Premium working'!$T$4:$U$19,2,0)),0)),""),"") -> 361 | O44: =IFERROR(IF($D$35="Dubai",IF((COUNTIFS(D44,"Female",F44,"Married",I44,">=18",I44,"<=45"))=1,VLOOKUP((CONCATENATE($D$33," ",$D$34," ",$D$35," Maternity")),'Premium working'!$F:$H,3,0),0),IF($D$35="Abu Dhabi",IF((COUNTIFS(D44,"Female",F44,"Married",I44,">=18",I44,"<=50"))=1,VLOOKUP((CONCATENATE($D$33," ",$D$34," ",$D$35," Maternity")),'Premium working'!$F:$H,3,0),),"Not Applicable")),"") -> 0 | P44: =IFERROR(M44+N44+O44,"") -> 5489 | R44: 0
A45: ALY CHABANI | D45: Male | E45: 39320 | F45: Single | G45: Child | H45: SYRIA | I45: =IFERROR((IF(E45=0,"",(ROUND((TODAY()-E45)/365.25,0)))),"") -> 18 | J45: =IFERROR(IF((CONCATENATE($D$33,"&",$D$35))='Age Band'!$A$1,VLOOKUP('Census List'!I45,'Age Band'!$A:$B,2,0),IF((CONCATENATE($D$33,"&",$D$35))='Age Band'!$D$1,VLOOKUP('Census List'!I45,'Age Band'!$D:$E,2,0),(IF($D$35='Age Band'!$G$1,VLOOKUP('Census List'!I45,'Age Band'!$G:$H,2,0),0)))),"") -> 18-35 | K45: =IFERROR((VLOOKUP((CONCATENATE($D$33," ",$D$34," ",$D$35," ",J45," ",D45)),'Premium working'!$F$5:$H$227,3,0)),"") -> 4439 | L45: 0 | M45: =IFERROR(K45+(K45*R45),"") -> 4439 | N45: =IFERROR(IF(E45<>"",(IF($D$36="Enhanced",(VLOOKUP((CONCATENATE($D$33," ",$D$34," ",$D$35)),'Premium working'!$T$4:$U$19,2,0)),0)),""),"") -> 361 | O45: =IFERROR(IF($D$35="Dubai",IF((COUNTIFS(D45,"Female",F45,"Married",I45,">=18",I45,"<=45"))=1,VLOOKUP((CONCATENATE($D$33," ",$D$34," ",$D$35," Maternity")),'Premium working'!$F:$H,3,0),0),IF($D$35="Abu Dhabi",IF((COUNTIFS(D45,"Female",F45,"Married",I45,">=18",I45,"<=50"))=1,VLOOKUP((CONCATENATE($D$33," ",$D$34," ",$D$35," Maternity")),'Premium working'!$F:$H,3,0),),"Not Applicable")),"") -> 0 | P45: =IFERROR(M45+N45+O45,"") -> 4800 | R45: 0
I46: =IFERROR((IF(E46=0,"",(ROUND((TODAY()-E46)/365.25,0)))),"") | J46: =IFERROR(IF((CONCATENATE($D$33,"&",$D$35))='Age Band'!$A$1,VLOOKUP('Census List'!I46,'Age Band'!$A:$B,2,0),IF((CONCATENATE($D$33,"&",$D$35))='Age Band'!$D$1,VLOOKUP('Census List'!I46,'Age Band'!$D:$E,2,0),(IF($D$35='Age Band'!$G$1,VLOOKUP('Census List'!I46,'Age Band'!$G:$H,2,0),0)))),"") | K46: =IFERROR((VLOOKUP((CONCATENATE($D$33," ",$D$34," ",$D$35," ",J46," ",D46)),'Premium working'!$F$5:$H$227,3,0)),"") | M46: =IFERROR(K46+(K46*R46),"") | N46: =IFERROR(IF(E46<>"",(IF($D$36="Enhanced",(VLOOKUP((CONCATENATE($D$33," ",$D$34," ",$D$35)),'Premium working'!$T$4:$U$19,2,0)),0)),""),"") | O46: =IFERROR(IF($D$35="Dubai",IF((COUNTIFS(D46,"Female",F46,"Married",I46,">=18",I46,"<=45"))=1,VLOOKUP((CONCATENATE($D$33," ",$D$34," ",$D$35," Maternity")),'Premium working'!$F:$H,3,0),0),IF($D$35="Abu Dhabi",IF((COUNTIFS(D46,"Female",F46,"Married",I46,">=18",I46,"<=50"))=1,VLOOKUP((CONCATENATE($D$33," ",$D$34," ",$D$35," Maternity")),'Premium working'!$F:$H,3,0),),"Not Applicable")),"") -> 0 | P46: =IFERROR(M46+N46+O46,"") | R46: 0
I47: =IFERROR((IF(E47=0,"",(ROUND((TODAY()-E47)/365.25,0)))),"") | J47: =IFERROR(IF((CONCATENATE($D$33,"&",$D$35))='Age Band'!$A$1,VLOOKUP('Census List'!I47,'Age Band'!$A:$B,2,0),IF((CONCATENATE($D$33,"&",$D$35))='Age Band'!$D$1,VLOOKUP('Census List'!I47,'Age Band'!$D:$E,2,0),(IF($D$35='Age Band'!$G$1,VLOOKUP('Census List'!I47,'Age Band'!$G:$H,2,0),0)))),"") | K47: =IFERROR((VLOOKUP((CONCATENATE($D$33," ",$D$34," ",$D$35," ",J47," ",D47)),'Premium working'!$F$5:$H$227,3,0)),"") | M47: =IFERROR(K47+(K47*R47),"") | N47: =IFERROR(IF(E47<>"",(IF($D$36="Enhanced",(VLOOKUP((CONCATENATE($D$33," ",$D$34," ",$D$35)),'Premium working'!$T$4:$U$19,2,0)),0)),""),"") | O47: =IFERROR(IF($D$35="Dubai",IF((COUNTIFS(D47,"Female",F47,"Married",I47,">=18",I47,"<=45"))=1,VLOOKUP((CONCATENATE($D$33," ",$D$34," ",$D$35," Maternity")),'Premium working'!$F:$H,3,0),0),IF($D$35="Abu Dhabi",IF((COUNTIFS(D47,"Female",F47,"Married",I47,">=18",I47,"<=50"))=1,VLOOKUP((CONCATENATE($D$33," ",$D$34," ",$D$35," Maternity")),'Premium working'!$F:$H,3,0),),"Not Applicable")),"") -> 0 | P47: =IFERROR(M47+N47+O47,"") | R47: 0
I48: =IFERROR((IF(E48=0,"",(ROUND((TODAY()-E48)/365.25,0)))),"") | J48: =IFERROR(IF((CONCATENATE($D$33,"&",$D$35))='Age Band'!$A$1,VLOOKUP('Census List'!I48,'Age Band'!$A:$B,2,0),IF((CONCATENATE($D$33,"&",$D$35))='Age Band'!$D$1,VLOOKUP('Census List'!I48,'Age Band'!$D:$E,2,0),(IF($D$35='Age Band'!$G$1,VLOOKUP('Census List'!I48,'Age Band'!$G:$H,2,0),0)))),"") | K48: =IFERROR((VLOOKUP((CONCATENATE($D$33," ",$D$34," ",$D$35," ",J48," ",D48)),'Premium working'!$F$5:$H$227,3,0)),"") | M48: =IFERROR(K48+(K48*R48),"") | N48: =IFERROR(IF(E48<>"",(IF($D$36="Enhanced",(VLOOKUP((CONCATENATE($D$33," ",$D$34," ",$D$35)),'Premium working'!$T$4:$U$19,2,0)),0)),""),"") | O48: =IFERROR(IF($D$35="Dubai",IF((COUNTIFS(D48,"Female",F48,"Married",I48,">=18",I48,"<=45"))=1,VLOOKUP((CONCATENATE($D$33," ",$D$34," ",$D$35," Maternity")),'Premium working'!$F:$H,3,0),0),IF($D$35="Abu Dhabi",IF((COUNTIFS(D48,"Female",F48,"Married",I48,">=18",I48,"<=50"))=1,VLOOKUP((CONCATENATE($D$33," ",$D$34," ",$D$35," Maternity")),'Premium working'!$F:$H,3,0),),"Not Applicable")),"") -> 0 | P48: =IFERROR(M48+N48+O48,"") | R48: 0
I49: =IFERROR((IF(E49=0,"",(ROUND((TODAY()-E49)/365.25,0)))),"") | J49: =IFERROR(IF((CONCATENATE($D$33,"&",$D$35))='Age Band'!$A$1,VLOOKUP('Census List'!I49,'Age Band'!$A:$B,2,0),IF((CONCATENATE($D$33,"&",$D$35))='Age Band'!$D$1,VLOOKUP('Census List'!I49,'Age Band'!$D:$E,2,0),(IF($D$35='Age Band'!$G$1,VLOOKUP('Census List'!I49,'Age Band'!$G:$H,2,0),0)))),"") | K49: =IFERROR((VLOOKUP((CONCATENATE($D$33," ",$D$34," ",$D$35," ",J49," ",D49)),'Premium working'!$F$5:$H$227,3,0)),"") | M49: =IFERROR(K49+(K49*R49),"") | N49: =IFERROR(IF(E49<>"",(IF($D$36="Enhanced",(VLOOKUP((CONCATENATE($D$33," ",$D$34," ",$D$35)),'Premium working'!$T$4:$U$19,2,0)),0)),""),"") | O49: =IFERROR(IF($D$35="Dubai",IF((COUNTIFS(D49,"Female",F49,"Married",I49,">=18",I49,"<=45"))=1,VLOOKUP((CONCATENATE($D$33," ",$D$34," ",$D$35," Maternity")),'Premium working'!$F:$H,3,0),0),IF($D$35="Abu Dhabi",IF((COUNTIFS(D49,"Female",F49,"Married",I49,">=18",I49,"<=50"))=1,VLOOKUP((CONCATENATE($D$33," ",$D$34," ",$D$35," Maternity")),'Premium working'!$F:$H,3,0),),"Not Applicable")),"") -> 0 | P49: =IFERROR(M49+N49+O49,"") | R49: 0
I50: =IFERROR((IF(E50=0,"",(ROUND((TODAY()-E50)/365.25,0)))),"") | J50: =IFERROR(IF((CONCATENATE($D$33,"&",$D$35))='Age Band'!$A$1,VLOOKUP('Census List'!I50,'Age Band'!$A:$B,2,0),IF((CONCATENATE($D$33,"&",$D$35))='Age Band'!$D$1,VLOOKUP('Census List'!I50,'Age Band'!$D:$E,2,0),(IF($D$35='Age Band'!$G$1,VLOOKUP('Census List'!I50,'Age Band'!$G:$H,2,0),0)))),"") | K50: =IFERROR((VLOOKUP((CONCATENATE($D$33," ",$D$34," ",$D$35," ",J50," ",D50)),'Premium working'!$F$5:$H$227,3,0)),"") | L50: 0 | M50: =IFERROR(K50+(K50*R50),"") | N50: =IFERROR(IF(E50<>"",(IF($D$36="Enhanced",(VLOOKUP((CONCATENATE($D$33," ",$D$34," ",$D$35)),'Premium working'!$T$4:$U$19,2,0)),0)),""),"") | O50: =IFERROR(IF($D$35="Dubai",IF((COUNTIFS(D50,"Female",F50,"Married",I50,">=18",I50,"<=45"))=1,VLOOKUP((CONCATENATE($D$33," ",$D$34," ",$D$35," Maternity")),'Premium working'!$F:$H,3,0),0),IF($D$35="Abu Dhabi",IF((COUNTIFS(D50,"Female",F50,"Married",I50,">=18",I50,"<=50"))=1,VLOOKUP((CONCATENATE($D$33," ",$D$34," ",$D$35," Maternity")),'Premium working'!$F:$H,3,0),),"Not Applicable")),"") -> 0 | P50: =IFERROR(M50+N50+O50,"") | R50: 0
I51: =IFERROR((IF(E51=0,"",(ROUND((TODAY()-E51)/365.25,0)))),"") | J51: =IFERROR(IF((CONCATENATE($D$33,"&",$D$35))='Age Band'!$A$1,VLOOKUP('Census List'!I51,'Age Band'!$A:$B,2,0),IF((CONCATENATE($D$33,"&",$D$35))='Age Band'!$D$1,VLOOKUP('Census List'!I51,'Age Band'!$D:$E,2,0),(IF($D$35='Age Band'!$G$1,VLOOKUP('Census List'!I51,'Age Band'!$G:$H,2,0),0)))),"") | K51: =IFERROR((VLOOKUP((CONCATENATE($D$33," ",$D$34," ",$D$35," ",J51," ",D51)),'Premium working'!$F$5:$H$227,3,0)),"") | L51: 0 | M51: =IFERROR(K51+(K51*R51),"") | N51: =IFERROR(IF(E51<>"",(IF($D$36="Enhanced",(VLOOKUP((CONCATENATE($D$33," ",$D$34," ",$D$35)),'Premium working'!$T$4:$U$19,2,0)),0)),""),"") | O51: =IFERROR(IF($D$35="Dubai",IF((COUNTIFS(D51,"Female",F51,"Married",I51,">=18",I51,"<=45"))=1,VLOOKUP((CONCATENATE($D$33," ",$D$34," ",$D$35," Maternity")),'Premium working'!$F:$H,3,0),0),IF($D$35="Abu Dhabi",IF((COUNTIFS(D51,"Female",F51,"Married",I51,">=18",I51,"<=50"))=1,VLOOKUP((CONCATENATE($D$33," ",$D$34," ",$D$35," Maternity")),'Premium working'!$F:$H,3,0),),"Not Applicable")),"") -> 0 | P51: =IFERROR(M51+N51+O51,"") | R51: 0
I52: =COUNT(I42:I51) -> 4 | P52: =SUM(P42:P51) -> 30307
A54: Premium Summary | I54: Benefits Summary :
A55: Name | D55: Dependency | E55: Age | F55: Total Premium | I55: Maximum Benefit Per Year | K55: ='TOB '!D9 -> AED 250,000
A56: =IFERROR(A42,"") -> HUSSEIN ALI CHABANI | D56: =G42 -> Principal | E56: =I42 -> 52 | F56: =P42 -> 8822 | I56: Network | K56: ='TOB '!D11 -> HN Standard Plus (Additional 10% Co-pay applicable on all OP Services excluding Pharmacy at NMC Royal Hosp. Sharjah)
A57: =IFERROR(A43,"") -> KINDA AL ASSAD | D57: =G43 -> Spouse | E57: =I43 -> 47 | F57: =P43 -> 11196
A58: =IFERROR(A44,"") -> LAYAL CHABANI | D58: =G44 -> Child | E58: =I44 -> 15 | F58: =P44 -> 5489 | I58: Room & Board | K58: ='TOB '!D20 -> Private
A59: =IFERROR(A45,"") -> ALY CHABANI | D59: =G45 -> Child | E59: =I45 -> 18 | F59: =P45 -> 4800 | I59: OP Deductible | K59: ='TOB '!D27 -> 20% up to AED 50/-
A60: =IFERROR(A46,"") -> 0 | D60: =G46 -> 0 | E60: =I46 | F60: =P46 | I60: Lab and Diagnostics | K60: ='TOB '!D28 -> 100% Covered
A61: =IFERROR(A47,"") -> 0 | D61: =G47 -> 0 | E61: =I47 | F61: =P47
A62: =IFERROR(A48,"") -> 0 | D62: =G48 -> 0 | E62: =I48 | F62: =P48 | I62: Prescribed Drugs and Medicines | K62: ='TOB '!D31 -> Covered up to AED 10,000 with Nil Co Insurance (Branded)
A63: =IFERROR(A49,"") -> 0 | D63: =G49 -> 0 | E63: =I49 | F63: =P49
A64: =IFERROR(A50,"") -> 0 | D64: =G50 -> 0 | E64: =I50 | F64: =P50 | I64: Physiotherapy | K64: ='TOB '!D30 -> 20 sessions per member per annum
A65: =IFERROR(A51,"") -> 0 | D65: =G51 -> 0 | E65: =I51 | F65: =P51 | I65: Dental Benefit | K65: ='TOB '!D54 -> Covered up to AED 2,000/- with 20% Co Insurance
A67: Total Premium | E67: =COUNT(E56:E66) -> 4 | F67: =SUM(F56:F66) -> 30307
A68: Vat @ 5% | F68: =ROUND(F67*5%,2) -> 1515.35
A69: 1) BASMAH Program @AED. 19 PPPY 2) HCV @ AED. 18 PPPY (Total 38.85 PPPA with Vat) | F69: =IFERROR((IF($D$37="Dubai",$E$67*38.85,0)),"") -> 0
A71: ICP Fee | F71: =IFERROR(IF(OR(D37="NE", D37="AUH"), $E$67*25.2, "-"), "-") -> 100.8
A72: Total Premium | F72: =IFERROR(ROUND(SUM(F69,F68,F67,F71),2),"") -> 31923.15
A74: Terms and Conditions:
A76: 1- | B76: The issued rates are indicative non-binding and subject to validation by NGI on review of the submitted Health declaration From and the supporting medical reports.
A77: 2- | B77: The rates are valid for 30 days from the date of Issuance.
A78: 3- | B78: Premiums Quoted are based on the information provided on the Health Declaration Form and may change in case the declarations by the applicant are revised.
A79: 4- | B79: NGI reserves the right to non-coverage of the medical conditions and/or to invalidate the policy in event of Non-Disclosure or misrepresentation.
A80: 5- | B80: The applicant must notify NGI in case of a significant change in the medical status of any of the insured members/applicant from the issuance of the quotation until its acceptance. Failure to do so will invalidate the quoted Premium and the quotation will be considered null and void.
A82: 6- | B82: The premiums are payable in advance and must be received by NGI before issuance of the policy.

Sheet Age Band
A1: Healthnet&Dubai | D1: Nextcare&Dubai | G1: Abu Dhabi
A2: No | B2: bracket | D2: No | E2: bracket | G2: No | H2: bracket
A3: 0 | B3: 00-17 | D3: 0 | E3: 00-15 | G3: 0 | H3: 00-17
A4: 1 | B4: 00-17 | D4: 1 | E4: 00-15 | G4: 1 | H4: 00-17
A5: 2 | B5: 00-17 | D5: 2 | E5: 00-15 | G5: 2 | H5: 00-17
A6: 3 | B6: 00-17 | D6: 3 | E6: 00-15 | G6: 3 | H6: 00-17
A7: 4 | B7: 00-17 | D7: 4 | E7: 00-15 | G7: 4 | H7: 00-17
A8: 5 | B8: 00-17 | D8: 5 | E8: 00-15 | G8: 5 | H8: 00-17
A9: 6 | B9: 00-17 | D9: 6 | E9: 00-15 | G9: 6 | H9: 00-17
A10: 7 | B10: 00-17 | D10: 7 | E10: 00-15 | G10: 7 | H10: 00-17
A11: 8 | B11: 00-17 | D11: 8 | E11: 00-15 | G11: 8 | H11: 00-17
A12: 9 | B12: 00-17 | D12: 9 | E12: 00-15 | G12: 9 | H12: 00-17
A13: 10 | B13: 00-17 | D13: 10 | E13: 00-15 | G13: 10 | H13: 00-17
A14: 11 | B14: 00-17 | D14: 11 | E14: 00-15 | G14: 11 | H14: 00-17
... A69: 66 | B69: 66-70 | D69: 66 | E69: 66-69 | G69: 66 | H69: 60-69
A70: =A69+1 -> 67 | B70: 66-70 | D70: =D69+1 -> 67 | E70: 66-69 | G70: =G69+1 -> 67 | H70: 60-69
A71: =A70+1 -> 68 | B71: 66-70 | D71: =D70+1 -> 68 | E71: 66-69 | G71: =G70+1 -> 68 | H71: 60-69
A72: =A71+1 -> 69 | B72: 66-70 | D72: =D71+1 -> 69 | E72: 66-69 | G72: =G71+1 -> 69 | H72: 60-69
A73: =A72+1 -> 70 | B73: 66-70 | D73: =D72+1 -> 70 | E73: 70-75 | G73: =G72+1 -> 70 | H73: 70-75
A74: =A73+1 -> 71 | B74: Refer to HO | D74: =D73+1 -> 71 | E74: 70-75 | G74: =G73+1 -> 71 | H74: 70-75
A75: =A74+1 -> 72 | B75: Refer to HO | D75: =D74+1 -> 72 | E75: 70-75 | G75: =G74+1 -> 72 | H75: 70-75
A76: =A75+1 -> 73 | B76: Refer to HO | D76: =D75+1 -> 73 | E76: 70-75 | G76: =G75+1 -> 73 | H76: 70-75
A77: =A76+1 -> 74 | B77: Refer to HO | D77: =D76+1 -> 74 | E77: 70-75 | G77: =G76+1 -> 74 | H77: 70-75
A78: =A77+1 -> 75 | B78: Refer to HO | D78: =D77+1 -> 75 | E78: 70-75 | G78: =G77+1 -> 75 | H78: 70-75
A79: =A78+1 -> 76 | B79: Refer to HO | D79: =D78+1 -> 76 | E79: 76-80 | G79: =G78+1 -> 76 | H79: 76-80
A80: =A79+1 -> 77 | B80: Refer to HO | D80: =D79+1 -> 77 | E80: 76-80 | G80: =G79+1 -> 77 | H80: 76-80
A81: =A80+1 -> 78 | B81: Refer to HO | D81: =D80+1 -> 78 | E81: 76-80 | G81: =G80+1 -> 78 | H81: 76-80
... A103: =A102+1 -> 100 | B103: Refer to HO | D103: =D102+1 -> 100 | E103: Refer to HO | G103: =G102+1 -> 100 | H103: Refer to HO

Sheet TOB 
A2: Date | B2: =TODAY() -> 46024 | G2: Ref Number : | H2: ='Census List'!L20 -> Head Office -
A3: Policy Holder Name | B3: ='Census List'!D32 -> 0
A5: Medical Insurance Program – | F5: ='Census List'!D33 -> Healthnet
A6: Dear Sir, National General Insurance Company (NGI) is pleased to welcome you to enroll in a distinctively designed program for you. NGI is a leading composite insurer in UAE, recognized as a fully accredited National Insurer, publicly listed, and rated “A-(Excellent)” by AM Best. The Health Plans for are tailored with comprehensive range of benefits, compliant to DHA and DOH-AUH, and offer highest levels of service and care to the insured members. We are pleased to offer you our proposal and hope that you will find the quoted terms competitive. Please do not hesitate to contact us for further assistance or any clarification that you may need on the product and services. On behalf of Medical Department - National General Insurance (NGI)
A7: Plan Name | D7: ='Census List'!D34 -> Classic Plan-2 | H7: =IF('Census List'!D35="Dubai","",'Census List'!P12)
A8: Table of Benefits
A9: Maximum Benefit Per Year | D9: =VLOOKUP($D$7,'TOB IN PUT'!A2:S17,3,0) -> AED 250,000 | J9: =D22 -> Covered on Reimbursement up to AED 250 per night and a maximum of 10 nights. The Cash Indemnity claim must be submitted within 15 days after discharge from the hospital with a proof of hospitalization including a discharge summary.
A10: Area of Coverage | D10: =VLOOKUP($D$7,'TOB IN PUT'!$A$2:$S$17,4,0) -> Worldwide Excluding USA and Canada
A11: Provider Network | D11: =VLOOKUP($D$7,'TOB IN PUT'!$A$2:$S$17,5,0) -> HN Standard Plus (Additional 10% Co-pay applicable on all OP Services excluding Pharmacy at NMC Royal Hosp. Sharjah) | J11: =D11 -> HN Standard Plus (Additional 10% Co-pay applicable on all OP Services excluding Pharmacy at NMC Royal Hosp. Sharjah)
A12: Pre-existing & Chronic Conditions Subject to Medical Application Form (MAF) | B12: Coverage | D12: =IF('Census List'!D35="Dubai","Covered up to a limit of AED 150,000 per member per year","Covered up to a limit of AED 250,000 per member per year") -> Covered up to a limit of AED 150,000 per member per year
B13: Note | D13: No waiting period applies if evidence of continuity of coverage is provided; otherwise a waiting period of 6 months applies to the first scheme membership. All pre-existing medical conditions should be declared in the medical application form and is subject to medical undewriting Undeclared pre-existing conditions will not be covered during the policy period and will be underwritten at renewal.
A14: TPA | D14: NGI Healthnet
A15: Claims Settlement Basis (After application of Copayments) | B15: Within Provider Network | D15: Direct Billing Available. Reimbursement is also possible but will be settled at 80% of the usual & customary rates of the selected Network.
B16: Reimbursement Outside Network within the area of coverage | D16: Re-imbursement at 80% of actual costs (subject to be reasonable) or 80% of the usual & customary rates of the network, whichever is less.
A17: Life Threatening Emergency case within the area of coverage (to be notified within 24 hours of treatment if in a non-network provider) | D17: 100% of incurred costs
A18: Cover within the scope of territory, for Elective and Emergency | D18: When treatment received for emergency, accident or illnesses first arising after leaving U.A.E. whilst traveling on business or vacation for a maximum of 90 to 150 days within the geographical area, the country actual reasonable and customary prices will apply to inpatient and out -patient services.
A19: IN-PATIENT BENEFITS
A20: Room & Board | D20: Private | J20: =D20 -> Private
A21: Tests, diagnosis, treatments and surgeries for Non-urgent cases Pre-approval is required for this benefit. | D21: Covered
A22: Cash Indemnity for In-Patient hospitalizations that are not submitted to the Insurance Company | D22: =VLOOKUP($D$7,'TOB IN PUT'!$A$2:$S$17,11,0) -> Covered on Reimbursement up to AED 250 per night and a maximum of 10 nights. The Cash Indemnity claim must be submitted within 15 days after discharge from the hospital with a proof of hospitalization including a discharge summary.
A23: Parent Accommodation for child under 16 years of age | D23: =VLOOKUP($D$7,'TOB IN PUT'!$A$2:$S$17,6,0) -> Covered up to AED 300 / night
A24: The cost of accommodating a person accompanying an in-patient in the same room in cases of medical necessity at the recommendation of the treating doctor and after the prior approval of the insurance | D24: =VLOOKUP($D$7,'TOB IN PUT'!$A$2:$S$17,6,0) -> Covered up to AED 300 / night
A25: Emergency road ambulance services to and from hospital by registered ambulance services provider | D25: 100% Covered
A26: OUT-PATIENT BENEFITS
A27: Examination, diagnostic and treatment by authorized general practitioners, specialist, and consultants. (Will not be applicable for follow-up visits within 7 days from the same treatment and with the same doctor) | D27: =IF('Census List'!D35="Dubai",VLOOKUP('TOB '!$D$7,'TOB IN PUT'!A2:H11,8,0),VLOOKUP($D$7,'TOB IN PUT'!A12:H17,8,0)) -> 20% up to AED 50/- | J27: =F27 -> 0
A28: Laboratory tests carried out in authorized facility | D28: =VLOOKUP($D$7,'TOB IN PUT'!$A$2:$S$17,10,0) -> 100% Covered | J28: =D28 -> 100% Covered
A29: Radiology diagnostic services carried out in authorized facility. (Pre- approval required for Elective MRI, CT scans, Endoscopies) | D29: =VLOOKUP($D$7,'TOB IN PUT'!$A$2:$S$17,10,0) -> 100% Covered
A30: Physiotherapy Pre-approval is required for this benefit (as per policy conditions) | D30: =VLOOKUP($D$7,'TOB IN PUT'!$A$2:$S$17,12,0) -> 20 sessions per member per annum | J30: =D30 -> 20 sessions per member per annum
A31: Prescribed Drugs and Medicines | D31: =VLOOKUP($D$7,'TOB IN PUT'!$A$2:$S$17,9,0) -> Covered up to AED 10,000 with Nil Co Insurance (Branded) | J31: =D31 -> Covered up to AED 10,000 with Nil Co Insurance (Branded)
A32: PREVENTIVE SERVICES, VACCINES, AND IMMUNIZATIONS
A33: Essential vaccinations and inoculations | D33: =IF('Census List'!D35="Dubai"," Essential vaccinations and inoculations for newborns and children as stipulated in the DHAs policies and its updates in the assigned facilities (currently the same as Federal MOH) are covered ","Covered as per DOH list") -> Essential vaccinations and inoculations for newborns and children as stipulated in the DHAs policies and its updates in the assigned facilities (currently the same as Federal MOH) are covered
A34: Diabetes screening (Frequency restricted to: Diabetes: Every 3 years from age 30, High risk individuals annually from age 18) | D34: =IF('Census List'!D35="Dubai"," Covered as per terms, conditions and exclusions of the program defined by DHA ","Not Covered") -> Covered as per terms, conditions and exclusions of the program defined by DHA
A35: Adult Pneumococcal Conjugate Vaccine | D35: =IF('Census List'!D35="Dubai"," Covered as per terms, conditions and exclusions of the program defined by DHA ","Not Covered") -> Covered as per terms, conditions and exclusions of the program defined by DHA
A36: Influenza Vaccine | D36: =IF('Census List'!D35="Dubai","Covered once per annum“Limited to the cost of the vaccine and its administration only”","Not Covered") -> Covered once per annum“Limited to the cost of the vaccine and its administration only”
A37: Shingrix Vaccine (For NLSB members DXB visa holders) | D37: Covered only for members satisfying the eligibility criteria set by DHA. Limited to the cost of the vaccine and its administration only.
A38: ADDITIONAL BENEFITS
A39: Diagnostic and treatment services for dental and gum treatments (Emergency cases Only). Dental emergency is any injury to your teeth or gums that can put you at a risk of permanent damage, such as Chipped or broken teeth, Knocked-out tooth, Soft-tissue injuries etc. | D39: =IF('Census List'!D35="Dubai"," Subject to 20% coinsurance ","100% covered") -> Subject to 20% coinsurance
A40: Hearing and vision aids, and vision correction by surgeries and laser (Emergency cases Only) Hearing Emergencies include Object/insect in the ear, ruptured eardrum, sudden hearing loss etc. Vision Emergencies include bleeding or discharge from or around the eye, double vision, and Loss of vision, total or partial, one eye or both etc. | D40: =IF('Census List'!D35="Dubai"," Subject to 20% coinsurance ","100% covered") -> Subject to 20% coinsurance
A41: Cancer Screening & Treatment (Breast, Cervical & colorectal Covered under BASMAH patient support program .) | D41: =IF('Census List'!D35="Dubai"," Covered as per terms, conditions and exclusions of the program defined by DHA ","Not Covered") -> Covered as per terms, conditions and exclusions of the program defined by DHA
A42: Hepatitis B & C Virus (Screening and Treatment Screening, Healthcare Services, Investigations and Treatments only for members enrolled under Patient Support Program only) | D42: =IF('Census List'!D35="Dubai"," Covered as per terms, conditions and exclusions of the program defined by DHA ","Not Covered") -> Covered as per terms, conditions and exclusions of the program defined by DHA
A43: Vitamins (If medically necessary in case of deficiency OR if prescribed by the treating physician) | D43: Covered
A44: Alternative Medicines/ Therapies: Covers the following: Chiropractic/ Osteopathy/ Homeopathy and Ayurvedic. Alternative Treatment administered by registered & licensed Practitioner on reimbursement basis only. (all forms of massage therapy is excluded) | D44: =VLOOKUP($D$7,'TOB IN PUT'!$A$2:$S$17,18,0) -> Covered up to AED 2,000/- with 20% Co Insurance
A45: Psychiatric Treatment and Mental Health Services, Inpatient, outpatient, emergency. No coinsurance if a follow-up visit made within seven days | D45: =VLOOKUP($D$7,'TOB IN PUT'!$A$2:$S$17,19,0) -> Covered up to AED 2,000/- with 20% Coins
A46: Organ Transplant : Organ transplantation shall cover the organ transplantation as recipient excluding any cost related to donor, and excluding the acquisition and organ cost, Organs covered are: heart, lung, kidney, pancreas, liver, Allogeneic & autologous bone marrow). | D46: =IF('Census List'!D35="Dubai"," Covered up to AED 150,000/- ","Covered up to AED 250,000/-") -> Covered up to AED 150,000/-
A47: Repatriation of Mortal Remains (Repatriation costs for the transport of mortal remains to the country of origin.) | D47: =VLOOKUP($D$7,'TOB IN PUT'!$A$2:$S$17,13,0) -> Covered up to Maximum AED. 15,000 per person per annum (Settled on Reimbursement basis with no co-pay)
A48: Home Nursing following inpatient treatment | D48: =VLOOKUP($D$7,'TOB IN PUT'!$A$2:$S$17,7,0) -> Covered up to 10 weeks (on reimbusement)
A49: Economy Return Air ticket (For Insured Member only): (Subject to prior approval from NGI for cost effective treatment). | D49: 100% Covered on Reimbursement
A50: Work Related Injuries for AUH only (Healthcare services for work illnesses and injuries as per Federal Law No. 8 of 1980 concerning the Regulation of Work Relations, as amended, and applicable laws in this respect.) | D50: =IF('Census List'!D35="Dubai"," Not Covered ","100% covered") -> Not Covered
A51: Kidney Dialysis | D51: =IF('Census List'!D35="Dubai"," Covered up to AED 60,000/- with 20% Co Insurance on all OP Services (Coverage is provided in accordance with the terms, conditions, and exclusions defined by DHA and is applicable exclusively to Dubai visa holders only.)","Not Covered") -> Covered up to AED 60,000/- with 20% Co Insurance on all OP Services (Coverage is provided in accordance with the terms, conditions, and exclusions defined by DHA and is applicable exclusively to Dubai visa holders only.)
A52: Mental Health (Outpatient counselling) | D52: =IF('Census List'!D35="Dubai"," Covered up to AED 800/- with 30% Co Insurance (Coverage is provided in accordance with the terms, conditions, and exclusions defined by DHA and is applicable exclusively to Dubai visa holders only.)","Not Covered") -> Covered up to AED 800/- with 30% Co Insurance (Coverage is provided in accordance with the terms, conditions, and exclusions defined by DHA and is applicable exclusively to Dubai visa holders only.)
A53: Second Medical Opinion | D53: Covered
A54: =VLOOKUP('Census List'!D36,'TOB IN PUT'!D20:E21,2,0) -> Dental Benefit: •Routine oral examination and routine cleaning of teeth. Once only per policy year. •Extraction (removal of teeth) on the recommendation of a dentist. •Filling of decayed or fractured teeth on the recommendation of a dentist. •Dental x-rays when needed to diagnose and treat a covered dental condition. •General anesthetics, when medically necessary and in connection with a covered dental procedure. •Endodontic treatment, including root canal therapy. •Surgical Interventions •Prescribed Drugs related to the above treatment | D54: =IF('Census List'!$D$36="Enhanced",VLOOKUP('Census List'!$D$34,'TOB IN PUT'!A2:U17,17,0),"Covered up to AED 500/- with 30% Co Insurance (Coverage is provided in accordance with the terms, conditions, and exclusions defined by DHA and is applicable exclusively to Dubai visa holders only.)") -> Covered up to AED 2,000/- with 20% Co Insurance | J54: =D54 -> Covered up to AED 2,000/- with 20% Co Insurance
A55: MATERNITY
A56: In-patient maternity services: (Requires prior approval from the insurance company or within 24 hours of emergency treatment). | D56: =IF('Census List'!$D$35="Dubai",VLOOKUP($D$7,'TOB IN PUT'!A2:S11,16,0),VLOOKUP($D$7,'TOB IN PUT'!A12:S17,16,0)) -> Covered with Nil co-insurance up payable by the insured) Normal Delivery: Aggregate Limit Per Year: AED.12,500 Medically necessary Cesarean Section, Complications & Medically Necessary Termination: Aggregate Limit Per Year: AED. 15,000/- (Where any condition develops which becomes life threatening to either the mother or the new born, the medically necessary expenses will be covered up to AED 150,000/-)
A57: Out-patient maternity services: | D57: =IF('Census List'!$D$35="Dubai",VLOOKUP($D$7,'TOB IN PUT'!A2:S11,15,0),VLOOKUP($D$7,'TOB IN PUT'!A12:S17,15,0)) -> Covered subject to Nil coinsurance payable by the insured maximum 10 visits are allowed (as per applicable network); Initial investigations to include: · FBC and Platelets · Blood group, Rhesus status and antibodies · VDRL · MSU & urinalysis· Rubella serology· HIV · Hep C offered to high risk patients · GTT if high risk · FBS , random s or A1c for all due to high prevalence of diabetes in UAE Visits to include reviews, checks and tests in accordance with DHA Antenatal Care Protocols 8 ante-natal ultrasound scans
A58: Newborn cover | C58: Newborn Entitlement | D58: =IF('Census List'!$D$35="Dubai",VLOOKUP($D$7,'TOB IN PUT'!A2:U11,20,0),VLOOKUP($D$7,'TOB IN PUT'!A12:U17,20,0)) -> Coverage of a pregnant female is extended by the insurer to provide the same benefits for a newborn child of that female for a period up to 30 days from its date of birth. This cover is provided regardless of whether the newborn is eventually enrolled as a dependent member under the insurer’s policy. Covered under the mother’s card in event of Hospitalization, up to AED.150,000 PPPY
C59: Coverage | D59: =IF('Census List'!$D$35="Dubai",VLOOKUP($D$7,'TOB IN PUT'!A2:U11,21,0),VLOOKUP($D$7,'TOB IN PUT'!A12:U17,21,0)) -> Coverage of a pregnant female is extended by the insurer to provide the same benefits for a newborn child of that female for a period up to 30 days from its date of birth. This cover is provided regardless of whether the newborn is eventually enrolled as a dependent member under the insurer’s policy. Cover for 30 days from birth. BCG, Hepatitis B and neo-natal screening tests (Phenylketonuria (PKU), Congenital Hypothyroidism, sickle cell screening, congenital adrenal hyperplasia)
A60: ‘Personal Accident Free cover for Insured persons between 3 years to 69 years’
A61: Personal Accident Coverage:(For Priamry Insured and Spouse) Accidental Death and Dismemberment (AD&D) Permanent Total Disability (PTD) Accidental Death (AD) on Common Carrier Permanent Partial Disability (PPD) Accidental Medical Reimbursement (AMR) Repatriation due to Accidental Death (AD)/ Permanent Total Disability (PTD) | D61: Covered up to AED 50,000/- Covered up to AED 50,000/- Covered up to AED 100,000/- Covered As Per Continental Scale Covered up to AED 5,000/- Covered up to AED 5,000/-
A62: Personal Accident Coverage:(For Children) Accidental Death and Dismemberment (AD&D) Permanent Partial Disability (PPD) Accidental Medical Reimbursement (AMR) | D62: Covered up to AED 50,000/- Covered As Per Continental Scale Covered up to AED 2,500/-
A63: Quotation Terms and Conditions. 1) The above quotation shall be valid for 30 days from date of issuance. 2) All Applicants are UAE residents. 3) Premiums are per person per annum and are payable annually in advance. 4) *Coverage of Pre-existing Conditions is subject to submission of Health Declaration form (HDF) as below: a. Members aged above 50 years of age, premiums are subject to Medical Underwriting upon submission of duly filled Health Declaration Forms, MER, Urinalysis, HBA1C, FBS, CBC, Lipid Profile and ECG with the report. b. NGI reserves the right to ask for any medical check-up if necessary and the cost of which should be borne by the applicant. c. Pre-existing and chronic medical conditions are subject to medical underwriting and should be declared in the HDF (Health Declaration Form), where applicable. Undeclared conditions are not covered, and the policy will be subject to cancellation and or re-underwriting to validate the medical coverage. For new chronic conditions diagnosed after the inception of the policy, a waiting period of 6 months applies unless evidence of continuity of coverage is provided (if applicable). 5) Non- Guaranteed Premium – Premiums payable for this plan are not guaranteed and may be increased at each Policy Renewal based on the claims experience of the portfolio. 6) Change of benefit may only take place upon renewal of the policy. 7) This proposal is based on the information given. Any change in the number, age, gender, or marital status of the persons to be insured or the scope of coverage will result in recalculation of the premium rates. 8) Insurance Company reserves the right to include/exclude/upgrade banding/degrade banding of any Hospitals and Clinics at any time from the designated provider network list. VAT Clause: The quote provided above is exclusive of any Value Added Tax ('VAT') or any similar tax, if applicable on the policy. VAT or any similar tax shall be charged extra as applicable.
A65: Disclaimer: We, the client, hereby verify that we have submitted to National General Insurance is complete, accurate and true member registration data as mandated by the Dubai Health Authority. We discharge National General Insurance from any liability and / or responsibility from submission of erroneous data that could prevent and / or delay the issue of visa or renewal of an existing visa and resulting penalties. We hereby also confirm that in the event of penalty imposed on National General Insurance by Dubai Health Authority and / or General Directorate of Residency and Foreigners Affairs Dubai, we will assume full liability to pay the fines and release National General Insurance from any financial responsibility.

Sheet HDF Review
B1: Group Name
B2: S. No. | C2: Member Name | D2: DOB DDMMYYYY | E2: Age | F2: Plan | G2: Network | H2: Height (cm) | I2: Weight (kg) | J2: BMI | K2: Base Premium | L2: Loadings | M2: Total Premium | N2: Observations | O2: Recommendations
B3: 1 | E3: =IF(D3="","",2021-YEAR(D3)) | J3: =IF(H3="","",IFERROR(I3/((H3/100)^2),0)) | M3: =IF(K3="","",(K3+(K3*L3)))
B4: 2 | E4: =IF(D4="","",2021-YEAR(D4)) | J4: =IF(H4="","",IFERROR(I4/((H4/100)^2),0)) | M4: =IF(K4="","",(K4+(K4*L4)))
B5: 3 | E5: =IF(D5="","",2021-YEAR(D5)) | J5: =IF(H5="","",IFERROR(I5/((H5/100)^2),0)) | M5: =IF(K5="","",(K5+(K5*L5)))
B6: 4 | E6: =IF(D6="","",2021-YEAR(D6)) | J6: =IF(H6="","",IFERROR(I6/((H6/100)^2),0)) | M6: =IF(K6="","",(K6+(K6*L6)))
B7: 5 | E7: =IF(D7="","",2020-YEAR(D7)) | J7: =IF(H7="","",IFERROR(I7/((H7/100)^2),0)) | M7: =IF(K7="","",(K7+(K7*L7)))
B8: 6 | E8: =IF(D8="","",2020-YEAR(D8)) | J8: =IF(H8="","",IFERROR(I8/((H8/100)^2),0)) | M8: =IF(K8="","",(K8+(K8*L8)))
B9: 7 | E9: =IF(D9="","",2020-YEAR(D9)) | J9: =IF(H9="","",IFERROR(I9/((H9/100)^2),0)) | M9: =IF(K9="","",(K9+(K9*L9)))
B10: 8 | E10: =IF(D10="","",2020-YEAR(D10)) | J10: =IF(H10="","",IFERROR(I10/((H10/100)^2),0)) | M10: =IF(K10="","",(K10+(K10*L10)))
B11: 9 | E11: =IF(D11="","",2020-YEAR(D11)) | J11: =IF(H11="","",IFERROR(I11/((H11/100)^2),0)) | M11: =IF(K11="","",(K11+(K11*L11)))
B12: 10 | E12: =IF(D12="","",2020-YEAR(D12)) | J12: =IF(H12="","",IFERROR(I12/((H12/100)^2),0)) | M12: =IF(K12="","",(K12+(K12*L12)))
B13: 11 | E13: =IF(D13="","",2020-YEAR(D13)) | J13: =IF(H13="","",IFERROR(I13/((H13/100)^2),0)) | M13: =IF(K13="","",(K13+(K13*L13)))
B14: 12 | E14: =IF(D14="","",2020-YEAR(D14)) | J14: =IF(H14="","",IFERROR(I14/((H14/100)^2),0)) | M14: =IF(K14="","",(K14+(K14*L14)))
B15: 13 | E15: =IF(D15="","",2020-YEAR(D15)) | J15: =IF(H15="","",IFERROR(I15/((H15/100)^2),0)) | M15: =IF(K15="","",(K15+(K15*L15)))
B16: 14 | E16: =IF(D16="","",2020-YEAR(D16)) | J16: =IF(H16="","",IFERROR(I16/((H16/100)^2),0)) | M16: =IF(K16="","",(K16+(K16*L16)))
B17: 15 | E17: =IF(D17="","",2020-YEAR(D17)) | J17: =IF(H17="","",IFERROR(I17/((H17/100)^2),0)) | M17: =IF(K17="","",(K17+(K17*L17)))
B18: 16 | E18: =IF(D18="","",2020-YEAR(D18)) | J18: =IF(H18="","",IFERROR(I18/((H18/100)^2),0)) | M18: =IF(K18="","",(K18+(K18*L18)))
... B32: 22 | E32: =IF(D32="","",2020-YEAR(D32)) | J32: =IF(H32="","",IFERROR(I32/((H32/100)^2),0)) | M32: =IF(K32="","",(K32+(K32*L32)))

Sheet Exclusions 
B1: Standard Policy Exclusions
B2: (Applicable to Dubai and Northern Emirates Visa holders)
B3: (Non Abu Dhabi Members)
A5: 1- | B5: Healthcare Services which are not medically necessary.
A6: 2- | B6: All expenses relating to dental prostheses, orthodontic treatments, etc.
A7: 3- | B7: Care for the sake of travelling.
A8: 4- | B8: Custodial care including
B9: (1 ) Non-medical treatment services.
B10: (2) Health-related services which do not seek to improve or which do not result in a change in the medical condition of the patient.
A11: 5- | B11: Services that do not require continuous administration by specialized medical personnel.
A12: 6- | B12: Personal comfort and convenience items (television, barber or beauty service, guest service and similar incidental services and supplies)
A13: 7- | B13: All cosmetic healthcare services and services associated with replacement of an existing breast implant. Cosmetic operations which are related to an Injury, sickness or congenital anomaly when the primary purpose is to improve physiological functioning of the involved part of the body and breast reconstruction following a mastectomy for cancer are covered.
A14: 8- | B14: Surgical and non-surgical treatment for obesity (including morbid obesity), and any other weight control programs, services, or supplies.
A15: 9- | B15: Medical services utilized for the sake of research, medically non-approved experiments, investigations, and pharmacological weight reduction regimens.
A16: 10- | B16: Healthcare Services that are not performed by Authorized Healthcare Service Providers.
A17: 11- | B17: Healthcare services and associated expenses for the treatment of alopecia, baldness, hair falling, dandruff or wigs.
A18: 12- | B18: Health services and supplies for smoking cessation programs and the treatment of nicotine addiction.
A19: 13- | B19: Treatment and services for contraception.
A20: 14- | B20: Treatment and services for sex transformation, sterilization or intended to correct a state of sterility or infertility or sexual dysfunction. Sterilization is allowed only if medically indicated and if allowed under the Law.
A21: 15- | B21: External prosthetic devices and medical equipment.
A22: 16- | B22: Treatments and services arising as a result of professional sports activities, including but not limited to, any form of aerial flight, any kind of power-vehicle race, water sports, horse riding activities, mountaineering activities, violent sports such as judo, boxing, and wrestling, bungee jumping and any other professional sports activities.
... A47: 41- | B47: Services and educational programs for people of determination, this also includes disability types such as but not limited to mental, intellectual, developmental, physical and/or psychological disabilities.
A49: Healthcare services outside the scope of health insurance (In Emergency cases as defined by PD 02-2017, the following must be covered until stabilization at minimum)
A50: 1 - | B50: Injuries or illnesses suffered by the Insured Person as a result of military operations of whatever type.
A51: 2 - | B51: Injuries or illnesses suffered by the Insured Person as a result of wars or acts of terror of whatever type.
A52: 3 - | B52: Healthcare services for injuries and accidents arising from nuclear or chemical contamination.
A53: 4 - | B53: Injuries resulting from natural disasters, including but not limited to: earthquakes, tornados and any other type of natural disaster.
A54: 5 - | B54: Injuries resulting from criminal acts or resisting authority by the Insured Person.
A55: 6 - | B55: Injuries resulting from a road traffic accident.
A56: 7 - | B56: Healthcare services for work related illnesses and injuries as per Federal Law No. 8 of 1980 concerning the Regulation of Work Relations, its amendments, and applicable laws in this respect.
A57: 8 - | B57: All cases resulting from the use of alcoholic drinks, controlled substances and drugs and hallucinating substances.
A58: 9 - | B58: Any investigation or treatment not prescribed by a doctor.
A59: 10 - | B59: Injuries resulting from attempted suicide or self-inflicted injuries.
A60: 11 - | B60: Diagnosis and treatment services for complications of exempted illnesses.
A61: 12 - | B61: All healthcare services for internationally and/or locally recognized epidemics.
A62: 13 - | B62: Healthcare services for patients suffering from (and related to the diagnosis and treatment of) HIV – AIDS and its complications and all types of hepatitis except virus A, B and C hepatitis.
A64: Standard Policy Exclusions (Valid for Abu Dhabi members only)
A65: 1 - | B65: Healthcare Services, which are not medically necessary.
A66: 2 - | B66: All expenses relating to dental treatment, dental prostheses, and orthodontic treatments.
A67: 3 - | B67: Domiciliary care; private nursing care; care for the sake of travelling.
A68: 4 - | B68: Custodial care includes (1) Non-medical treatment services; or (2) Health related services which do not seek to improve or which do not result in a change in the medical condition of the patient.
A69: 5 - | B69: Services which do not require continuous administration by specialized medical personnel.
A70: 6 - | B70: Personal comfort and convenience items (television, barber or beauty service, guest service and similar incidental services and supplies).
A71: 7 - | B71: Cosmetic operations aimed at improving physical appearance Page - 63 Book 2: Health Insurance and operations for replacement of an existing breast implant. Cosmetic operations with respect to an injury, sickness or congenital anomaly when the primary purpose is to improve physiological functioning of the involved part of the body, and breast reconstruction following a mastectomy for cancer are covered in the Basic Healthcare Services.
A72: 8 - | B72: Surgical and non-surgical treatment for obesity (including morbid obesity), and any other weight control programs, services, or accessories.
A73: 9 - | B73: Medically non-approved experimental, research, investigational healthcare services, treatments, devices and pharmacological regimens.
A74: 10 - | B74: Healthcare Services that are not performed by Authorized Healthcare Service Providers, apart from Healthcare Services rendered in a Medical Emergency.
A75: 11 - | B75: Healthcare services, treatments & associated expenses for alopecia, baldness, hair falling, dandruff or wigs.
A76: 12 - | B76: Supplies, Treatment and services for smoking cessation programs and the treatment of nicotine addiction.
... A107: 43 - | B107: Services and educational program for handicaps.
B109: Healthcare Services outside the Scope of Health Insurance
A110: 1 - | B110: Injuries or illnesses suffered by the Insured as a result of military operations of whatever type.
A111: 2 - | B111: Injuries or illnesses suffered by the Insured as a result of wars or acts of terror of whatever type.
A112: 3 - | B112: Healthcare services for injuries and accidents arising from nuclear or chemical contamination.
A113: 4 - | B113: Injuries resulting from natural disasters (including but not limited to) tremors, earthquakes, tornados, cyclones and any other type of natural disaster.
A114: 5 - | B114: Injuries resulting from criminal acts or resisting authority by the Insured.
A115: 6 - | B115: Healthcare services for patients suffering from AIDS and its complications.
A116: 7 - | B116: Healthcare services for work illnesses and injuries as per Page - 68 Book 2: Health Insurance Federal Law No. 8 of 1980 concerning the Regulation of Work Relations, as amended, and applicable laws in this respect.
A117: 8 - | B117: All cases resulting from the use of alcohol, drugs and hallucinatory substances.
A118: 9 - | B118: Any test or treatment not prescribed by a doctor.
A119: 10 - | B119: Injuries resulting from attempted suicide or self-inflicted injuries.
A120: 11 - | B120: Diagnosis and treatment services for complications of exempted illnesses.
A121: 12 - | B121: All healthcare services for internationally and locally recognized epidemics.
A122: 13 - | B122: Venereal sexually transmitted diseases. A list with respect thereto will be set out by the General Authority for Health Services.
B123: Dental Exclusions Elaborated
B124: These services remain excluded under the Dental benefit unless otherwise explicitly stated in the dental coverage in the Schedule of Benefits.
A125: 1 | B125: Expenses incurred after the date coverage under the Plan ceases for an Insured Person for any reason. This is true even though the expenses relate to a condition that begins whilst an Insured Person was covered.
A126: 2 | B126: Fixed bridgework or dentures or replacement of any kind.
A127: 3 | B127: Services or supplies from anyone other than a dentist or a physician.
A128: 4 | B128: Facings, veneers or similar material placed on any teeth.
A129: 5 | B129: Services or supplies that are partially or wholly cosmetic in nature or directed towards a cosmetic end.
A130: 6 | B130: A broken appointment.
A131: 7 | B131: Application of fluoride.
A132: 8 | B132: Any service that is not necessary or is not normally performed for proper dental care of the condition or any service that is not approved by the attending dentist.
A133: 9 | B133: Services or supplies that do not meet accepted standards of dental practice including experimental services or supplies.
A134: 10 | B134: Any prosthetic appliances or replacement of any kind.
A135: 11 | B135: Claim form completion costs.
A136: 12 | B136: Any implant.
... A143: 19 | B143: Orthodontic Treatment

Sheet TOB IN PUT
A1: Plan 1 | B1: Plan | C1: Aggregate Annual Limit | D1: Area of Coverage | E1: Medical Network | F1: Parent Accommodation for child under 18 years of age | G1: Home Nursing following inpatient treatment | H1: OP - Deductible | I1: OP Prescribed Drugs & Medicines | J1: OP Diagonistics | K1: Cash Indemnity for In-Patient hospitalizations that are not submitted to the Insurance Company | L1: Physiotherapy | M1: Repatriation of Mortal Remains | N1: Second Medical Opinion | O1: OUT -patient maternity | P1: In-patient maternity | Q1: Dental Benefit | R1: Alternative Medicines | S1: Psychiatric Treatment | T1: Newborn Entitlement | U1: Coverage
A2: Prime Plan-1 | B2: Prime Plan-1 | C2: AED 1,000,000 | D2: Worldwide | E2: HN Exclusive | F2: Covered to AED 450 / night | G2: Covered up to 13 weeks (on reimbusement) | H2: 20% up to AED 100/- | I2: Covered up to AED 15,000 with Nil Co Insurance (Branded) | J2: 100% Covered | K2: Covered on Reimbursement up to AED 300 per night and a maximum of 10 nights. The Cash Indemnity claim must be submitted within 15 days after discharge from the hospital with a proof of hospitalization including a discharge summary. | L2: 24 sessions per member per annum | M2: Covered up to Maximum AED. 20,000 per person per annum (Settled on Reimbursement basis with no co-pay) | N2: Covered | O2: Covered subject to Nil coinsurance payable by the insured maximum 15 visits are allowed (as per applicable network); Initial investigations to include: · FBC and Platelets · Blood group, Rhesus status and antibodies · VDRL · MSU & urinalysis· Rubella serology· HIV · Hep C offered to high risk patients · GTT if high risk · FBS , random s or A1c for all due to high prevalence of diabetes in UAE Visits to include reviews, checks and tests in accordance with DHA Antenatal Care Protocols 8 ante-natal ultrasound scans | P2: Covered with Nil co-insurance up payable by the insured) Normal Delivery: Aggregate Limit Per Year: AED.20,000 Medically necessary Cesarean Section, Complications & Medically Necessary Termination: Aggregate Limit Per Year: AED. 20,000/- (Where any condition develops which becomes life threatening to either the mother or the new born, the medically necessary expenses will be covered up to AED 150,000/-) | Q2: Covered up to AED 5,000/- with 20% Co Insurance | R2: Covered up to AED 2,500/- with 20% Co Insurance | S2: Covered up to AED 5,000/- with 20% Coins | T2: Coverage of a pregnant female is extended by the insurer to provide the same benefits for a newborn child of that female for a period up to 30 days from its date of birth. This cover is provided regardless of whether the newborn is eventually enrolled as a dependent member under the insurer’s policy. Covered under the mother’s card in event of Hospitalization, up to AED.150,000 PPPY | U2: Coverage of a pregnant female is extended by the insurer to provide the same benefits for a newborn child of that female for a period up to 30 days from its date of birth. This cover is provided regardless of whether the newborn is eventually enrolled as a dependent member under the insurer’s policy. Cover for 30 days from birth. BCG, Hepatitis B and neo-natal screening tests (Phenylketonuria (PKU), Congenital Hypothyroidism, sickle cell screening, congenital adrenal hyperplasia)
A3: Prime Plan-2 | B3: Prime Plan-2 | C3: AED 500,000 | D3: Worldwide | E3: HN Premier | F3: Covered to AED 400 / night | G3: Covered up to 13 weeks (on reimbusement) | H3: 20% up to AED 100/- | I3: Covered up to AED 15,000 with Nil Co Insurance (Branded) | J3: 100% Covered | K3: Covered on Reimbursement up to AED 300 per night and a maximum of 10 nights. The Cash Indemnity claim must be submitted within 15 days after discharge from the hospital with a proof of hospitalization including a discharge summary. | L3: 20 sessions per member per annum | M3: Covered up to Maximum AED. 20,000 per person per annum (Settled on Reimbursement basis with no co-pay) | N3: Covered | O3: Covered subject to Nil coinsurance payable by the insured maximum 15 visits are allowed (as per applicable network); Initial investigations to include: · FBC and Platelets · Blood group, Rhesus status and antibodies · VDRL · MSU & urinalysis· Rubella serology· HIV · Hep C offered to high risk patients · GTT if high risk · FBS , random s or A1c for all due to high prevalence of diabetes in UAE Visits to include reviews, checks and tests in accordance with DHA Antenatal Care Protocols 8 ante-natal ultrasound scans | P3: Covered with Nil co-insurance up payable by the insured) Normal Delivery: Aggregate Limit Per Year: AED.18,000 Medically necessary Cesarean Section, Complications & Medically Necessary Termination: Aggregate Limit Per Year: AED. 18,000 (Where any condition develops which becomes life threatening to either the mother or the new born, the medically necessary expenses will be covered up to AED 150,000/-) | Q3: Covered up to AED 3,500/- with 20% Co Insurance | R3: Covered up to AED 2,500/- with 20% Co Insurance | S3: Covered up to AED 5,000/- with 20% Coins | T3: Coverage of a pregnant female is extended by the insurer to provide the same benefits for a newborn child of that female for a period up to 30 days from its date of birth. This cover is provided regardless of whether the newborn is eventually enrolled as a dependent member under the insurer’s policy. Covered under the mother’s card in event of Hospitalization, up to AED.150,000 PPPY | U3: Coverage of a pregnant female is extended by the insurer to provide the same benefits for a newborn child of that female for a period up to 30 days from its date of birth. This cover is provided regardless of whether the newborn is eventually enrolled as a dependent member under the insurer’s policy. Cover for 30 days from birth. BCG, Hepatitis B and neo-natal screening tests (Phenylketonuria (PKU), Congenital Hypothyroidism, sickle cell screening, congenital adrenal hyperplasia)
A4: Classic Plan-1 | B4: Calssic Plan-1 | C4: AED 300,000 | D4: Worldwide Excluding USA and Canada | E4: HN Advantage (Additional 10% Co-pay applicable on all OP Services excluding Pharmacy at NMC Royal Hosp. Sharjah) | F4: Covered up to AED 350 / night | G4: Covered up to 10 weeks (on reimbusement) | H4: 20% up to AED 50/- | I4: Covered up to AED 10,000 with Nil Co Insurance (Branded) | J4: 100% Covered | K4: Covered on Reimbursement up to AED 300 per night and a maximum of 10 nights. The Cash Indemnity claim must be submitted within 15 days after discharge from the hospital with a proof of hospitalization including a discharge summary. | L4: 20 sessions per member per annum | M4: Covered up to Maximum AED. 15,000 per person per annum (Settled on Reimbursement basis with no co-pay) | N4: Covered | O4: Covered subject to Nil coinsurance payable by the insured maximum 12 visits are allowed (as per applicable network); Initial investigations to include: · FBC and Platelets · Blood group, Rhesus status and antibodies · VDRL · MSU & urinalysis· Rubella serology· HIV · Hep C offered to high risk patients · GTT if high risk · FBS , random s or A1c for all due to high prevalence of diabetes in UAE Visits to include reviews, checks and tests in accordance with DHA Antenatal Care Protocols 8 ante-natal ultrasound scans | P4: Covered with Nil co-insurance up payable by the insured) Normal Delivery: Aggregate Limit Per Year: AED.15,000 Medically necessary Cesarean Section, Complications & Medically Necessary Termination: Aggregate Limit Per Year: AED. 15,000/- (Where any condition develops which becomes life threatening to either the mother or the new born, the medically necessary expenses will be covered up to AED 150,000/-) | Q4: Covered up to AED 2,500/- with 20% Co Insurance | R4: Covered up to AED 2,000/- with 20% Co Insurance | S4: Covered up to AED 3,000/- with 20% Coins | T4: Coverage of a pregnant female is extended by the insurer to provide the same benefits for a newborn child of that female for a period up to 30 days from its date of birth. This cover is provided regardless of whether the newborn is eventually enrolled as a dependent member under the insurer’s policy. Covered under the mother’s card in event of Hospitalization, up to AED.150,000 PPPY | U4: Coverage of a pregnant female is extended by the insurer to provide the same benefits for a newborn child of that female for a period up to 30 days from its date of birth. This cover is provided regardless of whether the newborn is eventually enrolled as a dependent member under the insurer’s policy. Cover for 30 days from birth. BCG, Hepatitis B and neo-natal screening tests (Phenylketonuria (PKU), Congenital Hypothyroidism, sickle cell screening, congenital adrenal hyperplasia)
A5: Classic Plan-2 | B5: Calssic Plan-2 | C5: AED 250,000 | D5: Worldwide Excluding USA and Canada | E5: HN Standard Plus (Additional 10% Co-pay applicable on all OP Services excluding Pharmacy at NMC Royal Hosp. Sharjah) | F5: Covered up to AED 300 / night | G5: Covered up to 10 weeks (on reimbusement) | H5: 20% up to AED 50/- | I5: Covered up to AED 10,000 with Nil Co Insurance (Branded) | J5: 100% Covered | K5: Covered on Reimbursement up to AED 250 per night and a maximum of 10 nights. The Cash Indemnity claim must be submitted within 15 days after discharge from the hospital with a proof of hospitalization including a discharge summary. | L5: 20 sessions per member per annum | M5: Covered up to Maximum AED. 15,000 per person per annum (Settled on Reimbursement basis with no co-pay) | N5: Covered | O5: Covered subject to Nil coinsurance payable by the insured maximum 10 visits are allowed (as per applicable network); Initial investigations to include: · FBC and Platelets · Blood group, Rhesus status and antibodies · VDRL · MSU & urinalysis· Rubella serology· HIV · Hep C offered to high risk patients · GTT if high risk · FBS , random s or A1c for all due to high prevalence of diabetes in UAE Visits to include reviews, checks and tests in accordance with DHA Antenatal Care Protocols 8 ante-natal ultrasound scans | P5: Covered with Nil co-insurance up payable by the insured) Normal Delivery: Aggregate Limit Per Year: AED.12,500 Medically necessary Cesarean Section, Complications & Medically Necessary Termination: Aggregate Limit Per Year: AED. 15,000/- (Where any condition develops which becomes life threatening to either the mother or the new born, the medically necessary expenses will be covered up to AED 150,000/-) | Q5: Covered up to AED 2,000/- with 20% Co Insurance | R5: Covered up to AED 2,000/- with 20% Co Insurance | S5: Covered up to AED 2,000/- with 20% Coins | T5: Coverage of a pregnant female is extended by the insurer to provide the same benefits for a newborn child of that female for a period up to 30 days from its date of birth. This cover is provided regardless of whether the newborn is eventually enrolled as a dependent member under the insurer’s policy. Covered under the mother’s card in event of Hospitalization, up to AED.150,000 PPPY | U5: Coverage of a pregnant female is extended by the insurer to provide the same benefits for a newborn child of that female for a period up to 30 days from its date of birth. This cover is provided regardless of whether the newborn is eventually enrolled as a dependent member under the insurer’s policy. Cover for 30 days from birth. BCG, Hepatitis B and neo-natal screening tests (Phenylketonuria (PKU), Congenital Hypothyroidism, sickle cell screening, congenital adrenal hyperplasia)
A6: Classic Plan-3 | B6: Calssic Plan-3 | C6: AED 250,000 | D6: UAE+Home country | E6: HN Standard | F6: Covered up to AED 150 / night | G6: Covered up to 10 weeks (on reimbusement) | H6: 20% up to AED 50/- | I6: Covered up to AED 10,000 with Nil Co Insurance (Branded) | J6: 100% Covered | K6: Covered on Reimbursement up to AED 250 per night and a maximum of 10 nights. The Cash Indemnity claim must be submitted within 15 days after discharge from the hospital with a proof of hospitalization including a discharge summary. | L6: 20 sessions per member per annum | M6: Covered up to Maximum AED. 10,000 per person per annum (Settled on Reimbursement basis with no co-pay) | N6: Covered | O6: Covered subject to Nil coinsurance payable by the insured maximum 10 visits are allowed (as per applicable network); Initial investigations to include: · FBC and Platelets · Blood group, Rhesus status and antibodies · VDRL · MSU & urinalysis· Rubella serology· HIV · Hep C offered to high risk patients · GTT if high risk · FBS , random s or A1c for all due to high prevalence of diabetes in UAE Visits to include reviews, checks and tests in accordance with DHA Antenatal Care Protocols 8 ante-natal ultrasound scans | P6: Covered with Nil co-insurance up payable by the insured) Normal Delivery: Aggregate Limit Per Year: AED.12,500 Medically necessary Cesarean Section, Complications & Medically Necessary Termination: Aggregate Limit Per Year: AED. 15,000 /- (Where any condition develops which becomes life threatening to either the mother or the new born, the medically necessary expenses will be covered up to AED 150,000/-) | Q6: Covered up to AED 2,000/- with 20% Co Insurance | R6: Covered up to AED 1,500/- with 20% Co Insurance | S6: Covered up to AED 1,500/- with 20% Coins | T6: Coverage of a pregnant female is extended by the insurer to provide the same benefits for a newborn child of that female for a period up to 30 days from its date of birth. This cover is provided regardless of whether the newborn is eventually enrolled as a dependent member under the insurer’s policy. Covered under the mother’s card in event of Hospitalization, up to AED.150,000 PPPY | U6: Coverage of a pregnant female is extended by the insurer to provide the same benefits for a newborn child of that female for a period up to 30 days from its date of birth. This cover is provided regardless of whether the newborn is eventually enrolled as a dependent member under the insurer’s policy. Cover for 30 days from birth. BCG, Hepatitis B and neo-natal screening tests (Phenylketonuria (PKU), Congenital Hypothyroidism, sickle cell screening, congenital adrenal hyperplasia)
A7: Classic Plan-4 | B7: Calssic Plan-4 | C7: AED 150,000 | D7: UAE+Home country | E7: HN Basic Plus | F7: Covered up to AED 150 / night | G7: Covered up to 6 weeks (on reimbusement) | H7: 20% up to AED 50/- | I7: Covered up to AED 10,000 with Nil Co Insurance (Branded) | J7: 100% Covered | K7: Covered on Reimbursement up to AED 250 per night and a maximum of 10 nights. The Cash Indemnity claim must be submitted within 15 days after discharge from the hospital with a proof of hospitalization including a discharge summary. | L7: 20 sessions per member per annum | M7: Covered up to Maximum AED. 10,000 per person per annum (Settled on Reimbursement basis with no co-pay) | N7: Covered | O7: Covered subject to Nil coinsurance payable by the insured maximum 8 visits are allowed (as per applicable network); Initial investigations to include: · FBC and Platelets · Blood group, Rhesus status and antibodies · VDRL · MSU & urinalysis· Rubella serology· HIV · Hep C offered to high risk patients · GTT if high risk · FBS , random s or A1c for all due to high prevalence of diabetes in UAE Visits to include reviews, checks and tests in accordance with DHA Antenatal Care Protocols 8 ante-natal ultrasound scans | P7: Covered with Nil co-insurance up payable by the insured) Normal Delivery: Aggregate Limit Per Year: AED.10,000 Medically necessary Cesarean Section, Complications & Medically Necessary Termination: Aggregate Limit Per Year: AED. 10,000 | Q7: Covered up to AED 1,500/- with 20% Co Insurance | R7: Covered up to AED 1,500/- with 20% Co Insurance | S7: Covered up to AED 1,500/- with 20% Coins | T7: Coverage of a pregnant female is extended by the insurer to provide the same benefits for a newborn child of that female for a period up to 30 days from its date of birth. This cover is provided regardless of whether the newborn is eventually enrolled as a dependent member under the insurer’s policy. Covered under the mother’s card in event of Hospitalization, up to AED.150,000 PPPY | U7: Coverage of a pregnant female is extended by the insurer to provide the same benefits for a newborn child of that female for a period up to 30 days from its date of birth. This cover is provided regardless of whether the newborn is eventually enrolled as a dependent member under the insurer’s policy. Cover for 30 days from birth. BCG, Hepatitis B and neo-natal screening tests (Phenylketonuria (PKU), Congenital Hypothyroidism, sickle cell screening, congenital adrenal hyperplasia)
A8: Classic Plan-1R | B8: Calssic Plan-1R | C8: AED 300,000 | D8: Worldwide Excluding USA and Canada | E8: HN Advantage | F8: Covered up to AED 350 / night | G8: Covered up to 10 weeks (on reimbusement) | H8: 20% up to AED 50/- | I8: Covered up to AED 10,000/- with 10% Co Insurance (Branded) | J8: Hospital : Covered up to ABL with 20% Co Insurance on all OP Services -Clinics : Covered up to ABL with Nil Co Insurance | K8: Covered on Reimbursement up to AED 300 per night and a maximum of 10 nights. The Cash Indemnity claim must be submitted within 15 days after discharge from the hospital with a proof of hospitalization including a discharge summary. | L8: 20 sessions per member per annum | M8: Covered up to Maximum AED. 15,000 per person per annum (Settled on Reimbursement basis with no co-pay) | N8: Covered | O8: Covered subject to 10% coinsurance payable by the insured maximum 12 visits are allowed (as per applicable network); Initial investigations to include: · FBC and Platelets · Blood group, Rhesus status and antibodies · VDRL · MSU & urinalysis· Rubella serology· HIV · Hep C offered to high risk patients · GTT if high risk · FBS , random s or A1c for all due to high prevalence of diabetes in UAE Visits to include reviews, checks and tests in accordance with DHA Antenatal Care Protocols 8 ante-natal ultrasound scans | P8: Covered with 10% co-insurance up payable by the insured) Normal Delivery: Aggregate Limit Per Year: AED.15,000 Medically necessary Cesarean Section, Complications & Medically Necessary Termination: Aggregate Limit Per Year: AED. 15,000 | Q8: Covered up to AED 2,500/- with 20% Co Insurance | R8: Covered up to AED 2,000/- with 20% Co Insurance | S8: Covered up to AED 3,000/- with 20% Coins | T8: Coverage of a pregnant female is extended by the insurer to provide the same benefits for a newborn child of that female for a period up to 30 days from its date of birth. This cover is provided regardless of whether the newborn is eventually enrolled as a dependent member under the insurer’s policy. Covered under the mother’s card in event of Hospitalization, up to AED.150,000 PPPY | U8: Coverage of a pregnant female is extended by the insurer to provide the same benefits for a newborn child of that female for a period up to 30 days from its date of birth. This cover is provided regardless of whether the newborn is eventually enrolled as a dependent member under the insurer’s policy. Cover for 30 days from birth. BCG, Hepatitis B and neo-natal screening tests (Phenylketonuria (PKU), Congenital Hypothyroidism, sickle cell screening, congenital adrenal hyperplasia)
A9: Classic Plan-2R | B9: Calssic Plan-2R | C9: AED 250,000 | D9: Worldwide Excluding USA and Canada | E9: HN Standard Plus | F9: Covered up to AED 300 / night | G9: Covered up to 10 weeks (on reimbusement) | H9: 20% up to AED 50/- | I9: Covered up to AED 10,000/- with 10% Co Insurance (Branded) | J9: Hospital : Covered up to ABL with 20% Co Insurance on all OP Services - Clinics : Covered up to ABL with Nil Co Insurance | K9: Covered on Reimbursement up to AED 250 per night and a maximum of 10 nights. The Cash Indemnity claim must be submitted within 15 days after discharge from the hospital with a proof of hospitalization including a discharge summary. | L9: 20 sessions per member per annum | M9: Covered up to Maximum AED. 15,000 per person per annum (Settled on Reimbursement basis with no co-pay) | N9: Covered | O9: Covered subject to 10% coinsurance payable by the insured maximum 10 visits are allowed (as per applicable network); Initial investigations to include: · FBC and Platelets · Blood group, Rhesus status and antibodies · VDRL · MSU & urinalysis· Rubella serology· HIV · Hep C offered to high risk patients · GTT if high risk · FBS , random s or A1c for all due to high prevalence of diabetes in UAE Visits to include reviews, checks and tests in accordance with DHA Antenatal Care Protocols 8 ante-natal ultrasound scans | P9: Covered with 10% co-insurance up payable by the insured) Normal Delivery: Aggregate Limit Per Year: AED.12,500 Medically necessary Cesarean Section, Complications & Medically Necessary Termination: Aggregate Limit Per Year: AED. 15,000 | Q9: Covered up to AED 2,000/- with 20% Co Insurance | R9: Covered up to AED 2,000/- with 20% Co Insurance | S9: Covered up to AED 2,000/- with 20% Coins | T9: Coverage of a pregnant female is extended by the insurer to provide the same benefits for a newborn child of that female for a period up to 30 days from its date of birth. This cover is provided regardless of whether the newborn is eventually enrolled as a dependent member under the insurer’s policy. Covered under the mother’s card in event of Hospitalization, up to AED.150,000 PPPY | U9: Coverage of a pregnant female is extended by the insurer to provide the same benefits for a newborn child of that female for a period up to 30 days from its date of birth. This cover is provided regardless of whether the newborn is eventually enrolled as a dependent member under the insurer’s policy. Cover for 30 days from birth. BCG, Hepatitis B and neo-natal screening tests (Phenylketonuria (PKU), Congenital Hypothyroidism, sickle cell screening, congenital adrenal hyperplasia)
A10: Classic Plan-3R | B10: Calssic Plan-3R | C10: AED 250,000 | D10: UAE+Home country | E10: HN Standard | F10: Covered up to AED 150 / night | G10: Covered up to 10 weeks (on reimbusement) | H10: 20% up to AED 50/- | I10: Covered up to AED 10,000/- with 10% Co Insurance (Branded) | J10: Hospital : Covered up to ABL with 20% Co Insurance on all OP Services- Clinics : Covered up to ABL with Nil Co Insurance | K10: Covered on Reimbursement up to AED 250 per night and a maximum of 10 nights. The Cash Indemnity claim must be submitted within 15 days after discharge from the hospital with a proof of hospitalization including a discharge summary. | L10: 20 sessions per member per annum | M10: Covered up to Maximum AED. 10,000 per person per annum (Settled on Reimbursement basis with no co-pay) | N10: Covered | O10: Covered subject to 10% coinsurance payable by the insured maximum 10 visits are allowed (as per applicable network); Initial investigations to include: · FBC and Platelets · Blood group, Rhesus status and antibodies · VDRL · MSU & urinalysis· Rubella serology· HIV · Hep C offered to high risk patients · GTT if high risk · FBS , random s or A1c for all due to high prevalence of diabetes in UAE Visits to include reviews, checks and tests in accordance with DHA Antenatal Care Protocols 8 ante-natal ultrasound scans | P10: Covered with 10% co-insurance up payable by the insured) Normal Delivery: Aggregate Limit Per Year: AED.12,500 Medically necessary Cesarean Section, Complications & Medically Necessary Termination: Aggregate Limit Per Year: AED. 15,000 | Q10: Covered up to AED 2,000/- with 20% Co Insurance | R10: Covered up to AED 1,500/- with 20% Co Insurance | S10: Covered up to AED 1,500/- with 20% Coins | T10: Coverage of a pregnant female is extended by the insurer to provide the same benefits for a newborn child of that female for a period up to 30 days from its date of birth. This cover is provided regardless of whether the newborn is eventually enrolled as a dependent member under the insurer’s policy. Covered under the mother’s card in event of Hospitalization, up to AED.150,000 PPPY | U10: Coverage of a pregnant female is extended by the insurer to provide the same benefits for a newborn child of that female for a period up to 30 days from its date of birth. This cover is provided regardless of whether the newborn is eventually enrolled as a dependent member under the insurer’s policy. Cover for 30 days from birth. BCG, Hepatitis B and neo-natal screening tests (Phenylketonuria (PKU), Congenital Hypothyroidism, sickle cell screening, congenital adrenal hyperplasia)
A11: Classic Plan-4R | B11: Calssic Plan-4R | C11: AED 150,000 | D11: UAE+Home country | E11: HN Basic Plus | F11: Covered up to AED 150 / night | G11: Covered up to 6 weeks (on reimbusement) | H11: 20% up to AED 50/- | I11: Covered up to AED 10,000/- with 10% Co Insurance (Branded) | J11: Hospital : Covered up to ABL with 20% Co Insurance on all OP Services - Clinics : Covered up to ABL with Nil Co Insurance | K11: Covered on Reimbursement up to AED 250 per night and a maximum of 10 nights. The Cash Indemnity claim must be submitted within 15 days after discharge from the hospital with a proof of hospitalization including a discharge summary. | L11: 20 sessions per member per annum | M11: Covered up to Maximum AED. 10,000 per person per annum (Settled on Reimbursement basis with no co-pay) | N11: Covered | O11: Covered subject to 10% coinsurance payable by the insured maximum 8 visits are allowed (as per applicable network); Initial investigations to include: · FBC and Platelets · Blood group, Rhesus status and antibodies · VDRL · MSU & urinalysis· Rubella serology· HIV · Hep C offered to high risk patients · GTT if high risk · FBS , random s or A1c for all due to high prevalence of diabetes in UAE Visits to include reviews, checks and tests in accordance with DHA Antenatal Care Protocols 8 ante-natal ultrasound scans | P11: Covered with 10% co-insurance up payable by the insured) Normal Delivery: Aggregate Limit Per Year: AED.10,000 Medically necessary Cesarean Section, Complications & Medically Necessary Termination: Aggregate Limit Per Year: AED. 10,000 | Q11: Covered up to AED 1,500/- with 20% Co Insurance | R11: Covered up to AED 1,500/- with 20% Co Insurance | S11: Covered up to AED 1,500/- with 20% Coins | T11: Coverage of a pregnant female is extended by the insurer to provide the same benefits for a newborn child of that female for a period up to 30 days from its date of birth. This cover is provided regardless of whether the newborn is eventually enrolled as a dependent member under the insurer’s policy. Covered under the mother’s card in event of Hospitalization, up to AED.150,000 PPPY | U11: Coverage of a pregnant female is extended by the insurer to provide the same benefits for a newborn child of that female for a period up to 30 days from its date of birth. This cover is provided regardless of whether the newborn is eventually enrolled as a dependent member under the insurer’s policy. Cover for 30 days from birth. BCG, Hepatitis B and neo-natal screening tests (Phenylketonuria (PKU), Congenital Hypothyroidism, sickle cell screening, congenital adrenal hyperplasia)
A12: Prime Plan-1-AUH | B12: Prime Plan-1-AUH | C12: AED 1,000,000 | D12: Worldwide | E12: HN Exclusive | F12: Covered to AED 450 / night | G12: Covered | H12: AED 50/- | I12: Covered up to AED 15,000 with Nil Insurance (Branded) | J12: 100% Covered | K12: Covered on Reimbursement up to AED 300 per night and a maximum of 10 nights. The Cash Indemnity claim must be submitted within 15 days after discharge from the hospital with a proof of hospitalization including a discharge summary. | L12: 100% Covered | M12: Covered up to Maximum AED. 20,000 per person per annum (Settled on Reimbursement basis with no co-pay) | N12: Covered | O12: covered up to the Annual Limit of the policy subject to the same deductible in the selected plan on consultation | P12: Inside Emirate of Abu Dhabi : Covered up to the Annual Limit of the policy ( In-Patient & Out-Patient) Delivery inside Emirate of Abu Dhabi is subject to a deductible of AED 500/- as per HAAD law Outside Emirate of Abu Dhabi (within UAE): -Normal Delivery is covered up to AED 10,000/-, C-Section and maternity complications are covered up to AED 12,000/-, Medical Emergency related to Maternity is covered up to AED 150,000/- | Q12: Covered up to AED 5,000/- with 20% Co Insurance | R12: Covered up to AED 2,500/- with 20% Co Insurance | S12: Covered up to AED 5,000/- with 20% Coins | T12: Covered as per DOH Abu Dhabi guidelines | U12: Vaccination for Children (as per MOH, UAE) Inside Network : Covered 100% at Actual Cost Outside Network : Covered on UCR Basis.
... A17: Classic Plan-4-AUH | B17: Calssic Plan-4-AUH | C17: AED 250,000 | D17: UAE+Home country | E17: HN Basic Plus | F17: Covered up to AED 150 / night | G17: Covered | H17: AED 50/- | I17: Covered up to AED 10,000 with Nil Insurance (Branded) | J17: 100% Covered | K17: Covered on Reimbursement up to AED 250 per night and a maximum of 10 nights. The Cash Indemnity claim must be submitted within 15 days after discharge from the hospital with a proof of hospitalization including a discharge summary. | L17: 100% Covered | M17: Covered up to Maximum AED. 10,000 per person per annum (Settled on Reimbursement basis with no co-pay) | N17: Covered | O17: covered up to the Annual Limit of the policy subject to the same deductible in the selected plan on consultation | P17: Inside Emirate of Abu Dhabi : Covered up to the Annual Limit of the policy ( In-Patient & Out-Patient) Delivery inside Emirate of Abu Dhabi is subject to a deductible of AED 500/- as per HAAD law Outside Emirate of Abu Dhabi (within UAE): -Normal Delivery is covered up to AED 10,000/-, C-Section and maternity complications are covered up to AED 12,000/-, Medical Emergency related to Maternity is covered up to AED 150,000/- | Q17: Covered up to AED 1,500/- with 20% Co Insurance | R17: Covered up to AED 1,500/- with 20% Co Insurance | S17: Covered up to AED 1,500/- with 20% Coins | T17: Covered as per DOH Abu Dhabi guidelines | U17: Vaccination for Children (as per MOH, UAE) Inside Network : Covered 100% at Actual Cost Outside Network : Covered on UCR Basis.
D20: Enhanced | E20: Dental Benefit: •Routine oral examination and routine cleaning of teeth. Once only per policy year. •Extraction (removal of teeth) on the recommendation of a dentist. •Filling of decayed or fractured teeth on the recommendation of a dentist. •Dental x-rays when needed to diagnose and treat a covered dental condition. •General anesthetics, when medically necessary and in connection with a covered dental procedure. •Endodontic treatment, including root canal therapy. •Surgical Interventions •Prescribed Drugs related to the above treatment
D21: Basic | E21: Dental Benefit: Dental consultation, Extraction, Fillings, Root Canal Treatment, Scaling, x-rays, Antibiotics and prophylaxis)
E38: Education and all types of training institutes (Schools, universities and academic institutions), | F38: Reffer to HO UW
E39: Medical Service Providers | F39: Reffer to HO UW
E40: Driving Institutes or similar professions (including Taxi Companies & Transport companies) | F40: Reffer to HO UW
E41: Military Services | F41: Reffer to HO UW
E42: Associations of any kind | F42: Reffer to HO UW
E43: Legal Consultants | F43: Reffer to HO UW
E44: Banking & Financial institutions | F44: Reffer to HO UW
E45: Insurance/ TPA | F45: Reffer to HO UW
E46: Others | F46: Please Proceed

Sheet Not Used
P1: Premier | Q1: 0.12
F2: HN Exclusive | G2: 0.2 | P2: HN Std Plus | Q2: 0.07
F3: HN Advantage | G3: -0.15 | P3: HN Std | Q3: 0.07
P4: HN Basic Plus | Q4: 0.08
A5: Plan Name | B5: Network | C5: Age Band | D5: Gender | E5: Uniqe ID | F5: NRP - R | G5: Maternity Premium | H5: Dental Premium | I5: NRP - R without Dental & Maternity | K5: Plan Name | L5: Network | M5: Age Band | N5: Gender | O5: Uniqe ID | P5: NRP For Open Network | Q5: Dental Premium | R5: Maternity Premium | S5: NRP without Dental & Maternity
A6: Not Applicable | B6: HN Exclusive | C6: 00-17 | D6: Male | E6: =CONCATENATE(A6," ",B6," ",C6) -> Not Applicable HN Exclusive 00-17 | F6: =F20+(F20*$G$2) -> 4840 | G6: =G20+(G20*$G$2) -> 0 | H6: =H20+(H20*$G$2) -> 2160 | I6: =F6-G6 -> 4840 | K6: Prime Plan-1 | L6: HN Exclusive | M6: 00-17 | N6: Male | O6: =CONCATENATE(K6," ",L6," ",M6) -> Prime Plan-1 HN Exclusive 00-17 | P6: =F6+(F6*$Q$1) -> 5421 | Q6: =G6+(G6*$Q$1) -> 0 | R6: =H6+(H6*$Q$1) -> 2419 | S6: =P6-Q6 -> 5421
A7: Not Applicable | B7: HN Exclusive | C7: 18-35 | D7: Male | E7: =CONCATENATE(A7," ",B7," ",C7) -> Not Applicable HN Exclusive 18-35 | F7: =F21+(F21*$G$2) -> 5549 | G7: =G21+(G21*$G$2) -> 300 | H7: =H21+(H21*$G$2) -> 2160 | I7: =F7-G7 -> 5249 | K7: Prime Plan-1 | L7: HN Exclusive | M7: 18-35 | N7: Male | O7: =CONCATENATE(K7," ",L7," ",M7) -> Prime Plan-1 HN Exclusive 18-35 | P7: =F7+(F7*$Q$1) -> 6215 | Q7: =G7+(G7*$Q$1) -> 336 | R7: =H7+(H7*$Q$1) -> 2419 | S7: =P7-Q7 -> 5879
A8: Not Applicable | B8: HN Exclusive | C8: 36-45 | D8: Male | E8: =CONCATENATE(A8," ",B8," ",C8) -> Not Applicable HN Exclusive 36-45 | F8: =F22+(F22*$G$2) -> 6521 | G8: =G22+(G22*$G$2) -> 420 | H8: =H22+(H22*$G$2) -> 2160 | I8: =F8-G8 -> 6101 | K8: Prime Plan-1 | L8: HN Exclusive | M8: 36-45 | N8: Male | O8: =CONCATENATE(K8," ",L8," ",M8) -> Prime Plan-1 HN Exclusive 36-45 | P8: =F8+(F8*$Q$1) -> 7304 | Q8: =G8+(G8*$Q$1) -> 470 | R8: =H8+(H8*$Q$1) -> 2419 | S8: =P8-Q8 -> 6834
A9: Not Applicable | B9: HN Exclusive | C9: 46-55 | D9: Male | E9: =CONCATENATE(A9," ",B9," ",C9) -> Not Applicable HN Exclusive 46-55 | F9: =F23+(F23*$G$2) -> 11136 | G9: =G23+(G23*$G$2) -> 420 | H9: =H23+(H23*$G$2) -> 2160 | I9: =F9-G9 -> 10716 | K9: Prime Plan-1 | L9: HN Exclusive | M9: 46-55 | N9: Male | O9: =CONCATENATE(K9," ",L9," ",M9) -> Prime Plan-1 HN Exclusive 46-55 | P9: =F9+(F9*$Q$1) -> 12472 | Q9: =G9+(G9*$Q$1) -> 470 | R9: =H9+(H9*$Q$1) -> 2419 | S9: =P9-Q9 -> 12002
A10: Not Applicable | B10: HN Exclusive | C10: 56-59 | D10: Male | E10: =CONCATENATE(A10," ",B10," ",C10) -> Not Applicable HN Exclusive 56-59 | F10: =F24+(F24*$G$2) -> 13790 | G10: =G24+(G24*$G$2) -> 420 | H10: =H24+(H24*$G$2) -> 2160 | I10: =F10-G10 -> 13370 | K10: Prime Plan-1 | L10: HN Exclusive | M10: 56-59 | N10: Male | O10: =CONCATENATE(K10," ",L10," ",M10) -> Prime Plan-1 HN Exclusive 56-59 | P10: =F10+(F10*$Q$1) -> 15445 | Q10: =G10+(G10*$Q$1) -> 470 | R10: =H10+(H10*$Q$1) -> 2419 | S10: =P10-Q10 -> 14975
A11: Not Applicable | B11: HN Exclusive | C11: 60 - 65 | D11: Male | E11: =CONCATENATE(A11," ",B11," ",C11) -> Not Applicable HN Exclusive 60 - 65 | F11: =F25+(F25*$G$2) -> 19811 | G11: =G25+(G25*$G$2) -> 420 | H11: =H25+(H25*$G$2) -> 2160 | I11: =F11-G11 -> 19391 | K11: Prime Plan-1 | L11: HN Exclusive | M11: 60 - 65 | N11: Male | O11: =CONCATENATE(K11," ",L11," ",M11) -> Prime Plan-1 HN Exclusive 60 - 65 | P11: =F11+(F11*$Q$1) -> 22188 | Q11: =G11+(G11*$Q$1) -> 470 | R11: =H11+(H11*$Q$1) -> 2419 | S11: =P11-Q11 -> 21718
A12: Not Applicable | B12: HN Exclusive | C12: 66 and above | D12: Male | E12: =CONCATENATE(A12," ",B12," ",C12) -> Not Applicable HN Exclusive 66 and above | F12: =F26+(F26*$G$2) -> 30845 | G12: =G26+(G26*$G$2) -> 420 | H12: =H26+(H26*$G$2) -> 2160 | I12: =F12-G12 -> 30425 | K12: Prime Plan-1 | L12: HN Exclusive | M12: 66 and above | N12: Male | O12: =CONCATENATE(K12," ",L12," ",M12) -> Prime Plan-1 HN Exclusive 66 and above | P12: =F12+(F12*$Q$1) -> 34546 | Q12: =G12+(G12*$Q$1) -> 470 | R12: =H12+(H12*$Q$1) -> 2419 | S12: =P12-Q12 -> 34076
A13: Not Applicable | B13: HN Exclusive | C13: 00-17 | D13: Female | E13: =CONCATENATE(A13," ",B13," ",C13) -> Not Applicable HN Exclusive 00-17 | F13: =F27+(F27*$G$2) -> 5081 | G13: =G27+(G27*$G$2) -> 420 | H13: =H27+(H27*$G$2) -> 2160 | I13: =F13 -> 5081 | K13: Prime Plan-1 | L13: HN Exclusive | M13: 00-17 | N13: Female | O13: =CONCATENATE(K13," ",L13," ",M13) -> Prime Plan-1 HN Exclusive 00-17 | P13: =F13+(F13*$Q$1) -> 5691 | Q13: =G13+(G13*$Q$1) -> 470 | R13: =H13+(H13*$Q$1) -> 2419 | S13: =P13-Q13 -> 5221
A14: Not Applicable | B14: HN Exclusive | C14: 18-35 | D14: Female | E14: =CONCATENATE(A14," ",B14," ",C14) -> Not Applicable HN Exclusive 18-35 | F14: =F28+(F28*$G$2) -> 8202 | G14: =G28+(G28*$G$2) -> 420 | H14: =H28+(H28*$G$2) -> 2160 | I14: =F14-H14 -> 6042 | K14: Prime Plan-1 | L14: HN Exclusive | M14: 18-35 | N14: Female | O14: =CONCATENATE(K14," ",L14," ",M14) -> Prime Plan-1 HN Exclusive 18-35 | P14: =F14+(F14*$Q$1) -> 9186 | Q14: =G14+(G14*$Q$1) -> 470 | R14: =H14+(H14*$Q$1) -> 2419 | S14: =P14-Q14 -> 8716
A15: Not Applicable | B15: HN Exclusive | C15: 36-45 | D15: Female | E15: =CONCATENATE(A15," ",B15," ",C15) -> Not Applicable HN Exclusive 36-45 | F15: =F29+(F29*$G$2) -> 9223 | G15: =G29+(G29*$G$2) -> 420 | H15: =H29+(H29*$G$2) -> 2160 | I15: =F15-H15 -> 7063 | K15: Prime Plan-1 | L15: HN Exclusive | M15: 36-45 | N15: Female | O15: =CONCATENATE(K15," ",L15," ",M15) -> Prime Plan-1 HN Exclusive 36-45 | P15: =F15+(F15*$Q$1) -> 10330 | Q15: =G15+(G15*$Q$1) -> 470 | R15: =H15+(H15*$Q$1) -> 2419 | S15: =P15-Q15 -> 9860
A16: Not Applicable | B16: HN Exclusive | C16: 46-55 | D16: Female | E16: =CONCATENATE(A16," ",B16," ",C16) -> Not Applicable HN Exclusive 46-55 | F16: =F30+(F30*$G$2) -> 12683 | G16: =G30+(G30*$G$2) -> 420 | H16: =H30+(H30*$G$2) -> 2160 | I16: =F16 -> 12683 | K16: Prime Plan-1 | L16: HN Exclusive | M16: 46-55 | N16: Female | O16: =CONCATENATE(K16," ",L16," ",M16) -> Prime Plan-1 HN Exclusive 46-55 | P16: =F16+(F16*$Q$1) -> 14205 | Q16: =G16+(G16*$Q$1) -> 470 | R16: =H16+(H16*$Q$1) -> 2419 | S16: =P16-Q16 -> 13735
A17: Not Applicable | B17: HN Exclusive | C17: 56-59 | D17: Female | E17: =CONCATENATE(A17," ",B17," ",C17) -> Not Applicable HN Exclusive 56-59 | F17: =F31+(F31*$G$2) -> 15865 | G17: =G31+(G31*$G$2) -> 420 | H17: =H31+(H31*$G$2) -> 2160 | I17: =F17 -> 15865 | K17: Prime Plan-1 | L17: HN Exclusive | M17: 56-59 | N17: Female | O17: =CONCATENATE(K17," ",L17," ",M17) -> Prime Plan-1 HN Exclusive 56-59 | P17: =F17+(F17*$Q$1) -> 17769 | Q17: =G17+(G17*$Q$1) -> 470 | R17: =H17+(H17*$Q$1) -> 2419 | S17: =P17-Q17 -> 17299
A18: Not Applicable | B18: HN Exclusive | C18: 60 - 65 | D18: Female | E18: =CONCATENATE(A18," ",B18," ",C18) -> Not Applicable HN Exclusive 60 - 65 | F18: =F32+(F32*$G$2) -> 20801 | G18: =G32+(G32*$G$2) -> 420 | H18: =H32+(H32*$G$2) -> 2160 | I18: =F18 -> 20801 | K18: Prime Plan-1 | L18: HN Exclusive | M18: 60 - 65 | N18: Female | O18: =CONCATENATE(K18," ",L18," ",M18) -> Prime Plan-1 HN Exclusive 60 - 65 | P18: =F18+(F18*$Q$1) -> 23297 | Q18: =G18+(G18*$Q$1) -> 470 | R18: =H18+(H18*$Q$1) -> 2419 | S18: =P18-Q18 -> 22827
A19: Not Applicable | B19: HN Exclusive | C19: 66 and above | D19: Female | E19: =CONCATENATE(A19," ",B19," ",C19) -> Not Applicable HN Exclusive 66 and above | F19: =F33+(F33*$G$2) -> 32387 | G19: =G33+(G33*$G$2) -> 420 | H19: =H33+(H33*$G$2) -> 2160 | I19: =F19 -> 32387 | K19: Prime Plan-1 | L19: HN Exclusive | M19: 66 and above | N19: Female | O19: =CONCATENATE(K19," ",L19," ",M19) -> Prime Plan-1 HN Exclusive 66 and above | P19: =F19+(F19*$Q$1) -> 36273 | Q19: =G19+(G19*$Q$1) -> 470 | R19: =H19+(H19*$Q$1) -> 2419 | S19: =P19-Q19 -> 35803
A20: Not Applicable | B20: HN Premier | C20: 00-17 | D20: Male | E20: =CONCATENATE(A20," ",B20," ",C20) -> Not Applicable HN Premier 00-17 | F20: 4033 | H20: 1800 | I20: =F20-G20 -> 4033 | K20: Prime Plan-2 | L20: HN Premier | M20: 00-17 | N20: Male | O20: =CONCATENATE(K20," ",L20," ",M20) -> Prime Plan-2 HN Premier 00-17 | P20: =F20+(F20*$Q$1) -> 4517 | Q20: =G20+(G20*$Q$1) -> 0 | R20: =H20+(H20*$Q$1) -> 2016 | S20: =P20-Q20 -> 4517
A21: Not Applicable | B21: HN Premier | C21: 18-35 | D21: Male | E21: =CONCATENATE(A21," ",B21," ",C21) -> Not Applicable HN Premier 18-35 | F21: 4624 | G21: 250 | H21: 1800 | I21: =F21-G21 -> 4374 | K21: Prime Plan-2 | L21: HN Premier | M21: 18-35 | N21: Male | O21: =CONCATENATE(K21," ",L21," ",M21) -> Prime Plan-2 HN Premier 18-35 | P21: =F21+(F21*$Q$1) -> 5179 | Q21: =G21+(G21*$Q$1) -> 280 | R21: =H21+(H21*$Q$1) -> 2016 | S21: =P21-Q21 -> 4899
A22: Not Applicable | B22: HN Premier | C22: 36-45 | D22: Male | E22: =CONCATENATE(A22," ",B22," ",C22) -> Not Applicable HN Premier 36-45 | F22: 5434 | G22: 350 | H22: 1800 | I22: =F22-G22 -> 5084 | K22: Prime Plan-2 | L22: HN Premier | M22: 36-45 | N22: Male | O22: =CONCATENATE(K22," ",L22," ",M22) -> Prime Plan-2 HN Premier 36-45 | P22: =F22+(F22*$Q$1) -> 6086 | Q22: =G22+(G22*$Q$1) -> 392 | R22: =H22+(H22*$Q$1) -> 2016 | S22: =P22-Q22 -> 5694
A23: Not Applicable | B23: HN Premier | C23: 46-55 | D23: Male | E23: =CONCATENATE(A23," ",B23," ",C23) -> Not Applicable HN Premier 46-55 | F23: 9280 | G23: 350 | H23: 1800 | I23: =F23-G23 -> 8930 | K23: Prime Plan-2 | L23: HN Premier | M23: 46-55 | N23: Male | O23: =CONCATENATE(K23," ",L23," ",M23) -> Prime Plan-2 HN Premier 46-55 | P23: =F23+(F23*$Q$1) -> 10394 | Q23: =G23+(G23*$Q$1) -> 392 | R23: =H23+(H23*$Q$1) -> 2016 | S23: =P23-Q23 -> 10002
A24: Not Applicable | B24: HN Premier | C24: 56-59 | D24: Male | E24: =CONCATENATE(A24," ",B24," ",C24) -> Not Applicable HN Premier 56-59 | F24: 11492 | G24: 350 | H24: 1800 | I24: =F24-G24 -> 11142 | K24: Prime Plan-2 | L24: HN Premier | M24: 56-59 | N24: Male | O24: =CONCATENATE(K24," ",L24," ",M24) -> Prime Plan-2 HN Premier 56-59 | P24: =F24+(F24*$Q$1) -> 12871 | Q24: =G24+(G24*$Q$1) -> 392 | R24: =H24+(H24*$Q$1) -> 2016 | S24: =P24-Q24 -> 12479
A25: Not Applicable | B25: HN Premier | C25: 60 - 65 | D25: Male | E25: =CONCATENATE(A25," ",B25," ",C25) -> Not Applicable HN Premier 60 - 65 | F25: 16509 | G25: 350 | H25: 1800 | I25: =F25-G25 -> 16159 | K25: Prime Plan-2 | L25: HN Premier | M25: 60 - 65 | N25: Male | O25: =CONCATENATE(K25," ",L25," ",M25) -> Prime Plan-2 HN Premier 60 - 65 | P25: =F25+(F25*$Q$1) -> 18490 | Q25: =G25+(G25*$Q$1) -> 392 | R25: =H25+(H25*$Q$1) -> 2016 | S25: =P25-Q25 -> 18098
A26: Not Applicable | B26: HN Premier | C26: 66 and above | D26: Male | E26: =CONCATENATE(A26," ",B26," ",C26) -> Not Applicable HN Premier 66 and above | F26: 25704 | G26: 350 | H26: 1800 | I26: =F26-G26 -> 25354 | K26: Prime Plan-2 | L26: HN Premier | M26: 66 and above | N26: Male | O26: =CONCATENATE(K26," ",L26," ",M26) -> Prime Plan-2 HN Premier 66 and above | P26: =F26+(F26*$Q$1) -> 28788 | Q26: =G26+(G26*$Q$1) -> 392 | R26: =H26+(H26*$Q$1) -> 2016 | S26: =P26-Q26 -> 28396
A27: Not Applicable | B27: HN Premier | C27: 00-17 | D27: Female | E27: =CONCATENATE(A27," ",B27," ",C27) -> Not Applicable HN Premier 00-17 | F27: 4234 | G27: 350 | H27: 1800 | I27: =F27 -> 4234 | K27: Prime Plan-2 | L27: HN Premier | M27: 00-17 | N27: Female | O27: =CONCATENATE(K27," ",L27," ",M27) -> Prime Plan-2 HN Premier 00-17 | P27: =F27+(F27*$Q$1) -> 4742 | Q27: 0 | R27: =H27+(H27*$Q$1) -> 2016 | S27: =P27-Q27 -> 4742
A28: Not Applicable | B28: HN Premier | C28: 18-35 | D28: Female | E28: =CONCATENATE(A28," ",B28," ",C28) -> Not Applicable HN Premier 18-35 | F28: 6835 | G28: 350 | H28: 1800 | I28: =F28-H28 -> 5035 | K28: Prime Plan-2 | L28: HN Premier | M28: 18-35 | N28: Female | O28: =CONCATENATE(K28," ",L28," ",M28) -> Prime Plan-2 HN Premier 18-35 | P28: =F28+(F28*$Q$1) -> 7655 | Q28: =G28+(G28*$Q$1) -> 392 | R28: =H28+(H28*$Q$1) -> 2016 | S28: =P28-Q28 -> 7263
A29: Not Applicable | B29: HN Premier | C29: 36-45 | D29: Female | E29: =CONCATENATE(A29," ",B29," ",C29) -> Not Applicable HN Premier 36-45 | F29: 7686 | G29: 350 | H29: 1800 | I29: =F29-H29 -> 5886 | K29: Prime Plan-2 | L29: HN Premier | M29: 36-45 | N29: Female | O29: =CONCATENATE(K29," ",L29," ",M29) -> Prime Plan-2 HN Premier 36-45 | P29: =F29+(F29*$Q$1) -> 8608 | Q29: =G29+(G29*$Q$1) -> 392 | R29: =H29+(H29*$Q$1) -> 2016 | S29: =P29-Q29 -> 8216
A30: Not Applicable | B30: HN Premier | C30: 46-55 | D30: Female | E30: =CONCATENATE(A30," ",B30," ",C30) -> Not Applicable HN Premier 46-55 | F30: 10569 | G30: 350 | H30: 1800 | I30: =F30 -> 10569 | K30: Prime Plan-2 | L30: HN Premier | M30: 46-55 | N30: Female | O30: =CONCATENATE(K30," ",L30," ",M30) -> Prime Plan-2 HN Premier 46-55 | P30: =F30+(F30*$Q$1) -> 11837 | Q30: =G30+(G30*$Q$1) -> 392 | R30: =H30+(H30*$Q$1) -> 2016 | S30: =P30-Q30 -> 11445
A31: Not Applicable | B31: HN Premier | C31: 56-59 | D31: Female | E31: =CONCATENATE(A31," ",B31," ",C31) -> Not Applicable HN Premier 56-59 | F31: 13221 | G31: 350 | H31: 1800 | I31: =F31 -> 13221 | K31: Prime Plan-2 | L31: HN Premier | M31: 56-59 | N31: Female | O31: =CONCATENATE(K31," ",L31," ",M31) -> Prime Plan-2 HN Premier 56-59 | P31: =F31+(F31*$Q$1) -> 14808 | Q31: =G31+(G31*$Q$1) -> 392 | R31: =H31+(H31*$Q$1) -> 2016 | S31: =P31-Q31 -> 14416
A32: Not Applicable | B32: HN Premier | C32: 60 - 65 | D32: Female | E32: =CONCATENATE(A32," ",B32," ",C32) -> Not Applicable HN Premier 60 - 65 | F32: 17334 | G32: 350 | H32: 1800 | I32: =F32 -> 17334 | K32: Prime Plan-2 | L32: HN Premier | M32: 60 - 65 | N32: Female | O32: =CONCATENATE(K32," ",L32," ",M32) -> Prime Plan-2 HN Premier 60 - 65 | P32: =F32+(F32*$Q$1) -> 19414 | Q32: =G32+(G32*$Q$1) -> 392 | R32: =H32+(H32*$Q$1) -> 2016 | S32: =P32-Q32 -> 19022
A33: Not Applicable | B33: HN Premier | C33: 66 and above | D33: Female | E33: =CONCATENATE(A33," ",B33," ",C33) -> Not Applicable HN Premier 66 and above | F33: 26989 | G33: 350 | H33: 1800 | I33: =F33 -> 26989 | K33: Prime Plan-2 | L33: HN Premier | M33: 66 and above | N33: Female | O33: =CONCATENATE(K33," ",L33," ",M33) -> Prime Plan-2 HN Premier 66 and above | P33: =F33+(F33*$Q$1) -> 30228 | Q33: =G33+(G33*$Q$1) -> 392 | R33: =H33+(H33*$Q$1) -> 2016 | S33: =P33-Q33 -> 29836
A34: Calssic Plan-1R | B34: HN Advantage | C34: 00-17 | D34: Male | E34: =CONCATENATE(A34," ",B34," ",C34) -> Calssic Plan-1R HN Advantage 00-17 | F34: =F20+(F20*$G$3) -> 3428 | G34: =G20+(G20*$G$3) -> 0 | H34: =H20+(H20*$G$3) -> 1530 | I34: =F34-G34 -> 3428 | K34: Calssic Plan-1 | L34: HN Advantage | M34: 00-17 | N34: Male | O34: =CONCATENATE(K34," ",L34," ",M34) -> Calssic Plan-1 HN Advantage 00-17 | P34: =F34+(F34*$Q$1) -> 3839 | Q34: =G34+(G34*$Q$1) -> 0 | R34: =H34+(H34*$Q$1) -> 1714 | S34: =P34 -> 3839
A35: Calssic Plan-1R | B35: HN Advantage | C35: 18-35 | D35: Male | E35: =CONCATENATE(A35," ",B35," ",C35) -> Calssic Plan-1R HN Advantage 18-35 | F35: =F21+(F21*$G$3) -> 3930 | G35: =G21+(G21*$G$3) -> 213 | H35: =H21+(H21*$G$3) -> 1530 | I35: =F35-G35 -> 3717 | K35: Calssic Plan-1 | L35: HN Advantage | M35: 18-35 | N35: Male | O35: =CONCATENATE(K35," ",L35," ",M35) -> Calssic Plan-1 HN Advantage 18-35 | P35: =F35+(F35*$Q$1) -> 4402 | Q35: =G35+(G35*$Q$1) -> 239 | R35: =H35+(H35*$Q$1) -> 1714 | S35: =P35 -> 4402
A36: Calssic Plan-1R | B36: HN Advantage | C36: 36-45 | D36: Male | E36: =CONCATENATE(A36," ",B36," ",C36) -> Calssic Plan-1R HN Advantage 36-45 | F36: =F22+(F22*$G$3) -> 4619 | G36: =G22+(G22*$G$3) -> 298 | H36: =H22+(H22*$G$3) -> 1530 | I36: =F36-G36 -> 4321 | K36: Calssic Plan-1 | L36: HN Advantage | M36: 36-45 | N36: Male | O36: =CONCATENATE(K36," ",L36," ",M36) -> Calssic Plan-1 HN Advantage 36-45 | P36: =F36+(F36*$Q$1) -> 5173 | Q36: =G36+(G36*$Q$1) -> 334 | R36: =H36+(H36*$Q$1) -> 1714 | S36: =P36 -> 5173
A37: Calssic Plan-1R | B37: HN Advantage | C37: 46-55 | D37: Male | E37: =CONCATENATE(A37," ",B37," ",C37) -> Calssic Plan-1R HN Advantage 46-55 | F37: =F23+(F23*$G$3) -> 7888 | G37: =G23+(G23*$G$3) -> 298 | H37: =H23+(H23*$G$3) -> 1530 | I37: =F37-G37 -> 7590 | K37: Calssic Plan-1 | L37: HN Advantage | M37: 46-55 | N37: Male | O37: =CONCATENATE(K37," ",L37," ",M37) -> Calssic Plan-1 HN Advantage 46-55 | P37: =F37+(F37*$Q$1) -> 8835 | Q37: =G37+(G37*$Q$1) -> 334 | R37: =H37+(H37*$Q$1) -> 1714 | S37: =P37 -> 8835
A38: Calssic Plan-1R | B38: HN Advantage | C38: 56-59 | D38: Male | E38: =CONCATENATE(A38," ",B38," ",C38) -> Calssic Plan-1R HN Advantage 56-59 | F38: =F24+(F24*$G$3) -> 9768 | G38: =G24+(G24*$G$3) -> 298 | H38: =H24+(H24*$G$3) -> 1530 | I38: =F38-G38 -> 9470 | K38: Calssic Plan-1 | L38: HN Advantage | M38: 56-59 | N38: Male | O38: =CONCATENATE(K38," ",L38," ",M38) -> Calssic Plan-1 HN Advantage 56-59 | P38: =F38+(F38*$Q$1) -> 10940 | Q38: =G38+(G38*$Q$1) -> 334 | R38: =H38+(H38*$Q$1) -> 1714 | S38: =P38 -> 10940
A39: Calssic Plan-1R | B39: HN Advantage | C39: 60 - 65 | D39: Male | E39: =CONCATENATE(A39," ",B39," ",C39) -> Calssic Plan-1R HN Advantage 60 - 65 | F39: =F25+(F25*$G$3) -> 14033 | G39: =G25+(G25*$G$3) -> 298 | H39: =H25+(H25*$G$3) -> 1530 | I39: =F39-G39 -> 13735 | K39: Calssic Plan-1 | L39: HN Advantage | M39: 60 - 65 | N39: Male | O39: =CONCATENATE(K39," ",L39," ",M39) -> Calssic Plan-1 HN Advantage 60 - 65 | P39: =F39+(F39*$Q$1) -> 15717 | Q39: =G39+(G39*$Q$1) -> 334 | R39: =H39+(H39*$Q$1) -> 1714 | S39: =P39 -> 15717
A40: Calssic Plan-1R | B40: HN Advantage | C40: 66 and above | D40: Male | E40: =CONCATENATE(A40," ",B40," ",C40) -> Calssic Plan-1R HN Advantage 66 and above | F40: =F26+(F26*$G$3) -> 21848 | G40: =G26+(G26*$G$3) -> 298 | H40: =H26+(H26*$G$3) -> 1530 | I40: =F40-G40 -> 21550 | K40: Calssic Plan-1 | L40: HN Advantage | M40: 66 and above | N40: Male | O40: =CONCATENATE(K40," ",L40," ",M40) -> Calssic Plan-1 HN Advantage 66 and above | P40: =F40+(F40*$Q$1) -> 24470 | Q40: =G40+(G40*$Q$1) -> 334 | R40: =H40+(H40*$Q$1) -> 1714 | S40: =P40 -> 24470
A41: Calssic Plan-1R | B41: HN Advantage | C41: 00-17 | D41: Female | E41: =CONCATENATE(A41," ",B41," ",C41) -> Calssic Plan-1R HN Advantage 00-17 | F41: =F27+(F27*$G$3) -> 3599 | G41: =G27+(G27*$G$3) -> 298 | H41: =H27+(H27*$G$3) -> 1530 | I41: =F41 -> 3599 | K41: Calssic Plan-1 | L41: HN Advantage | M41: 00-17 | N41: Female | O41: =CONCATENATE(K41," ",L41," ",M41) -> Calssic Plan-1 HN Advantage 00-17 | P41: =F41+(F41*$Q$1) -> 4031 | Q41: =G41+(G41*$Q$1) -> 334 | R41: =H41+(H41*$Q$1) -> 1714 | S41: =P41 -> 4031
A42: Calssic Plan-1R | B42: HN Advantage | C42: 18-35 | D42: Female | E42: =CONCATENATE(A42," ",B42," ",C42) -> Calssic Plan-1R HN Advantage 18-35 | F42: =F28+(F28*$G$3) -> 5810 | G42: =G28+(G28*$G$3) -> 298 | H42: =H28+(H28*$G$3) -> 1530 | I42: =F42-H42 -> 4280 | K42: Calssic Plan-1 | L42: HN Advantage | M42: 18-35 | N42: Female | O42: =CONCATENATE(K42," ",L42," ",M42) -> Calssic Plan-1 HN Advantage 18-35 | P42: =F42+(F42*$Q$1) -> 6507 | Q42: =G42+(G42*$Q$1) -> 334 | R42: =H42+(H42*$Q$1) -> 1714 | S42: =P42 -> 6507
A43: Calssic Plan-1R | B43: HN Advantage | C43: 36-45 | D43: Female | E43: =CONCATENATE(A43," ",B43," ",C43) -> Calssic Plan-1R HN Advantage 36-45 | F43: =F29+(F29*$G$3) -> 6533 | G43: =G29+(G29*$G$3) -> 298 | H43: =H29+(H29*$G$3) -> 1530 | I43: =F43-H43 -> 5003 | K43: Calssic Plan-1 | L43: HN Advantage | M43: 36-45 | N43: Female | O43: =CONCATENATE(K43," ",L43," ",M43) -> Calssic Plan-1 HN Advantage 36-45 | P43: =F43+(F43*$Q$1) -> 7317 | Q43: =G43+(G43*$Q$1) -> 334 | R43: =H43+(H43*$Q$1) -> 1714 | S43: =P43 -> 7317
A44: Calssic Plan-1R | B44: HN Advantage | C44: 46-55 | D44: Female | E44: =CONCATENATE(A44," ",B44," ",C44) -> Calssic Plan-1R HN Advantage 46-55 | F44: =F30+(F30*$G$3) -> 8984 | G44: =G30+(G30*$G$3) -> 298 | H44: =H30+(H30*$G$3) -> 1530 | I44: =F44 -> 8984 | K44: Calssic Plan-1 | L44: HN Advantage | M44: 46-55 | N44: Female | O44: =CONCATENATE(K44," ",L44," ",M44) -> Calssic Plan-1 HN Advantage 46-55 | P44: =F44+(F44*$Q$1) -> 10062 | Q44: =G44+(G44*$Q$1) -> 334 | R44: =H44+(H44*$Q$1) -> 1714 | S44: =P44 -> 10062
A45: Calssic Plan-1R | B45: HN Advantage | C45: 56-59 | D45: Female | E45: =CONCATENATE(A45," ",B45," ",C45) -> Calssic Plan-1R HN Advantage 56-59 | F45: =F31+(F31*$G$3) -> 11238 | G45: =G31+(G31*$G$3) -> 298 | H45: =H31+(H31*$G$3) -> 1530 | I45: =F45 -> 11238 | K45: Calssic Plan-1 | L45: HN Advantage | M45: 56-59 | N45: Female | O45: =CONCATENATE(K45," ",L45," ",M45) -> Calssic Plan-1 HN Advantage 56-59 | P45: =F45+(F45*$Q$1) -> 12587 | Q45: =G45+(G45*$Q$1) -> 334 | R45: =H45+(H45*$Q$1) -> 1714 | S45: =P45 -> 12587
A46: Calssic Plan-1R | B46: HN Advantage | C46: 60 - 65 | D46: Female | E46: =CONCATENATE(A46," ",B46," ",C46) -> Calssic Plan-1R HN Advantage 60 - 65 | F46: =F32+(F32*$G$3) -> 14734 | G46: =G32+(G32*$G$3) -> 298 | H46: =H32+(H32*$G$3) -> 1530 | I46: =F46 -> 14734 | K46: Calssic Plan-1 | L46: HN Advantage | M46: 60 - 65 | N46: Female | O46: =CONCATENATE(K46," ",L46," ",M46) -> Calssic Plan-1 HN Advantage 60 - 65 | P46: =F46+(F46*$Q$1) -> 16502 | Q46: =G46+(G46*$Q$1) -> 334 | R46: =H46+(H46*$Q$1) -> 1714 | S46: =P46 -> 16502
A47: Calssic Plan-1R | B47: HN Advantage | C47: 66 and above | D47: Female | E47: =CONCATENATE(A47," ",B47," ",C47) -> Calssic Plan-1R HN Advantage 66 and above | F47: =F33+(F33*$G$3) -> 22941 | G47: =G33+(G33*$G$3) -> 298 | H47: =H33+(H33*$G$3) -> 1530 | I47: =F47 -> 22941 | K47: Calssic Plan-1 | L47: HN Advantage | M47: 66 and above | N47: Female | O47: =CONCATENATE(K47," ",L47," ",M47) -> Calssic Plan-1 HN Advantage 66 and above | P47: =F47+(F47*$Q$1) -> 25694 | Q47: =G47+(G47*$Q$1) -> 334 | R47: =H47+(H47*$Q$1) -> 1714 | S47: =P47 -> 25694
A48: Calssic Plan-2R | B48: HN Standard Plus | C48: 00-17 | D48: Male | E48: =CONCATENATE(A48," ",B48," ",C48) -> Calssic Plan-2R HN Standard Plus 00-17 | F48: 3062 | G48: 300 | H48: 1200 | I48: =F48-G48 -> 2762 | K48: Calssic Plan-2 | L48: HN Standard Plus | M48: 00-17 | N48: Male | O48: =CONCATENATE(K48," ",L48," ",M48) -> Calssic Plan-2 HN Standard Plus 00-17 | P48: =F48+(F48*$Q$3) -> 3276 | Q48: =G48+(G48*$Q$3) -> 321 | R48: =H48+(H48*$Q$3) -> 1284 | S48: =P48-Q48 -> 2955
A49: Calssic Plan-2R | B49: HN Standard Plus | C49: 18-35 | D49: Male | E49: =CONCATENATE(A49," ",B49," ",C49) -> Calssic Plan-2R HN Standard Plus 18-35 | F49: 3203 | G49: 300 | H49: 1200 | I49: =F49-G49 -> 2903 | K49: Calssic Plan-2 | L49: HN Standard Plus | M49: 18-35 | N49: Male | O49: =CONCATENATE(K49," ",L49," ",M49) -> Calssic Plan-2 HN Standard Plus 18-35 | P49: =F49+(F49*$Q$3) -> 3427 | Q49: =G49+(G49*$Q$3) -> 321 | R49: =H49+(H49*$Q$3) -> 1284 | S49: =P49-Q49 -> 3106
A50: Calssic Plan-2R | B50: HN Standard Plus | C50: 36-45 | D50: Male | E50: =CONCATENATE(A50," ",B50," ",C50) -> Calssic Plan-2R HN Standard Plus 36-45 | F50: 3796 | G50: 300 | H50: 1200 | I50: =F50-G50 -> 3496 | K50: Calssic Plan-2 | L50: HN Standard Plus | M50: 36-45 | N50: Male | O50: =CONCATENATE(K50," ",L50," ",M50) -> Calssic Plan-2 HN Standard Plus 36-45 | P50: =F50+(F50*$Q$3) -> 4062 | Q50: =G50+(G50*$Q$3) -> 321 | R50: =H50+(H50*$Q$3) -> 1284 | S50: =P50-Q50 -> 3741
A51: Calssic Plan-2R | B51: HN Standard Plus | C51: 46-55 | D51: Male | E51: =CONCATENATE(A51," ",B51," ",C51) -> Calssic Plan-2R HN Standard Plus 46-55 | F51: 5914 | G51: 300 | H51: 1200 | I51: =F51-G51 -> 5614 | K51: Calssic Plan-2 | L51: HN Standard Plus | M51: 46-55 | N51: Male | O51: =CONCATENATE(K51," ",L51," ",M51) -> Calssic Plan-2 HN Standard Plus 46-55 | P51: =F51+(F51*$Q$3) -> 6328 | Q51: =G51+(G51*$Q$3) -> 321 | R51: =H51+(H51*$Q$3) -> 1284 | S51: =P51-Q51 -> 6007
A52: Calssic Plan-2R | B52: HN Standard Plus | C52: 56-59 | D52: Male | E52: =CONCATENATE(A52," ",B52," ",C52) -> Calssic Plan-2R HN Standard Plus 56-59 | F52: 8993 | G52: 300 | H52: 1200 | I52: =F52-G52 -> 8693 | K52: Calssic Plan-2 | L52: HN Standard Plus | M52: 56-59 | N52: Male | O52: =CONCATENATE(K52," ",L52," ",M52) -> Calssic Plan-2 HN Standard Plus 56-59 | P52: =F52+(F52*$Q$3) -> 9623 | Q52: =G52+(G52*$Q$3) -> 321 | R52: =H52+(H52*$Q$3) -> 1284 | S52: =P52-Q52 -> 9302
A53: Calssic Plan-2R | B53: HN Standard Plus | C53: 60 - 65 | D53: Male | E53: =CONCATENATE(A53," ",B53," ",C53) -> Calssic Plan-2R HN Standard Plus 60 - 65 | F53: 10260 | G53: 300 | H53: 1200 | I53: =F53-G53 -> 9960 | K53: Calssic Plan-2 | L53: HN Standard Plus | M53: 60 - 65 | N53: Male | O53: =CONCATENATE(K53," ",L53," ",M53) -> Calssic Plan-2 HN Standard Plus 60 - 65 | P53: =F53+(F53*$Q$3) -> 10978 | Q53: =G53+(G53*$Q$3) -> 321 | R53: =H53+(H53*$Q$3) -> 1284 | S53: =P53-Q53 -> 10657
A54: Calssic Plan-2R | B54: HN Standard Plus | C54: 66 and above | D54: Male | E54: =CONCATENATE(A54," ",B54," ",C54) -> Calssic Plan-2R HN Standard Plus 66 and above | F54: 12334 | G54: 300 | H54: 1200 | I54: =F54-G54 -> 12034 | K54: Calssic Plan-2 | L54: HN Standard Plus | M54: 66 and above | N54: Male | O54: =CONCATENATE(K54," ",L54," ",M54) -> Calssic Plan-2 HN Standard Plus 66 and above | P54: =F54+(F54*$Q$3) -> 13197 | Q54: =G54+(G54*$Q$3) -> 321 | R54: =H54+(H54*$Q$3) -> 1284 | S54: =P54-Q54 -> 12876
A55: Calssic Plan-2R | B55: HN Standard Plus | C55: 00-17 | D55: Female | E55: =CONCATENATE(A55," ",B55," ",C55) -> Calssic Plan-2R HN Standard Plus 00-17 | F55: 3430 | G55: 300 | H55: 1200 | I55: =F55 -> 3430 | K55: Calssic Plan-2 | L55: HN Standard Plus | M55: 00-17 | N55: Female | O55: =CONCATENATE(K55," ",L55," ",M55) -> Calssic Plan-2 HN Standard Plus 00-17 | P55: =F55+(F55*$Q$3) -> 3670 | Q55: =G55+(G55*$Q$3) -> 321 | R55: =H55+(H55*$Q$3) -> 1284 | S55: =P55-Q55 -> 3349
A56: Calssic Plan-2R | B56: HN Standard Plus | C56: 18-35 | D56: Female | E56: =CONCATENATE(A56," ",B56," ",C56) -> Calssic Plan-2R HN Standard Plus 18-35 | F56: 4907 | G56: 300 | H56: 1200 | I56: =F56-H56 -> 3707 | K56: Calssic Plan-2 | L56: HN Standard Plus | M56: 18-35 | N56: Female | O56: =CONCATENATE(K56," ",L56," ",M56) -> Calssic Plan-2 HN Standard Plus 18-35 | P56: =F56+(F56*$Q$3) -> 5250 | Q56: =G56+(G56*$Q$3) -> 321 | R56: =H56+(H56*$Q$3) -> 1284 | S56: =P56-Q56 -> 4929
A57: Calssic Plan-2R | B57: HN Standard Plus | C57: 36-45 | D57: Female | E57: =CONCATENATE(A57," ",B57," ",C57) -> Calssic Plan-2R HN Standard Plus 36-45 | F57: 5572 | G57: 300 | H57: 1200 | I57: =F57-H57 -> 4372 | K57: Calssic Plan-2 | L57: HN Standard Plus | M57: 36-45 | N57: Female | O57: =CONCATENATE(K57," ",L57," ",M57) -> Calssic Plan-2 HN Standard Plus 36-45 | P57: =F57+(F57*$Q$3) -> 5962 | Q57: =G57+(G57*$Q$3) -> 321 | R57: =H57+(H57*$Q$3) -> 1284 | S57: =P57-Q57 -> 5641
A58: Calssic Plan-2R | B58: HN Standard Plus | C58: 46-55 | D58: Female | E58: =CONCATENATE(A58," ",B58," ",C58) -> Calssic Plan-2R HN Standard Plus 46-55 | F58: 6953 | G58: 300 | H58: 1200 | I58: =F58 -> 6953 | K58: Calssic Plan-2 | L58: HN Standard Plus | M58: 46-55 | N58: Female | O58: =CONCATENATE(K58," ",L58," ",M58) -> Calssic Plan-2 HN Standard Plus 46-55 | P58: =F58+(F58*$Q$3) -> 7440 | Q58: =G58+(G58*$Q$3) -> 321 | R58: =H58+(H58*$Q$3) -> 1284 | S58: =P58-Q58 -> 7119
A59: Calssic Plan-2R | B59: HN Standard Plus | C59: 56-59 | D59: Female | E59: =CONCATENATE(A59," ",B59," ",C59) -> Calssic Plan-2R HN Standard Plus 56-59 | F59: 10072 | G59: 300 | H59: 1200 | I59: =F59 -> 10072 | K59: Calssic Plan-2 | L59: HN Standard Plus | M59: 56-59 | N59: Female | O59: =CONCATENATE(K59," ",L59," ",M59) -> Calssic Plan-2 HN Standard Plus 56-59 | P59: =F59+(F59*$Q$3) -> 10777 | Q59: =G59+(G59*$Q$3) -> 321 | R59: =H59+(H59*$Q$3) -> 1284 | S59: =P59-Q59 -> 10456
A60: Calssic Plan-2R | B60: HN Standard Plus | C60: 60 - 65 | D60: Female | E60: =CONCATENATE(A60," ",B60," ",C60) -> Calssic Plan-2R HN Standard Plus 60 - 65 | F60: 10260 | G60: 300 | H60: 1200 | I60: =F60 -> 10260 | K60: Calssic Plan-2 | L60: HN Standard Plus | M60: 60 - 65 | N60: Female | O60: =CONCATENATE(K60," ",L60," ",M60) -> Calssic Plan-2 HN Standard Plus 60 - 65 | P60: =F60+(F60*$Q$3) -> 10978 | Q60: =G60+(G60*$Q$3) -> 321 | R60: =H60+(H60*$Q$3) -> 1284 | S60: =P60-Q60 -> 10657
A61: Calssic Plan-2R | B61: HN Standard Plus | C61: 66 and above | D61: Female | E61: =CONCATENATE(A61," ",B61," ",C61) -> Calssic Plan-2R HN Standard Plus 66 and above | F61: 12334 | G61: 300 | H61: 1200 | I61: =F61 -> 12334 | K61: Calssic Plan-2 | L61: HN Standard Plus | M61: 66 and above | N61: Female | O61: =CONCATENATE(K61," ",L61," ",M61) -> Calssic Plan-2 HN Standard Plus 66 and above | P61: =F61+(F61*$Q$3) -> 13197 | Q61: =G61+(G61*$Q$3) -> 321 | R61: =H61+(H61*$Q$3) -> 1284 | S61: =P61-Q61 -> 12876
A62: Calssic Plan-3R | B62: HN Standard | C62: 00-17 | D62: Male | E62: =CONCATENATE(A62," ",B62," ",C62) -> Calssic Plan-3R HN Standard 00-17 | F62: 2310 | G62: 300 | H62: 1100 | I62: =F62-G62 -> 2010 | K62: Calssic Plan-3 | L62: HN Standard | M62: 00-17 | N62: Male | O62: =CONCATENATE(K62," ",L62," ",M62) -> Calssic Plan-3 HN Standard 00-17 | P62: =F62+(F62*$Q$3) -> 2472 | Q62: =G62+(G62*$Q$3) -> 321 | R62: =H62+(H62*$Q$3) -> 1177 | S62: =P62-Q62 -> 2151
A63: Calssic Plan-3R | B63: HN Standard | C63: 18-35 | D63: Male | E63: =CONCATENATE(A63," ",B63," ",C63) -> Calssic Plan-3R HN Standard 18-35 | F63: 2606 | G63: 300 | H63: 1100 | I63: =F63-G63 -> 2306 | K63: Calssic Plan-3 | L63: HN Standard | M63: 18-35 | N63: Male | O63: =CONCATENATE(K63," ",L63," ",M63) -> Calssic Plan-3 HN Standard 18-35 | P63: =F63+(F63*$Q$3) -> 2788 | Q63: =G63+(G63*$Q$3) -> 321 | R63: =H63+(H63*$Q$3) -> 1177 | S63: =P63-Q63 -> 2467
A64: Calssic Plan-3R | B64: HN Standard | C64: 36-45 | D64: Male | E64: =CONCATENATE(A64," ",B64," ",C64) -> Calssic Plan-3R HN Standard 36-45 | F64: 2968 | G64: 300 | H64: 1100 | I64: =F64-G64 -> 2668 | K64: Calssic Plan-3 | L64: HN Standard | M64: 36-45 | N64: Male | O64: =CONCATENATE(K64," ",L64," ",M64) -> Calssic Plan-3 HN Standard 36-45 | P64: =F64+(F64*$Q$3) -> 3176 | Q64: =G64+(G64*$Q$3) -> 321 | R64: =H64+(H64*$Q$3) -> 1177 | S64: =P64-Q64 -> 2855
A65: Calssic Plan-3R | B65: HN Standard | C65: 46-55 | D65: Male | E65: =CONCATENATE(A65," ",B65," ",C65) -> Calssic Plan-3R HN Standard 46-55 | F65: 4207 | G65: 300 | H65: 1100 | I65: =F65-G65 -> 3907 | K65: Calssic Plan-3 | L65: HN Standard | M65: 46-55 | N65: Male | O65: =CONCATENATE(K65," ",L65," ",M65) -> Calssic Plan-3 HN Standard 46-55 | P65: =F65+(F65*$Q$3) -> 4501 | Q65: =G65+(G65*$Q$3) -> 321 | R65: =H65+(H65*$Q$3) -> 1177 | S65: =P65-Q65 -> 4180
A66: Calssic Plan-3R | B66: HN Standard | C66: 56-59 | D66: Male | E66: =CONCATENATE(A66," ",B66," ",C66) -> Calssic Plan-3R HN Standard 56-59 | F66: 5678 | G66: 300 | H66: 1100 | I66: =F66-G66 -> 5378 | K66: Calssic Plan-3 | L66: HN Standard | M66: 56-59 | N66: Male | O66: =CONCATENATE(K66," ",L66," ",M66) -> Calssic Plan-3 HN Standard 56-59 | P66: =F66+(F66*$Q$3) -> 6075 | Q66: =G66+(G66*$Q$3) -> 321 | R66: =H66+(H66*$Q$3) -> 1177 | S66: =P66-Q66 -> 5754
A67: Calssic Plan-3R | B67: HN Standard | C67: 60 - 65 | D67: Male | E67: =CONCATENATE(A67," ",B67," ",C67) -> Calssic Plan-3R HN Standard 60 - 65 | F67: 7323 | G67: 300 | H67: 1100 | I67: =F67-G67 -> 7023 | K67: Calssic Plan-3 | L67: HN Standard | M67: 60 - 65 | N67: Male | O67: =CONCATENATE(K67," ",L67," ",M67) -> Calssic Plan-3 HN Standard 60 - 65 | P67: =F67+(F67*$Q$3) -> 7836 | Q67: =G67+(G67*$Q$3) -> 321 | R67: =H67+(H67*$Q$3) -> 1177 | S67: =P67-Q67 -> 7515
A68: Calssic Plan-3R | B68: HN Standard | C68: 66 and above | D68: Male | E68: =CONCATENATE(A68," ",B68," ",C68) -> Calssic Plan-3R HN Standard 66 and above | F68: 9702 | G68: 300 | H68: 1100 | I68: =F68-G68 -> 9402 | K68: Calssic Plan-3 | L68: HN Standard | M68: 66 and above | N68: Male | O68: =CONCATENATE(K68," ",L68," ",M68) -> Calssic Plan-3 HN Standard 66 and above | P68: =F68+(F68*$Q$3) -> 10381 | Q68: =G68+(G68*$Q$3) -> 321 | R68: =H68+(H68*$Q$3) -> 1177 | S68: =P68-Q68 -> 10060
A69: Calssic Plan-3R | B69: HN Standard | C69: 00-17 | D69: Female | E69: =CONCATENATE(A69," ",B69," ",C69) -> Calssic Plan-3R HN Standard 00-17 | F69: 2426 | G69: 300 | H69: 1100 | I69: =F69 -> 2426 | K69: Calssic Plan-3 | L69: HN Standard | M69: 00-17 | N69: Female | O69: =CONCATENATE(K69," ",L69," ",M69) -> Calssic Plan-3 HN Standard 00-17 | P69: =F69+(F69*$Q$3) -> 2596 | Q69: =G69+(G69*$Q$3) -> 321 | R69: =H69+(H69*$Q$3) -> 1177 | S69: =P69-Q69 -> 2275
A70: Calssic Plan-3R | B70: HN Standard | C70: 18-35 | D70: Female | E70: =CONCATENATE(A70," ",B70," ",C70) -> Calssic Plan-3R HN Standard 18-35 | F70: 3946 | G70: 300 | H70: 1100 | I70: =F70-H70 -> 2846 | K70: Calssic Plan-3 | L70: HN Standard | M70: 18-35 | N70: Female | O70: =CONCATENATE(K70," ",L70," ",M70) -> Calssic Plan-3 HN Standard 18-35 | P70: =F70+(F70*$Q$3) -> 4222 | Q70: =G70+(G70*$Q$3) -> 321 | R70: =H70+(H70*$Q$3) -> 1177 | S70: =P70-Q70 -> 3901
A71: Calssic Plan-3R | B71: HN Standard | C71: 36-45 | D71: Female | E71: =CONCATENATE(A71," ",B71," ",C71) -> Calssic Plan-3R HN Standard 36-45 | F71: 4326 | G71: 300 | H71: 1100 | I71: =F71-H71 -> 3226 | K71: Calssic Plan-3 | L71: HN Standard | M71: 36-45 | N71: Female | O71: =CONCATENATE(K71," ",L71," ",M71) -> Calssic Plan-3 HN Standard 36-45 | P71: =F71+(F71*$Q$3) -> 4629 | Q71: =G71+(G71*$Q$3) -> 321 | R71: =H71+(H71*$Q$3) -> 1177 | S71: =P71-Q71 -> 4308
A72: Calssic Plan-3R | B72: HN Standard | C72: 46-55 | D72: Female | E72: =CONCATENATE(A72," ",B72," ",C72) -> Calssic Plan-3R HN Standard 46-55 | F72: 5045 | G72: 300 | H72: 1100 | I72: =F72 -> 5045 | K72: Calssic Plan-3 | L72: HN Standard | M72: 46-55 | N72: Female | O72: =CONCATENATE(K72," ",L72," ",M72) -> Calssic Plan-3 HN Standard 46-55 | P72: =F72+(F72*$Q$3) -> 5398 | Q72: =G72+(G72*$Q$3) -> 321 | R72: =H72+(H72*$Q$3) -> 1177 | S72: =P72-Q72 -> 5077
A73: Calssic Plan-3R | B73: HN Standard | C73: 56-59 | D73: Female | E73: =CONCATENATE(A73," ",B73," ",C73) -> Calssic Plan-3R HN Standard 56-59 | F73: 6237 | G73: 300 | H73: 1100 | I73: =F73 -> 6237 | K73: Calssic Plan-3 | L73: HN Standard | M73: 56-59 | N73: Female | O73: =CONCATENATE(K73," ",L73," ",M73) -> Calssic Plan-3 HN Standard 56-59 | P73: =F73+(F73*$Q$3) -> 6674 | Q73: =G73+(G73*$Q$3) -> 321 | R73: =H73+(H73*$Q$3) -> 1177 | S73: =P73-Q73 -> 6353
A74: Calssic Plan-3R | B74: HN Standard | C74: 60 - 65 | D74: Female | E74: =CONCATENATE(A74," ",B74," ",C74) -> Calssic Plan-3R HN Standard 60 - 65 | F74: 7323 | G74: 300 | H74: 1100 | I74: =F74 -> 7323 | K74: Calssic Plan-3 | L74: HN Standard | M74: 60 - 65 | N74: Female | O74: =CONCATENATE(K74," ",L74," ",M74) -> Calssic Plan-3 HN Standard 60 - 65 | P74: =F74+(F74*$Q$3) -> 7836 | Q74: =G74+(G74*$Q$3) -> 321 | R74: =H74+(H74*$Q$3) -> 1177 | S74: =P74-Q74 -> 7515
A75: Calssic Plan-3R | B75: HN Standard | C75: 66 and above | D75: Female | E75: =CONCATENATE(A75," ",B75," ",C75) -> Calssic Plan-3R HN Standard 66 and above | F75: 9702 | G75: 300 | H75: 1100 | I75: =F75 -> 9702 | K75: Calssic Plan-3 | L75: HN Standard | M75: 66 and above | N75: Female | O75: =CONCATENATE(K75," ",L75," ",M75) -> Calssic Plan-3 HN Standard 66 and above | P75: =F75+(F75*$Q$3) -> 10381 | Q75: =G75+(G75*$Q$3) -> 321 | R75: =H75+(H75*$Q$3) -> 1177 | S75: =P75-Q75 -> 10060
A76: Calssic Plan-4R | B76: HN Basic Plus | C76: 00-17 | D76: Male | E76: =CONCATENATE(A76," ",B76," ",C76) -> Calssic Plan-4R HN Basic Plus 00-17 | F76: 1617 | G76: 210 | H76: 770 | I76: =F76-G76 -> 1407 | K76: Calssic Plan-4 | L76: HN Basic Plus | M76: 00-17 | N76: Male | O76: =CONCATENATE(K76," ",L76," ",M76) -> Calssic Plan-4 HN Basic Plus 00-17 | P76: =F76+(F76*$Q$4) -> 1746 | Q76: =G76+(G76*$Q$4) -> 227 | R76: =H76+(H76*$Q$4) -> 832 | S76: =P76-Q76 -> 1519
A77: Calssic Plan-4R | B77: HN Basic Plus | C77: 18-35 | D77: Male | E77: =CONCATENATE(A77," ",B77," ",C77) -> Calssic Plan-4R HN Basic Plus 18-35 | F77: 1824 | G77: 210 | H77: 770 | I77: =F77-G77 -> 1614 | K77: Calssic Plan-4 | L77: HN Basic Plus | M77: 18-35 | N77: Male | O77: =CONCATENATE(K77," ",L77," ",M77) -> Calssic Plan-4 HN Basic Plus 18-35 | P77: =F77+(F77*$Q$4) -> 1970 | Q77: =G77+(G77*$Q$4) -> 227 | R77: =H77+(H77*$Q$4) -> 832 | S77: =P77-Q77 -> 1743
A78: Calssic Plan-4R | B78: HN Basic Plus | C78: 36-45 | D78: Male | E78: =CONCATENATE(A78," ",B78," ",C78) -> Calssic Plan-4R HN Basic Plus 36-45 | F78: 2078 | G78: 210 | H78: 770 | I78: =F78-G78 -> 1868 | K78: Calssic Plan-4 | L78: HN Basic Plus | M78: 36-45 | N78: Male | O78: =CONCATENATE(K78," ",L78," ",M78) -> Calssic Plan-4 HN Basic Plus 36-45 | P78: =F78+(F78*$Q$4) -> 2244 | Q78: =G78+(G78*$Q$4) -> 227 | R78: =H78+(H78*$Q$4) -> 832 | S78: =P78-Q78 -> 2017
A79: Calssic Plan-4R | B79: HN Basic Plus | C79: 46-55 | D79: Male | E79: =CONCATENATE(A79," ",B79," ",C79) -> Calssic Plan-4R HN Basic Plus 46-55 | F79: 3495 | G79: 210 | H79: 770 | I79: =F79-G79 -> 3285 | K79: Calssic Plan-4 | L79: HN Basic Plus | M79: 46-55 | N79: Male | O79: =CONCATENATE(K79," ",L79," ",M79) -> Calssic Plan-4 HN Basic Plus 46-55 | P79: =F79+(F79*$Q$4) -> 3775 | Q79: =G79+(G79*$Q$4) -> 227 | R79: =H79+(H79*$Q$4) -> 832 | S79: =P79-Q79 -> 3548
A80: Calssic Plan-4R | B80: HN Basic Plus | C80: 56-59 | D80: Male | E80: =CONCATENATE(A80," ",B80," ",C80) -> Calssic Plan-4R HN Basic Plus 56-59 | F80: 3975 | G80: 210 | H80: 770 | I80: =F80-G80 -> 3765 | K80: Calssic Plan-4 | L80: HN Basic Plus | M80: 56-59 | N80: Male | O80: =CONCATENATE(K80," ",L80," ",M80) -> Calssic Plan-4 HN Basic Plus 56-59 | P80: =F80+(F80*$Q$4) -> 4293 | Q80: =G80+(G80*$Q$4) -> 227 | R80: =H80+(H80*$Q$4) -> 832 | S80: =P80-Q80 -> 4066
A81: Calssic Plan-4R | B81: HN Basic Plus | C81: 60 - 65 | D81: Male | E81: =CONCATENATE(A81," ",B81," ",C81) -> Calssic Plan-4R HN Basic Plus 60 - 65 | F81: 5126 | G81: 210 | H81: 770 | I81: =F81-G81 -> 4916 | K81: Calssic Plan-4 | L81: HN Basic Plus | M81: 60 - 65 | N81: Male | O81: =CONCATENATE(K81," ",L81," ",M81) -> Calssic Plan-4 HN Basic Plus 60 - 65 | P81: =F81+(F81*$Q$4) -> 5536 | Q81: =G81+(G81*$Q$4) -> 227 | R81: =H81+(H81*$Q$4) -> 832 | S81: =P81-Q81 -> 5309
A82: Calssic Plan-4R | B82: HN Basic Plus | C82: 66 and above | D82: Male | E82: =CONCATENATE(A82," ",B82," ",C82) -> Calssic Plan-4R HN Basic Plus 66 and above | F82: 6791 | G82: 210 | H82: 770 | I82: =F82-G82 -> 6581 | K82: Calssic Plan-4 | L82: HN Basic Plus | M82: 66 and above | N82: Male | O82: =CONCATENATE(K82," ",L82," ",M82) -> Calssic Plan-4 HN Basic Plus 66 and above | P82: =F82+(F82*$Q$4) -> 7334 | Q82: =G82+(G82*$Q$4) -> 227 | R82: =H82+(H82*$Q$4) -> 832 | S82: =P82-Q82 -> 7107
A83: Calssic Plan-4R | B83: HN Basic Plus | C83: 00-17 | D83: Female | E83: =CONCATENATE(A83," ",B83," ",C83) -> Calssic Plan-4R HN Basic Plus 00-17 | F83: 1698 | G83: 210 | H83: 770 | I83: =F83 -> 1698 | K83: Calssic Plan-4 | L83: HN Basic Plus | M83: 00-17 | N83: Female | O83: =CONCATENATE(K83," ",L83," ",M83) -> Calssic Plan-4 HN Basic Plus 00-17 | P83: =F83+(F83*$Q$4) -> 1834 | Q83: =G83+(G83*$Q$4) -> 227 | R83: =H83+(H83*$Q$4) -> 832 | S83: =P83-Q83 -> 1607
A84: Calssic Plan-4R | B84: HN Basic Plus | C84: 18-35 | D84: Female | E84: =CONCATENATE(A84," ",B84," ",C84) -> Calssic Plan-4R HN Basic Plus 18-35 | F84: 2912 | G84: 210 | H84: 770 | I84: =F84-H84 -> 2142 | K84: Calssic Plan-4 | L84: HN Basic Plus | M84: 18-35 | N84: Female | O84: =CONCATENATE(K84," ",L84," ",M84) -> Calssic Plan-4 HN Basic Plus 18-35 | P84: =F84+(F84*$Q$4) -> 3145 | Q84: =G84+(G84*$Q$4) -> 227 | R84: =H84+(H84*$Q$4) -> 832 | S84: =P84-Q84 -> 2918
A85: Calssic Plan-4R | B85: HN Basic Plus | C85: 36-45 | D85: Female | E85: =CONCATENATE(A85," ",B85," ",C85) -> Calssic Plan-4R HN Basic Plus 36-45 | F85: 3428 | G85: 210 | H85: 770 | I85: =F85-H85 -> 2658 | K85: Calssic Plan-4 | L85: HN Basic Plus | M85: 36-45 | N85: Female | O85: =CONCATENATE(K85," ",L85," ",M85) -> Calssic Plan-4 HN Basic Plus 36-45 | P85: =F85+(F85*$Q$4) -> 3702 | Q85: =G85+(G85*$Q$4) -> 227 | R85: =H85+(H85*$Q$4) -> 832 | S85: =P85-Q85 -> 3475
A86: Calssic Plan-4R | B86: HN Basic Plus | C86: 46-55 | D86: Female | E86: =CONCATENATE(A86," ",B86," ",C86) -> Calssic Plan-4R HN Basic Plus 46-55 | F86: 3932 | G86: 210 | H86: 770 | I86: =F86 -> 3932 | K86: Calssic Plan-4 | L86: HN Basic Plus | M86: 46-55 | N86: Female | O86: =CONCATENATE(K86," ",L86," ",M86) -> Calssic Plan-4 HN Basic Plus 46-55 | P86: =F86+(F86*$Q$4) -> 4247 | Q86: =G86+(G86*$Q$4) -> 227 | R86: =H86+(H86*$Q$4) -> 832 | S86: =P86-Q86 -> 4020
A87: Calssic Plan-4R | B87: HN Basic Plus | C87: 56-59 | D87: Female | E87: =CONCATENATE(A87," ",B87," ",C87) -> Calssic Plan-4R HN Basic Plus 56-59 | F87: 4366 | G87: 210 | H87: 770 | I87: =F87 -> 4366 | K87: Calssic Plan-4 | L87: HN Basic Plus | M87: 56-59 | N87: Female | O87: =CONCATENATE(K87," ",L87," ",M87) -> Calssic Plan-4 HN Basic Plus 56-59 | P87: =F87+(F87*$Q$4) -> 4715 | Q87: =G87+(G87*$Q$4) -> 227 | R87: =H87+(H87*$Q$4) -> 832 | S87: =P87-Q87 -> 4488
A88: Calssic Plan-4R | B88: HN Basic Plus | C88: 60 - 65 | D88: Female | E88: =CONCATENATE(A88," ",B88," ",C88) -> Calssic Plan-4R HN Basic Plus 60 - 65 | F88: 5126 | G88: 210 | H88: 770 | I88: =F88 -> 5126 | K88: Calssic Plan-4 | L88: HN Basic Plus | M88: 60 - 65 | N88: Female | O88: =CONCATENATE(K88," ",L88," ",M88) -> Calssic Plan-4 HN Basic Plus 60 - 65 | P88: =F88+(F88*$Q$4) -> 5536 | Q88: =G88+(G88*$Q$4) -> 227 | R88: =H88+(H88*$Q$4) -> 832 | S88: =P88-Q88 -> 5309
A89: Calssic Plan-4R | B89: HN Basic Plus | C89: 66 and above | D89: Female | E89: =CONCATENATE(A89," ",B89," ",C89) -> Calssic Plan-4R HN Basic Plus 66 and above | F89: 6791 | G89: 210 | H89: 770 | I89: =F89 -> 6791 | K89: Calssic Plan-4 | L89: HN Basic Plus | M89: 66 and above | N89: Female | O89: =CONCATENATE(K89," ",L89," ",M89) -> Calssic Plan-4 HN Basic Plus 66 and above | P89: =F89+(F89*$Q$4) -> 7334 | Q89: =G89+(G89*$Q$4) -> 227 | R89: =H89+(H89*$Q$4) -> 832 | S89: =P89-Q89 -> 7107
B93: Network | C93: Age Band | F93: NRP
B94: HN Exclusive | C94: [00-17] | F94: 4966
C95: [18-40] | F95: 5898
C96: [41-59] | F96: 9998
C97: [60-69] | F97: 20060
C98: 70-75] | F98: 26078
C99: [60+] | F99: 33902
C100: [00-17] | F100: 4966
C101: [18-40] | F101: 5898
C102: [41-59] | F102: 9998
C103: [60-69] | F103: 20060
...
